Workbook

Sheet 1. Capa
B2: DA ENGENHARIA AO CASO DE INVESTIMENTO
B3: Planta de doce de leite · 2024–2033 · modelo financeiro em padrão FP&A
B5: Projeto de conclusão de Engenharia de Alimentos (UNICAMP) relido como caso de investimento. A planilha original tem 27 abas de engenharia — balanço de massa, mapa de ocupação, APPCC — e nenhuma DRE. Este modelo não refaz a engenharia: consome os resultados dela como premissa e constrói em cima a camada que um comitê de investimento espera ver.
B9: RESULTADO — CENÁRIO ATIVO | D9: ='2. Inputs'!D5
B10: VPL @ WACC | D10: ='6. Valuation'!C18
B11: TIR | D11: ='6. Valuation'!C21
B12: WACC | D12: ='2. Inputs'!C81
B13: Payback descontado | D13: ='6. Valuation'!C24
B14: CAPEX no ano 0 | D14: ='2. Inputs'!C53
B15: EBITDA — ano 1 | D15: ='4. DRE'!D39
B16: Margem EBITDA — ano 1 | D16: ='4. DRE'!D40
B17: EBITDA — ano 10 | D17: ='4. DRE'!M39
B18: Margem EBITDA — ano 10 | D18: ='4. DRE'!M40
B19: Margem de segurança sobre o ponto de equilíbrio — ano 1 | D19: ='7. Cenarios e Sensibilidade'!D60
B21: CHECKS DE AMARRAÇÃO | D21: ='10. Checks'!C4
B23: O QUE ESTE MODELO CORRIGE
B24: Gap | C24: O que havia na origem | D24: O que este modelo faz | E24: Onde
B25: 1. DRE em formato FP&A | C25: Resultado espalhado entre 3 abas. Nenhuma linha de EBITDA, EBIT ou margem. | D25: DRE completa com margem em cada linha e memória por unidade. | G25: 4. DRE
B26: 2. Premissa dentro de fórmula | C26: Markup =0,18+0,0065+0,03+0,03+0,25 numa célula. CTU e volume digitados à mão. | D26: Toda premissa numa célula identificada, com fonte, na aba de inputs. | G26: 2. Inputs
B27: 3. Depreciação errada | C27: Anotado pelo próprio autor. Quatro defeitos: base incompleta, vida útil ignorada, reinvestimento sem depreciação, base de volume inconsistente. | D27: Registro de ativos por classe e vida útil, cronograma linear, antes e depois documentado. | G27: 3. Depreciacao
B28: 4. Taxa de desconto | C28: Selic de 12,25%, "vigente em outubro de 2020", sem prêmio de risco. | D28: WACC construído (CAPM), com o impacto no VPL isolado numa ponte de duas pontas. | G28: 6. Valuation
B29: 5. Cenários e sensibilidade | C29: Não existiam. | D29: Três cenários por seletor único, tornado de cinco alavancas, sensibilidade ao custo de capital e tabela WACC x g. | G29: 7. Cenarios
B30: 6. Checks, capa e sumário | C30: Nenhuma célula de verificação na planilha inteira. | D30: 19 checks de amarração e esta capa. | G30: 10. Checks
B31: 7. Ponte de variância de EBITDA | C31: Não havia EBITDA para decompor. | D31: Ponte volume x preço x mix x custo, ano a ano, fechando exatamente, com comentário de gestor. | G31: 9. Ponte EBITDA
B32: 8. Ponto de equilíbrio | C32: Calculado sobre um CTU diferente do usado na DRE, sem leitura de negócio. | D32: PE contábil e de caixa, margem de segurança, alavancagem operacional e o que isso significa. | G32: 7. Cenarios
B34: ACHADOS QUE NÃO ESTAVAM NA LISTA
B35: • O reinvestimento de 2028 estava R$ 5,6 mi inflado por duas referências erradas: 25 notebooks multiplicados pelo preço do tanque de leite, e uma soma elevada ao quadrado no laboratório.
B36: • O CUB (R$ 2.163,98 por m²) entrava somado ao investimento como se fosse um valor de obra.
B37: • A empilhadeira de 2030 era contada duas vezes dentro do mesmo SOMA.
B38: • A rotação do leite no crédito de fornecedores do ano 2 estava 260 em vez de 12 — copiada da linha de estoque.
B39: • A planilha vendia ~10% mais unidades do que produzia, todo ano, sem estoque.
B40: • A parcela de 3% que estava dentro do markup nunca virou despesa: era margem escondida.
B41: • No modo de precificação da origem (custo + markup), custo mais alto gera VPL mais alto. O modelo premiava ineficiência. Há um seletor na aba 2. Inputs para testar preço de mercado fixo.
B43: ÍNDICE
B44: 2. Inputs | C44: Todas as premissas, com fonte. Seletor de cenário em C5 e modo de precificação.
B45: 3. Depreciacao | C45: Registro de ativos, cronograma e o diagnóstico dos quatro defeitos da origem.
B46: 4. DRE | C46: Resultado em formato FP&A, com margem em cada linha.
B47: 5. Fluxo de Caixa | C47: Capital de giro reconstruído e fluxo de caixa livre.
B48: 6. Valuation | C48: WACC, VPL, TIR, payback, valor terminal e a ponte de VPL contra a origem.
B49: 7. Cenarios e Sensibilidade | C49: Três cenários, tornado, sensibilidade e ponto de equilíbrio.
B50: 8. Motor de Cenarios | C50: Camada de cálculo. Não editar — as alavancas ficam na aba 2.
B51: 9. Ponte EBITDA | C51: Decomposição volume x preço x mix x custo.
B52: 10. Checks | C52: 19 amarrações. Se alguma sair de OK, o modelo não sai da gaveta.
B54: CONVENÇÃO DE COR
B55: AZUL — input, pode mudar
B56: PRETO — fórmula, não mexer
B57: VERDE — link de outra aba
B58: AMARELO — premissa a confirmar antes de apresentar
B60: PREMISSAS A CONFIRMAR ANTES DE APRESENTAR
B61: • Prêmio de risco de mercado, beta do setor e estrutura de capital alvo — hoje são placeholders no bloco H da aba 2.
B62: • A taxa livre de risco: a origem diz "Selic de outubro de 2020" e usa 12,25%, valores que não se conciliam.
B63: • A margem-alvo crescente (25% no ano 1 até 43% no ano 10) não tem estudo de preço por trás.
B64: • A contingência de 10% do CAPEX ao ano — em 10 anos consome 100% do investimento.
B65: • A parcela de 3% do markup, aqui tratada como comissão sobre vendas.
B66: • O preço de mercado do modo 2, hoje semeado com o preço do próprio modelo.
... B69: Origem dos dados: projeto acadêmico de Engenharia de Alimentos do autor (UNICAMP). Nenhum dado, cliente ou estrutura de trabalho profissional entra neste arquivo.

Sheet 2. Inputs
A1: INPUTS E PREMISSAS
A2: Business case — planta de doce de leite | Toda premissa do modelo vive nesta aba. Nenhum número entra em fórmula fora daqui.
A4: Convenção de cor: | C4: AZUL = input | E4: PRETO = fórmula | G4: VERDE = link de outra aba | I4: AMARELO = a confirmar
A5: CENÁRIO ATIVO (1 = Pessimista · 2 = Base · 3 = Otimista) | C5: 2 | D5: =INDEX($C$93:$E$93,1,$C$5) | F5: <- nome do cenário lido da tabela de alavancas (bloco J)
A7: Ano | C7: 0 | D7: 1 | E7: 2 | F7: 3 | G7: 4 | H7: 5 | I7: 6 | J7: 7 | K7: 8 | L7: 9 | M7: 10 | O7: Fonte / observação
A8: Exercício | C8: 2023 | D8: 2024 | E8: 2025 | F8: 2026 | G8: 2027 | H8: 2028 | I8: 2029 | J8: 2030 | K8: 2031 | L8: 2032 | M8: 2033
A10: A. VOLUME
A11: Unidades produzidas — origem | B11: un/ano | D11: 1244035 | E11: 1375555 | F11: 1520979 | G11: 1681776 | H11: 1893740 | I11: 2056155 | J11: 2273468 | K11: 2513625 | L11: 2785395 | M11: 3079476 | O11: Origem: '7. Massas iniciais, ritmo de tr'!R122:R131 (balanço de massa). Não recalculado.
A12: Unidades vendidas — origem (referência) | B12: un/ano | D12: 1368200 | E12: 1375315 | F12: 1520713 | G12: 1681483 | H12: 1859250 | I12: 2093581 | J12: 2273136 | K12: 2513381 | L12: 2778882 | M12: 3079331 | O12: Origem: '3. Projeção de produção'!G23:G32, digitadas à mão. Divergem ~10% das produzidas. Ver D-01 em gaps-e-decisoes.
A13: Δ volume do cenário | B13: % | C13: =IF(C$8="2023","",INDEX($C$88:$E$88,1,$C$5)) | D13: =IF(D$8="2023","",INDEX($C$88:$E$88,1,$C$5)) | E13: =IF(E$8="2023","",INDEX($C$88:$E$88,1,$C$5)) | F13: =IF(F$8="2023","",INDEX($C$88:$E$88,1,$C$5)) | G13: =IF(G$8="2023","",INDEX($C$88:$E$88,1,$C$5)) | H13: =IF(H$8="2023","",INDEX($C$88:$E$88,1,$C$5)) | I13: =IF(I$8="2023","",INDEX($C$88:$E$88,1,$C$5)) | J13: =IF(J$8="2023","",INDEX($C$88:$E$88,1,$C$5)) | ... M13: =IF(M$8="2023","",INDEX($C$88:$E$88,1,$C$5)) | O13: Alavanca de cenário — bloco J.
A14: VOLUME DO MODELO | B14: un/ano | C14: =IF(C$8="2023","",C11*(1+C13)) | D14: =IF(D$8="2023","",D11*(1+D13)) | E14: =IF(E$8="2023","",E11*(1+E13)) | F14: =IF(F$8="2023","",F11*(1+F13)) | G14: =IF(G$8="2023","",G11*(1+G13)) | H14: =IF(H$8="2023","",H11*(1+H13)) | I14: =IF(I$8="2023","",I11*(1+I13)) | J14: =IF(J$8="2023","",J11*(1+J13)) | ... M14: =IF(M$8="2023","",M11*(1+M13)) | O14: Volume = produzido. Vender mais do que se produz, sem estoque, não se sustenta (D-01).
A15: Crescimento do volume | B15: % a.a. | E15: =IFERROR(E14/D14-1,"") | F15: =IFERROR(F14/E14-1,"") | G15: =IFERROR(G14/F14-1,"") | H15: =IFERROR(H14/G14-1,"") | I15: =IFERROR(I14/H14-1,"") | J15: =IFERROR(J14/I14-1,"") | K15: =IFERROR(K14/J14-1,"") | L15: =IFERROR(L14/K14-1,"") | M15: =IFERROR(M14/L14-1,"")
A17: B. MIX REGIONAL E FRETE
A18: Participação — Sudeste (alavanca) | B18: % | C18: =IF(C$8="2023","",INDEX($C$92:$E$92,1,$C$5)) | D18: =IF(D$8="2023","",INDEX($C$92:$E$92,1,$C$5)) | E18: =IF(E$8="2023","",INDEX($C$92:$E$92,1,$C$5)) | F18: =IF(F$8="2023","",INDEX($C$92:$E$92,1,$C$5)) | G18: =IF(G$8="2023","",INDEX($C$92:$E$92,1,$C$5)) | H18: =IF(H$8="2023","",INDEX($C$92:$E$92,1,$C$5)) | I18: =IF(I$8="2023","",INDEX($C$92:$E$92,1,$C$5)) | J18: =IF(J$8="2023","",INDEX($C$92:$E$92,1,$C$5)) | ... M18: =IF(M$8="2023","",INDEX($C$92:$E$92,1,$C$5)) | O18: Origem: 20. Custos Unitários!D96. É a alavanca de mix do cenário.
A19: Participação — Sul | B19: % | C19: =IF(C$8="2023","",$C$96/$C$100*(1-C18)) | D19: =IF(D$8="2023","",$C$96/$C$100*(1-D18)) | E19: =IF(E$8="2023","",$C$96/$C$100*(1-E18)) | F19: =IF(F$8="2023","",$C$96/$C$100*(1-F18)) | G19: =IF(G$8="2023","",$C$96/$C$100*(1-G18)) | H19: =IF(H$8="2023","",$C$96/$C$100*(1-H18)) | I19: =IF(I$8="2023","",$C$96/$C$100*(1-I18)) | J19: =IF(J$8="2023","",$C$96/$C$100*(1-J18)) | ... M19: =IF(M$8="2023","",$C$96/$C$100*(1-M18)) | O19: Origem: 20. Custos Unitários!C96. Redistribuída proporcionalmente quando o Sudeste muda.
A20: Participação — Nordeste | B20: % | C20: =IF(C$8="2023","",$C$97/$C$100*(1-C18)) | D20: =IF(D$8="2023","",$C$97/$C$100*(1-D18)) | E20: =IF(E$8="2023","",$C$97/$C$100*(1-E18)) | F20: =IF(F$8="2023","",$C$97/$C$100*(1-F18)) | G20: =IF(G$8="2023","",$C$97/$C$100*(1-G18)) | H20: =IF(H$8="2023","",$C$97/$C$100*(1-H18)) | I20: =IF(I$8="2023","",$C$97/$C$100*(1-I18)) | J20: =IF(J$8="2023","",$C$97/$C$100*(1-J18)) | ... M20: =IF(M$8="2023","",$C$97/$C$100*(1-M18)) | O20: Origem: 20. Custos Unitários!E96. Redistribuída proporcionalmente quando o Sudeste muda.
A21: Participação — Norte | B21: % | C21: =IF(C$8="2023","",$C$98/$C$100*(1-C18)) | D21: =IF(D$8="2023","",$C$98/$C$100*(1-D18)) | E21: =IF(E$8="2023","",$C$98/$C$100*(1-E18)) | F21: =IF(F$8="2023","",$C$98/$C$100*(1-F18)) | G21: =IF(G$8="2023","",$C$98/$C$100*(1-G18)) | H21: =IF(H$8="2023","",$C$98/$C$100*(1-H18)) | I21: =IF(I$8="2023","",$C$98/$C$100*(1-I18)) | J21: =IF(J$8="2023","",$C$98/$C$100*(1-J18)) | ... M21: =IF(M$8="2023","",$C$98/$C$100*(1-M18)) | O21: Origem: 20. Custos Unitários!F96. Redistribuída proporcionalmente quando o Sudeste muda.
A22: Participação — Centro-Oeste | B22: % | C22: =IF(C$8="2023","",$C$99/$C$100*(1-C18)) | D22: =IF(D$8="2023","",$C$99/$C$100*(1-D18)) | E22: =IF(E$8="2023","",$C$99/$C$100*(1-E18)) | F22: =IF(F$8="2023","",$C$99/$C$100*(1-F18)) | G22: =IF(G$8="2023","",$C$99/$C$100*(1-G18)) | H22: =IF(H$8="2023","",$C$99/$C$100*(1-H18)) | I22: =IF(I$8="2023","",$C$99/$C$100*(1-I18)) | J22: =IF(J$8="2023","",$C$99/$C$100*(1-J18)) | ... M22: =IF(M$8="2023","",$C$99/$C$100*(1-M18)) | O22: Origem: 20. Custos Unitários!G96. Redistribuída proporcionalmente quando o Sudeste muda.
A23: Soma das participações | B23: % | C23: =IF(C$8="2023","",SUM(C18:C22)) | D23: =IF(D$8="2023","",SUM(D18:D22)) | E23: =IF(E$8="2023","",SUM(E18:E22)) | F23: =IF(F$8="2023","",SUM(F18:F22)) | G23: =IF(G$8="2023","",SUM(G18:G22)) | H23: =IF(H$8="2023","",SUM(H18:H22)) | I23: =IF(I$8="2023","",SUM(I18:I22)) | J23: =IF(J$8="2023","",SUM(J18:J22)) | ... M23: =IF(M$8="2023","",SUM(M18:M22))
A24: Frete unitário — Sudeste | B24: R$/un | D24: 0.040654 | E24: 0.040654 | F24: 0.040654 | G24: 0.040654 | H24: 0.040654 | I24: 0.040654 | J24: 0.040654 | K24: 0.040654 | L24: 0.040654 | M24: 0.040654 | O24: Derivado de 20. Custos Unitários!C114:G123 / share / unidades. Constante por unidade em todo o horizonte.
A25: Frete unitário — Sul | B25: R$/un | D25: 0.097814 | E25: 0.097814 | F25: 0.097814 | G25: 0.097814 | H25: 0.097814 | I25: 0.097814 | J25: 0.097814 | K25: 0.097814 | L25: 0.097814 | M25: 0.097814 | O25: Derivado de 20. Custos Unitários!C114:G123 / share / unidades. Constante por unidade em todo o horizonte.
A26: Frete unitário — Nordeste | B26: R$/un | D26: 0.198798 | E26: 0.198798 | F26: 0.198798 | G26: 0.198798 | H26: 0.198798 | I26: 0.198798 | J26: 0.198798 | K26: 0.198798 | L26: 0.198798 | M26: 0.198798 | O26: Derivado de 20. Custos Unitários!C114:G123 / share / unidades. Constante por unidade em todo o horizonte.
A27: Frete unitário — Norte | B27: R$/un | D27: 0.299174 | E27: 0.299174 | F27: 0.299174 | G27: 0.299174 | H27: 0.299174 | I27: 0.299174 | J27: 0.299174 | K27: 0.299174 | L27: 0.299174 | M27: 0.299174 | O27: Derivado de 20. Custos Unitários!C114:G123 / share / unidades. Constante por unidade em todo o horizonte.
A28: Frete unitário — Centro-Oeste | B28: R$/un | D28: 0.121031 | E28: 0.121031 | F28: 0.121031 | G28: 0.121031 | H28: 0.121031 | I28: 0.121031 | J28: 0.121031 | K28: 0.121031 | L28: 0.121031 | M28: 0.121031 | O28: Derivado de 20. Custos Unitários!C114:G123 / share / unidades. Constante por unidade em todo o horizonte.
A29: FRETE UNITÁRIO PONDERADO | B29: R$/un | C29: =IF(C$8="2023","",SUMPRODUCT(C18:C22,C24:C28)) | D29: =IF(D$8="2023","",SUMPRODUCT(D18:D22,D24:D28)) | E29: =IF(E$8="2023","",SUMPRODUCT(E18:E22,E24:E28)) | F29: =IF(F$8="2023","",SUMPRODUCT(F18:F22,F24:F28)) | G29: =IF(G$8="2023","",SUMPRODUCT(G18:G22,G24:G28)) | H29: =IF(H$8="2023","",SUMPRODUCT(H18:H22,H24:H28)) | I29: =IF(I$8="2023","",SUMPRODUCT(I18:I22,I24:I28)) | J29: =IF(J$8="2023","",SUMPRODUCT(J18:J22,J24:J28)) | ... M29: =IF(M$8="2023","",SUMPRODUCT(M18:M22,M24:M28)) | O29: Cálculo: SOMARPRODUTO(participações; fretes unitários).
A31: C. PREÇO E MARKUP
A32: ICMS | B32: % | D32: 0.18 | E32: 0.18 | F32: 0.18 | G32: 0.18 | H32: 0.18 | I32: 0.18 | J32: 0.18 | K32: 0.18 | L32: 0.18 | M32: 0.18 | O32: Origem: 21. PVU!I3, alíquota que estava dentro da fórmula.
A33: PIS | B33: % | D33: 0.0065 | E33: 0.0065 | F33: 0.0065 | G33: 0.0065 | H33: 0.0065 | I33: 0.0065 | J33: 0.0065 | K33: 0.0065 | L33: 0.0065 | M33: 0.0065 | O33: Origem: 21. PVU!I3.
A34: COFINS | B34: % | D34: 0.03 | E34: 0.03 | F34: 0.03 | G34: 0.03 | H34: 0.03 | I34: 0.03 | J34: 0.03 | K34: 0.03 | L34: 0.03 | M34: 0.03 | O34: Origem: 21. PVU!I3.
A35: Comissão e outros sobre venda | B35: % | D35: 0.03 | E35: 0.03 | F35: 0.03 | G35: 0.03 | H35: 0.03 | I35: 0.03 | J35: 0.03 | K35: 0.03 | L35: 0.03 | M35: 0.03 | O35: (confirmar) — a parcela 0,03 do markup da origem nunca foi identificada nem cobrada como despesa. Aqui vira linha de custo. Zerar se não existir.
A36: Margem-alvo sobre preço | B36: % | D36: 0.25 | E36: 0.27 | F36: 0.29 | G36: 0.31 | H36: 0.33 | I36: 0.35 | J36: 0.37 | K36: 0.39 | L36: 0.41 | M36: 0.43 | O36: (confirmar) — origem: 21. PVU!B3:B12, sobe 2 p.p. ao ano até 43% sem justificativa de mercado.
A37: Δ margem-alvo do cenário | B37: p.p. | C37: =IF(C$8="2023","",INDEX($C$89:$E$89,1,$C$5)) | D37: =IF(D$8="2023","",INDEX($C$89:$E$89,1,$C$5)) | E37: =IF(E$8="2023","",INDEX($C$89:$E$89,1,$C$5)) | F37: =IF(F$8="2023","",INDEX($C$89:$E$89,1,$C$5)) | G37: =IF(G$8="2023","",INDEX($C$89:$E$89,1,$C$5)) | H37: =IF(H$8="2023","",INDEX($C$89:$E$89,1,$C$5)) | I37: =IF(I$8="2023","",INDEX($C$89:$E$89,1,$C$5)) | J37: =IF(J$8="2023","",INDEX($C$89:$E$89,1,$C$5)) | ... M37: =IF(M$8="2023","",INDEX($C$89:$E$89,1,$C$5)) | O37: Alavanca de cenário — bloco J.
A38: MODO DE PRECIFICAÇÃO | B38: 1 ou 2 | C38: 1 | O38: 1 = custo + markup (a lógica da origem) · 2 = preço de mercado fixo. No modo 1 o preço sobe junto com o custo: o modelo PREMIA ineficiência. Ver D-07 em gaps-e-decisoes.
A39: Preço de mercado | B39: R$/un | D39: 30.4717 | E39: 30.832 | F39: 31.341 | G39: 32.0037 | H39: 32.9725 | I39: 34.0046 | J39: 35.1081 | K39: 36.6072 | L39: 38.0728 | M39: 39.7606 | O39: (confirmar) — semeado com o preço que o modo 1 gera no cenário Base. Substituir por preço observado de doce de leite 600 g quando houver fonte.
A40: MARKUP TOTAL | B40: % | C40: =IF(C$8="2023","",C32+C33+C34+C35+C36+C37) | D40: =IF(D$8="2023","",D32+D33+D34+D35+D36+D37) | E40: =IF(E$8="2023","",E32+E33+E34+E35+E36+E37) | F40: =IF(F$8="2023","",F32+F33+F34+F35+F36+F37) | G40: =IF(G$8="2023","",G32+G33+G34+G35+G36+G37) | H40: =IF(H$8="2023","",H32+H33+H34+H35+H36+H37) | I40: =IF(I$8="2023","",I32+I33+I34+I35+I36+I37) | J40: =IF(J$8="2023","",J32+J33+J34+J35+J36+J37) | ... M40: =IF(M$8="2023","",M32+M33+M34+M35+M36+M37) | O40: Cálculo: ICMS + PIS + COFINS + comissão + margem-alvo. Era =0,18+0,0065+0,03+0,03+0,25 numa célula só.
A42: D. CUSTOS OPERACIONAIS
A43: Custo variável unitário (ex-frete) | B43: R$/un | D43: 11.1316 | E43: 11.0931 | F43: 11.0712 | G43: 11.0489 | H43: 11.0951 | I43: 11.0763 | J43: 11.0478 | K43: 11.104 | L43: 11.0842 | M43: 11.0533 | O43: Derivado: (20. Custos Unitários!K − I) / unidades produzidas. MP, embalagens, insumos, energia, água, EPI, limpeza.
A44: Δ custo variável unitário do cenário | B44: % | C44: =IF(C$8="2023","",INDEX($C$90:$E$90,1,$C$5)) | D44: =IF(D$8="2023","",INDEX($C$90:$E$90,1,$C$5)) | E44: =IF(E$8="2023","",INDEX($C$90:$E$90,1,$C$5)) | F44: =IF(F$8="2023","",INDEX($C$90:$E$90,1,$C$5)) | G44: =IF(G$8="2023","",INDEX($C$90:$E$90,1,$C$5)) | H44: =IF(H$8="2023","",INDEX($C$90:$E$90,1,$C$5)) | I44: =IF(I$8="2023","",INDEX($C$90:$E$90,1,$C$5)) | J44: =IF(J$8="2023","",INDEX($C$90:$E$90,1,$C$5)) | ... M44: =IF(M$8="2023","",INDEX($C$90:$E$90,1,$C$5)) | O44: Alavanca de cenário — bloco J.
A45: CUSTO VARIÁVEL UNITÁRIO DO MODELO | B45: R$/un | C45: =IF(C$8="2023","",C43*(1+C44)) | D45: =IF(D$8="2023","",D43*(1+D44)) | E45: =IF(E$8="2023","",E43*(1+E44)) | F45: =IF(F$8="2023","",F43*(1+F44)) | G45: =IF(G$8="2023","",G43*(1+G44)) | H45: =IF(H$8="2023","",H43*(1+H44)) | I45: =IF(I$8="2023","",I43*(1+I44)) | J45: =IF(J$8="2023","",J43*(1+J44)) | ... M45: =IF(M$8="2023","",M43*(1+M44))
A46: Custo fixo de estrutura (caixa) | B46: R$/ano | D46: 1792483.8 | E46: 1792450 | F46: 1792450 | G46: 1792450 | H46: 1886512.5 | I46: 1886548 | J46: 1886548 | K46: 1886548 | L46: 1886583.5 | M46: 1886512.5 | O46: Origem: 20. Custos Unitários, colunas L+M+N+O+Q (mat. administrativo, higiene, folha, encargos, laboratório).
A47: Manutenção | B47: % do CAPEX acumulado | D47: 0.03 | E47: 0.03 | F47: 0.03 | G47: 0.03 | H47: 0.03 | I47: 0.03 | J47: 0.03 | K47: 0.03 | L47: 0.03 | M47: 0.03 | O47: Origem: 20. Custos Unitários!R3 = 3% do CAPEX. Era % literal repetido em 10 linhas.
A48: Seguro | B48: % do CAPEX acumulado | D48: 0.015 | E48: 0.015 | F48: 0.015 | G48: 0.015 | H48: 0.015 | I48: 0.015 | J48: 0.015 | K48: 0.015 | L48: 0.015 | M48: 0.015 | O48: Origem: 20. Custos Unitários!S3 = 1,5% do CAPEX.
A49: Contingência (imprevistos) | B49: % do CAPEX acumulado | C49: =IF(C$8="2023","",INDEX($C$91:$E$91,1,$C$5)) | D49: =IF(D$8="2023","",INDEX($C$91:$E$91,1,$C$5)) | E49: =IF(E$8="2023","",INDEX($C$91:$E$91,1,$C$5)) | F49: =IF(F$8="2023","",INDEX($C$91:$E$91,1,$C$5)) | G49: =IF(G$8="2023","",INDEX($C$91:$E$91,1,$C$5)) | H49: =IF(H$8="2023","",INDEX($C$91:$E$91,1,$C$5)) | I49: =IF(I$8="2023","",INDEX($C$91:$E$91,1,$C$5)) | J49: =IF(J$8="2023","",INDEX($C$91:$E$91,1,$C$5)) | ... M49: =IF(M$8="2023","",INDEX($C$91:$E$91,1,$C$5)) | O49: (confirmar) — origem: 20. Custos Unitários!T3 = 10% do CAPEX TODO ANO. Em 10 anos consome 100% do CAPEX. É a maior premissa não justificada do modelo. Alavanca de cenário.
A51: E. CAPEX
A52: CAPEX da origem (como estava) | B52: R$ | C52: 17112602 | D52: 0 | E52: 0 | F52: 0 | G52: 161000 | H52: 5745001.4 | I52: 0 | J52: 338100 | K52: 0 | L52: 0 | M52: 0 | O52: Origem: 'Demanda de equipamentos e Inves'!AA46:AA55, realocado ao ano correto (a origem pulava 2026).
A53: CAPEX corrigido | B53: R$ | C53: 17110438 | D53: 0 | E53: 0 | F53: 0 | G53: 161000 | H53: 143118.65 | I53: 0 | J53: 289800 | K53: 0 | L53: 0 | M53: 0 | O53: Ver A-01/A-02/A-03 em leitura-da-origem.md: CUB somado como investimento, notebook ao preço do tanque de leite, soma ao quadrado no laboratório e empilhadeira contada duas vezes.
A54: CAPEX acumulado | B54: R$ | C54: =C53 | D54: =C54+D53 | E54: =D54+E53 | F54: =E54+F53 | G54: =F54+G53 | H54: =G54+H53 | I54: =H54+I53 | J54: =I54+J53 | K54: =J54+K53 | ... M54: =L54+M53
A55: Terreno (não depreciável) | B55: R$ | C55: 908611.9 | O55: Origem: 'Demanda...'!AM6 = 849.170 x 1,07. Tratamento correto na origem.
A57: F. TRIBUTOS SOBRE O LUCRO
A58: IRPJ | B58: % | D58: 0.15 | E58: 0.15 | F58: 0.15 | G58: 0.15 | H58: 0.15 | I58: 0.15 | J58: 0.15 | K58: 0.15 | L58: 0.15 | M58: 0.15 | O58: Origem: 21. PVU!I16.
A59: Adicional de IRPJ | B59: % | D59: 0.1 | E59: 0.1 | F59: 0.1 | G59: 0.1 | H59: 0.1 | I59: 0.1 | J59: 0.1 | K59: 0.1 | L59: 0.1 | M59: 0.1 | O59: Origem: 21. PVU!I16, sobre o lucro que exceder o limite. A origem não protegia lucro abaixo do limite.
A60: Limite do adicional | B60: R$/ano | D60: 240000 | E60: 240000 | F60: 240000 | G60: 240000 | H60: 240000 | I60: 240000 | J60: 240000 | K60: 240000 | L60: 240000 | M60: 240000 | O60: R$ 240 mil/ano (R$ 20 mil/mês). Lucro Real.
A61: CSLL | B61: % | D61: 0.09 | E61: 0.09 | F61: 0.09 | G61: 0.09 | H61: 0.09 | I61: 0.09 | J61: 0.09 | K61: 0.09 | L61: 0.09 | M61: 0.09 | O61: Origem: 21. PVU!J16.
A63: G. CAPITAL DE GIRO
A64: Prazo médio de recebimento | B64: dias | D64: 30 | E64: 30 | F64: 30 | G64: 30 | H64: 30 | I64: 30 | J64: 30 | K64: 30 | L64: 30 | M64: 30 | O64: Origem: 22.1 Capital de Giro!D22 = 30 dias.
A65: Giro de estoque | B65: dias | D65: 17.3 | E65: 17.3 | F65: 17.3 | G65: 17.3 | H65: 17.3 | I65: 17.3 | J65: 17.3 | K65: 17.3 | L65: 17.3 | M65: 17.3 | O65: Derivado de 22.1 Capital de Giro!F18 do ano 1: leite gira em 1 dia, demais insumos em 30. Média ponderada = 17,3 dias.
A66: Prazo médio de pagamento | B66: dias | D66: 30 | E66: 30 | F66: 30 | G66: 30 | H66: 30 | I66: 30 | J66: 30 | K66: 30 | L66: 30 | M66: 30 | O66: Origem: 22.1 Capital de Giro!D24:D33 = 30 dias.
A67: Caixa mínimo | B67: dias de custo caixa | D67: 30 | E67: 30 | F67: 30 | G67: 30 | H67: 30 | I67: 30 | J67: 30 | K67: 30 | L67: 30 | M67: 30 | O67: Origem: 22.1!D20 = 30 dias de custo total. Aqui sobre custo CAIXA: depreciação não exige caixa.
A68: Dias no ano (base financeira) | B68: dias | D68: 360 | E68: 360 | F68: 360 | G68: 360 | H68: 360 | I68: 360 | J68: 360 | K68: 360 | L68: 360 | M68: 360
A70: H. CUSTO DE CAPITAL
A71: Taxa livre de risco (Rf) | C71: 0.1225 | O71: Origem: 22.2 Fluxo de Caixa!J24 = 12,25%, declarada como "Selic vigente em outubro de 2020". (confirmar) — a taxa e a data não se conciliam: 12,25% corresponde à Selic do fim de 2023, não de out/2020. Atualizar com a Selic/NTN-B da data do caso.
A72: Prêmio de risco de mercado (ERP Brasil) | C72: 0.07 | O72: (confirmar) — PLACEHOLDER. Fonte sugerida: Damodaran, Country Risk Premiums, tabela do Brasil.
A73: Beta desalavancado do setor | C73: 0.85 | O73: (confirmar) — PLACEHOLDER. Fonte sugerida: Damodaran, Betas by Sector — Food Processing.
A74: D/E alvo | C74: 0 | O74: (confirmar) — o modelo da origem é 100% equity: não há dívida em aba nenhuma. Com 0, WACC = Ke. Mudar aqui muda o WACC e o VPL.
A75: Custo da dívida (Kd) antes do IR | C75: 0.14 | O75: (confirmar) — PLACEHOLDER. Só entra se D/E > 0.
A76: Alíquota marginal (IRPJ+adicional+CSLL) | C76: 0.34 | O76: 15% + 10% + 9% = 34%.
A77: Beta realavancado | C77: =C73*(1+(1-C76)*C74) | O77: Cálculo: Bu x (1 + (1-t) x D/E).
A78: Custo do capital próprio (Ke) | C78: =C71+C77*C72 | O78: Cálculo: Rf + Beta realavancado x ERP.
A79: Peso do equity (E/V) | C79: =1/(1+C74) | O79: Cálculo: 1 / (1 + D/E).
A80: Peso da dívida (D/V) | C80: =1-C79 | O80: Cálculo: 1 - E/V.
A81: WACC | C81: =C78*C79+C75*(1-C76)*C80 | O81: Cálculo: Ke x E/V + Kd x (1-t) x D/V. Substitui a Selic pura como taxa de desconto.
A82: Taxa da origem (Selic) — para comparação | C82: 0.1225 | O82: Mantida para a ponte de VPL Selic -> WACC na aba 6. Valuation.
A83: Crescimento na perpetuidade (g) | C83: 0 | O83: (confirmar) — com 0, o valor terminal é uma perpetuidade sem crescimento. A origem não tinha valor terminal nenhum.
A84: Considerar valor terminal? (1=sim, 0=não) | C84: 0 | O84: Base = 0, para comparar com a origem em igualdade. Ligar para ver o VPL de uma planta que continua operando.
A86: I. ALAVANCAS DE CENÁRIO
A87: Alavanca | C87: Pessimista | D87: Base | E87: Otimista | F87: Ativo
A88: Δ volume | C88: -0.15 | D88: 0 | E88: 0.1 | F88: =INDEX($C88:$E88,1,$C$5) | O88: (confirmar) — amplitude de julgamento. O caso não traz estudo de demanda.
A89: Δ margem-alvo (p.p.) | C89: -0.05 | D89: 0 | E89: 0.03 | F89: =INDEX($C89:$E89,1,$C$5) | O89: (confirmar) — testa a hipótese de margem crescente da origem.
A90: Δ custo variável unitário | C90: 0.08 | D90: 0 | E90: -0.04 | F90: =INDEX($C90:$E90,1,$C$5) | O90: (confirmar) — leite é ~52% do custo variável; a amplitude deveria vir da série do CEPEA.
A91: Contingência (% do CAPEX/ano) | C91: 0.12 | D91: 0.1 | E91: 0.06 | F91: =INDEX($C91:$E91,1,$C$5) | O91: Base = 10%, a premissa da origem.
A92: Participação do Sudeste | C92: 0.7 | D92: 0.8 | E92: 0.85 | F92: =INDEX($C92:$E92,1,$C$5) | O92: Mix: o Sudeste tem o menor frete unitário. Sair dele encarece.
A93: Nome do cenário | C93: Pessimista | D93: Base | E93: Otimista
A95: J. MIX REGIONAL DA ORIGEM (base da redistribuição do bloco B)
A96: Participação original — Sul | B96: % | C96: 0.05 | O96: Origem: 20. Custos Unitários!C96. Base fixa da redistribuição proporcional da linha 19.
A97: Participação original — Nordeste | B97: % | C97: 0.03 | O97: Origem: 20. Custos Unitários!E96. Base da linha 20.
A98: Participação original — Norte | B98: % | C98: 0.02 | O98: Origem: 20. Custos Unitários!F96. Base da linha 21.
A99: Participação original — Centro-Oeste | B99: % | C99: 0.1 | O99: Origem: 20. Custos Unitários!G96. Base da linha 22.
A100: Soma das regiões fora do Sudeste | B100: % | C100: =SUM(C96:C99) | O100: Denominador da redistribuição. Se o Sudeste sai de 80%, o que sobra é rateado nesta proporção.

Sheet 3. Depreciacao
A1: DEPRECIAÇÃO — DIAGNÓSTICO E CORREÇÃO
A2: O autor anotou "Depreciacao esta errada" em 22.2 Fluxo de Caixa!C5. São quatro defeitos distintos. Esta aba mostra o antes e o depois.
A7: Ano | C7: 0 | D7: 1 | E7: 2 | F7: 3 | G7: 4 | H7: 5 | I7: 6 | J7: 7 | K7: 8 | L7: 9 | M7: 10 | O7: Fonte / observação
A8: Exercício | C8: 2023 | D8: 2024 | E8: 2025 | F8: 2026 | G8: 2027 | H8: 2028 | I8: 2029 | J8: 2030 | K8: 2031 | L8: 2032 | M8: 2033
A10: A. REGISTRO DE ATIVOS (base corrigida)
A11: Ativo | B11: Classe | C11: Ano de entrada | D11: Valor (R$) | E11: Vida útil (anos) | F11: Taxa anual | G11: Depreciação anual (R$)
A12: Construção civil | B12: Edificações | C12: 0 | D12: 12472315 | E12: 25 | F12: =1/E12 | G12: =D12/E12 | O12: Origem: 'Demanda...'!AM5 = CUB x 4.803 m2 x 1,20.
A13: Equipamentos e instalações — ano 0 | B13: Equipamentos | C13: 0 | D13: 3562305.5 | E13: 10 | F13: =1/E13 | G13: =D13/E13 | O13: Equip. de processo + auxiliares + itens de laboratório e pias, TODOS com o acréscimo de 15%. A origem pegou os itens de laboratório antes do acréscimo e esqueceu bancada e armário (D1).
A14: Informática e móveis — ano 0 | B14: Informática/móveis | C14: 0 | D14: 167205.52 | E14: 5 | F14: =1/E14 | G14: =D14/E14 | O14: Equip. administrativos + impressora de laboratório + armários de vestiário, com o acréscimo de 15%.
A15: Reator encamisado (2027) | B15: Equipamentos | C15: 4 | D15: 161000 | E15: 10 | F15: =1/E15 | G15: =D15/E15 | O15: Origem: 'Demanda...'!AE10. Reinvestimento que nunca entrou na base (D3).
A16: Refratômetro e phmetro (2028) | B16: Equipamentos | C16: 5 | D16: 2388.55 | E16: 10 | F16: =1/E16 | G16: =D16/E16 | O16: Renovação de laboratório.
A17: Renovação de informática e móveis (2028) | B17: Informática/móveis | C17: 5 | D17: 140730.1 | E17: 5 | F17: =1/E17 | G17: =D17/E17 | O17: 25 notebooks, 30 cadeiras, 5 impressoras. É a renovação de 5 anos dos ativos de vida curta — e confirma que os R$ 5,7 mi da origem eram erro de fórmula (A-01).
A18: Reator e empilhadeira (2030) | B18: Equipamentos | C18: 7 | D18: 289800 | E18: 10 | F18: =1/E18 | G18: =D18/E18 | O18: Origem: 'Demanda...'!AH10+AH17. A origem somava a empilhadeira duas vezes (A-01).
A19: Subtotal depreciável | D19: =SUM(D12:D18)
A20: Terreno (não depreciável) | D20: 908611.9 | O20: Origem: 'Demanda...'!AM6. Terreno não deprecia — a origem acertou aqui.
A21: TOTAL ATIVO IMOBILIZADO | D21: =D19+D20
A23: B. CRONOGRAMA DE DEPRECIAÇÃO (linear, início no ano seguinte à entrada)
A24: Construção civil | C24: =IF(AND(0>$C$12,0<=$C$12+$E$12),$D$12/$E$12,0) | D24: =IF(AND(1>$C$12,1<=$C$12+$E$12),$D$12/$E$12,0) | E24: =IF(AND(2>$C$12,2<=$C$12+$E$12),$D$12/$E$12,0) | F24: =IF(AND(3>$C$12,3<=$C$12+$E$12),$D$12/$E$12,0) | G24: =IF(AND(4>$C$12,4<=$C$12+$E$12),$D$12/$E$12,0) | H24: =IF(AND(5>$C$12,5<=$C$12+$E$12),$D$12/$E$12,0) | I24: =IF(AND(6>$C$12,6<=$C$12+$E$12),$D$12/$E$12,0) | J24: =IF(AND(7>$C$12,7<=$C$12+$E$12),$D$12/$E$12,0) | K24: =IF(AND(8>$C$12,8<=$C$12+$E$12),$D$12/$E$12,0) | L24: =IF(AND(9>$C$12,9<=$C$12+$E$12),$D$12/$E$12,0) | M24: =IF(AND(10>$C$12,10<=$C$12+$E$12),$D$12/$E$12,0)
A25: Equipamentos e instalações — ano 0 | C25: =IF(AND(0>$C$13,0<=$C$13+$E$13),$D$13/$E$13,0) | D25: =IF(AND(1>$C$13,1<=$C$13+$E$13),$D$13/$E$13,0) | E25: =IF(AND(2>$C$13,2<=$C$13+$E$13),$D$13/$E$13,0) | F25: =IF(AND(3>$C$13,3<=$C$13+$E$13),$D$13/$E$13,0) | G25: =IF(AND(4>$C$13,4<=$C$13+$E$13),$D$13/$E$13,0) | H25: =IF(AND(5>$C$13,5<=$C$13+$E$13),$D$13/$E$13,0) | I25: =IF(AND(6>$C$13,6<=$C$13+$E$13),$D$13/$E$13,0) | J25: =IF(AND(7>$C$13,7<=$C$13+$E$13),$D$13/$E$13,0) | K25: =IF(AND(8>$C$13,8<=$C$13+$E$13),$D$13/$E$13,0) | L25: =IF(AND(9>$C$13,9<=$C$13+$E$13),$D$13/$E$13,0) | M25: =IF(AND(10>$C$13,10<=$C$13+$E$13),$D$13/$E$13,0)
A26: Informática e móveis — ano 0 | C26: =IF(AND(0>$C$14,0<=$C$14+$E$14),$D$14/$E$14,0) | D26: =IF(AND(1>$C$14,1<=$C$14+$E$14),$D$14/$E$14,0) | E26: =IF(AND(2>$C$14,2<=$C$14+$E$14),$D$14/$E$14,0) | F26: =IF(AND(3>$C$14,3<=$C$14+$E$14),$D$14/$E$14,0) | G26: =IF(AND(4>$C$14,4<=$C$14+$E$14),$D$14/$E$14,0) | H26: =IF(AND(5>$C$14,5<=$C$14+$E$14),$D$14/$E$14,0) | I26: =IF(AND(6>$C$14,6<=$C$14+$E$14),$D$14/$E$14,0) | J26: =IF(AND(7>$C$14,7<=$C$14+$E$14),$D$14/$E$14,0) | K26: =IF(AND(8>$C$14,8<=$C$14+$E$14),$D$14/$E$14,0) | L26: =IF(AND(9>$C$14,9<=$C$14+$E$14),$D$14/$E$14,0) | M26: =IF(AND(10>$C$14,10<=$C$14+$E$14),$D$14/$E$14,0)
A27: Reator encamisado (2027) | C27: =IF(AND(0>$C$15,0<=$C$15+$E$15),$D$15/$E$15,0) | D27: =IF(AND(1>$C$15,1<=$C$15+$E$15),$D$15/$E$15,0) | E27: =IF(AND(2>$C$15,2<=$C$15+$E$15),$D$15/$E$15,0) | F27: =IF(AND(3>$C$15,3<=$C$15+$E$15),$D$15/$E$15,0) | G27: =IF(AND(4>$C$15,4<=$C$15+$E$15),$D$15/$E$15,0) | H27: =IF(AND(5>$C$15,5<=$C$15+$E$15),$D$15/$E$15,0) | I27: =IF(AND(6>$C$15,6<=$C$15+$E$15),$D$15/$E$15,0) | J27: =IF(AND(7>$C$15,7<=$C$15+$E$15),$D$15/$E$15,0) | K27: =IF(AND(8>$C$15,8<=$C$15+$E$15),$D$15/$E$15,0) | L27: =IF(AND(9>$C$15,9<=$C$15+$E$15),$D$15/$E$15,0) | M27: =IF(AND(10>$C$15,10<=$C$15+$E$15),$D$15/$E$15,0)
A28: Refratômetro e phmetro (2028) | C28: =IF(AND(0>$C$16,0<=$C$16+$E$16),$D$16/$E$16,0) | D28: =IF(AND(1>$C$16,1<=$C$16+$E$16),$D$16/$E$16,0) | E28: =IF(AND(2>$C$16,2<=$C$16+$E$16),$D$16/$E$16,0) | F28: =IF(AND(3>$C$16,3<=$C$16+$E$16),$D$16/$E$16,0) | G28: =IF(AND(4>$C$16,4<=$C$16+$E$16),$D$16/$E$16,0) | H28: =IF(AND(5>$C$16,5<=$C$16+$E$16),$D$16/$E$16,0) | I28: =IF(AND(6>$C$16,6<=$C$16+$E$16),$D$16/$E$16,0) | J28: =IF(AND(7>$C$16,7<=$C$16+$E$16),$D$16/$E$16,0) | K28: =IF(AND(8>$C$16,8<=$C$16+$E$16),$D$16/$E$16,0) | L28: =IF(AND(9>$C$16,9<=$C$16+$E$16),$D$16/$E$16,0) | M28: =IF(AND(10>$C$16,10<=$C$16+$E$16),$D$16/$E$16,0)
A29: Renovação de informática e móveis (2028) | C29: =IF(AND(0>$C$17,0<=$C$17+$E$17),$D$17/$E$17,0) | D29: =IF(AND(1>$C$17,1<=$C$17+$E$17),$D$17/$E$17,0) | E29: =IF(AND(2>$C$17,2<=$C$17+$E$17),$D$17/$E$17,0) | F29: =IF(AND(3>$C$17,3<=$C$17+$E$17),$D$17/$E$17,0) | G29: =IF(AND(4>$C$17,4<=$C$17+$E$17),$D$17/$E$17,0) | H29: =IF(AND(5>$C$17,5<=$C$17+$E$17),$D$17/$E$17,0) | I29: =IF(AND(6>$C$17,6<=$C$17+$E$17),$D$17/$E$17,0) | J29: =IF(AND(7>$C$17,7<=$C$17+$E$17),$D$17/$E$17,0) | K29: =IF(AND(8>$C$17,8<=$C$17+$E$17),$D$17/$E$17,0) | L29: =IF(AND(9>$C$17,9<=$C$17+$E$17),$D$17/$E$17,0) | M29: =IF(AND(10>$C$17,10<=$C$17+$E$17),$D$17/$E$17,0)
A30: Reator e empilhadeira (2030) | C30: =IF(AND(0>$C$18,0<=$C$18+$E$18),$D$18/$E$18,0) | D30: =IF(AND(1>$C$18,1<=$C$18+$E$18),$D$18/$E$18,0) | E30: =IF(AND(2>$C$18,2<=$C$18+$E$18),$D$18/$E$18,0) | F30: =IF(AND(3>$C$18,3<=$C$18+$E$18),$D$18/$E$18,0) | G30: =IF(AND(4>$C$18,4<=$C$18+$E$18),$D$18/$E$18,0) | H30: =IF(AND(5>$C$18,5<=$C$18+$E$18),$D$18/$E$18,0) | I30: =IF(AND(6>$C$18,6<=$C$18+$E$18),$D$18/$E$18,0) | J30: =IF(AND(7>$C$18,7<=$C$18+$E$18),$D$18/$E$18,0) | K30: =IF(AND(8>$C$18,8<=$C$18+$E$18),$D$18/$E$18,0) | L30: =IF(AND(9>$C$18,9<=$C$18+$E$18),$D$18/$E$18,0) | M30: =IF(AND(10>$C$18,10<=$C$18+$E$18),$D$18/$E$18,0)
A31: DEPRECIAÇÃO CORRIGIDA | B31: R$/ano | C31: =SUM(C24:C30) | D31: =SUM(D24:D30) | E31: =SUM(E24:E30) | F31: =SUM(F24:F30) | G31: =SUM(G24:G30) | H31: =SUM(H24:H30) | I31: =SUM(I24:I30) | J31: =SUM(J24:J30) | ... M31: =SUM(M24:M30)
A32: Depreciação acumulada | B32: R$ | C32: =C31 | D32: =C32+D31 | E32: =D32+E31 | F32: =E32+F31 | G32: =F32+G31 | H32: =G32+H31 | I32: =H32+I31 | J32: =I32+J31 | K32: =J32+K31 | ... M32: =L32+M31
A33: Valor contábil líquido do imobilizado | B33: R$ | C33: =$D$21-C32 | D33: =$D$21-D32 | E33: =$D$21-E32 | F33: =$D$21-F32 | G33: =$D$21-G32 | H33: =$D$21-H32 | I33: =$D$21-I32 | J33: =$D$21-J32 | ... M33: =$D$21-M32 | O33: Cálculo: ativo total − depreciação acumulada. Usado no valor residual do fluxo de caixa.
A35: C. ANTES E DEPOIS — o que o erro custava
A36: Depreciação da origem | B36: R$/ano | C36: 0 | D36: 885858.58 | E36: 885858.58 | F36: 885858.58 | G36: 885858.58 | H36: 885858.58 | I36: 885858.58 | J36: 885858.58 | K36: 885858.58 | L36: 885858.58 | M36: 885858.58 | O36: Origem: 20. Custos Unitários!D136, constante nos 10 anos. Zero no ano 0.
A37: Depreciação corrigida | B37: R$/ano | C37: =C31 | D37: =D31 | E37: =E31 | F37: =F31 | G37: =G31 | H37: =H31 | I37: =I31 | J37: =J31 | ... M37: =M31
A38: Diferença (corrigida − origem) | B38: R$/ano | C38: =C37-C36 | D38: =D37-D36 | E38: =E37-E36 | F38: =F37-F36 | G38: =G37-G36 | H38: =H37-H36 | I38: =I37-I36 | J38: =J37-J36 | ... M38: =M37-M36
A39: Efeito no imposto | B39: R$/ano | C39: =-C38*'2. Inputs'!$C$76 | D39: =-D38*'2. Inputs'!$C$76 | E39: =-E38*'2. Inputs'!$C$76 | F39: =-F38*'2. Inputs'!$C$76 | G39: =-G38*'2. Inputs'!$C$76 | H39: =-H38*'2. Inputs'!$C$76 | I39: =-I38*'2. Inputs'!$C$76 | J39: =-J38*'2. Inputs'!$C$76 | ... M39: =-M38*'2. Inputs'!$C$76 | O39: Mais depreciação = menos lucro tributável = menos imposto. Alíquota em 2. Inputs!C76. Sinal negativo = imposto a menos.
A40: Efeito líquido no caixa | B40: R$/ano | C40: =C38*'2. Inputs'!$C$76 | D40: =D38*'2. Inputs'!$C$76 | E40: =E38*'2. Inputs'!$C$76 | F40: =F38*'2. Inputs'!$C$76 | G40: =G38*'2. Inputs'!$C$76 | H40: =H38*'2. Inputs'!$C$76 | I40: =I38*'2. Inputs'!$C$76 | J40: =J38*'2. Inputs'!$C$76 | ... M40: =M38*'2. Inputs'!$C$76 | O40: A depreciação sai do lucro e volta no fluxo: o efeito de caixa é só o escudo fiscal. Sinal positivo = caixa a mais.
A42: D. OS QUATRO DEFEITOS DA ORIGEM
A43: D1 — Base incompleta | C43: A origem depreciava R$ 16.185.053. A base correta do ano 0 é R$ 16.201.826. Faltavam R$ 16.773: itens de laboratório pegos antes do acréscimo de 15%, e bancada (R$ 3.800) e armário de laboratório (R$ 4.048) não classificados em ativo nenhum. | O43: subdepreciava
A44: D2 — Vida útil ignorada | C44: "Material de informática e móveis" tem vida de 5 anos na própria tabela da origem (20. Custos Unitários!B130) e era depreciado nos 10 anos do horizonte: R$ 313.844 sobre uma base de R$ 156.922. 200% do custo. | O44: superdepreciava R$ 156.922
A45: D3 — Reinvestimento sem depreciação | C45: R$ 594 mil de CAPEX corrigido entra no fluxo nos anos 4, 5 e 7 e nunca aparecia na base. A tabela D133:D135 só olhava o ano 0. | O45: subdepreciava
A46: D4 — Base de volume inconsistente | C46: A depreciação virava custo fixo unitário dividida por unidades PRODUZIDAS e voltava ao resultado multiplicada por unidades VENDIDAS. No ano 1 deduzia R$ 974.270 e somava de volta R$ 885.859: R$ 88.412 de caixa fantasma, todo ano. | O46: inflava o fluxo de caixa
A47: Não era erro | C47: O terreno (R$ 908.612) está fora da base — correto, terreno não deprecia. E a depreciação era deduzida antes do imposto e somada de volta no fluxo: o mecanismo do escudo fiscal estava certo. O problema era o valor, não o lugar. | O47: —

Sheet 4. DRE
A1: DRE — FORMATO FP&A
A2: Margem em cada linha. Na origem o resultado estava espalhado entre 20. Custos Unitários, 21. PVU e 22.2 Fluxo de Caixa, e não havia EBITDA em lugar nenhum.
A7: Ano | C7: 0 | D7: 1 | E7: 2 | F7: 3 | G7: 4 | H7: 5 | I7: 6 | J7: 7 | K7: 8 | L7: 9 | M7: 10 | O7: Observação
A8: Exercício | C8: 2023 | D8: 2024 | E8: 2025 | F8: 2026 | G8: 2027 | H8: 2028 | I8: 2029 | J8: 2030 | K8: 2031 | L8: 2032 | M8: 2033
A10: A. APURAÇÃO DO PREÇO (custo total + markup — a lógica da origem, com cada parcela visível)
A11: Volume | B11: un/ano | C11: — | D11: ='2. Inputs'!D14 | E11: ='2. Inputs'!E14 | F11: ='2. Inputs'!F14 | G11: ='2. Inputs'!G14 | H11: ='2. Inputs'!H14 | I11: ='2. Inputs'!I14 | J11: ='2. Inputs'!J14 | K11: ='2. Inputs'!K14 | ... M11: ='2. Inputs'!M14
A12: Custo variável | B12: R$ | C12: — | D12: =D11*'2. Inputs'!D45 | E12: =E11*'2. Inputs'!E45 | F12: =F11*'2. Inputs'!F45 | G12: =G11*'2. Inputs'!G45 | H12: =H11*'2. Inputs'!H45 | I12: =I11*'2. Inputs'!I45 | J12: =J11*'2. Inputs'!J45 | K12: =K11*'2. Inputs'!K45 | ... M12: =M11*'2. Inputs'!M45
A13: Frete sobre vendas | B13: R$ | C13: — | D13: =D11*'2. Inputs'!D29 | E13: =E11*'2. Inputs'!E29 | F13: =F11*'2. Inputs'!F29 | G13: =G11*'2. Inputs'!G29 | H13: =H11*'2. Inputs'!H29 | I13: =I11*'2. Inputs'!I29 | J13: =J11*'2. Inputs'!J29 | K13: =K11*'2. Inputs'!K29 | ... M13: =M11*'2. Inputs'!M29 | O13: Volume x frete unitário ponderado pelo mix regional.
A14: Custo fixo de estrutura | B14: R$ | C14: — | D14: ='2. Inputs'!D46 | E14: ='2. Inputs'!E46 | F14: ='2. Inputs'!F46 | G14: ='2. Inputs'!G46 | H14: ='2. Inputs'!H46 | I14: ='2. Inputs'!I46 | J14: ='2. Inputs'!J46 | K14: ='2. Inputs'!K46 | ... M14: ='2. Inputs'!M46
A15: Manutenção e seguro | B15: R$ | C15: — | D15: =('2. Inputs'!D47+'2. Inputs'!D48)*'2. Inputs'!D54 | E15: =('2. Inputs'!E47+'2. Inputs'!E48)*'2. Inputs'!E54 | F15: =('2. Inputs'!F47+'2. Inputs'!F48)*'2. Inputs'!F54 | G15: =('2. Inputs'!G47+'2. Inputs'!G48)*'2. Inputs'!G54 | H15: =('2. Inputs'!H47+'2. Inputs'!H48)*'2. Inputs'!H54 | I15: =('2. Inputs'!I47+'2. Inputs'!I48)*'2. Inputs'!I54 | J15: =('2. Inputs'!J47+'2. Inputs'!J48)*'2. Inputs'!J54 | K15: =('2. Inputs'!K47+'2. Inputs'!K48)*'2. Inputs'!K54 | ... M15: =('2. Inputs'!M47+'2. Inputs'!M48)*'2. Inputs'!M54 | O15: (3,0% + 1,5%) x CAPEX acumulado.
A16: Contingência | B16: R$ | C16: — | D16: ='2. Inputs'!D49*'2. Inputs'!D54 | E16: ='2. Inputs'!E49*'2. Inputs'!E54 | F16: ='2. Inputs'!F49*'2. Inputs'!F54 | G16: ='2. Inputs'!G49*'2. Inputs'!G54 | H16: ='2. Inputs'!H49*'2. Inputs'!H54 | I16: ='2. Inputs'!I49*'2. Inputs'!I54 | J16: ='2. Inputs'!J49*'2. Inputs'!J54 | K16: ='2. Inputs'!K49*'2. Inputs'!K54 | ... M16: ='2. Inputs'!M49*'2. Inputs'!M54 | O16: % x CAPEX acumulado — alavanca de cenário.
A17: Depreciação | B17: R$ | C17: — | D17: ='3. Depreciacao'!D31 | E17: ='3. Depreciacao'!E31 | F17: ='3. Depreciacao'!F31 | G17: ='3. Depreciacao'!G31 | H17: ='3. Depreciacao'!H31 | I17: ='3. Depreciacao'!I31 | J17: ='3. Depreciacao'!J31 | K17: ='3. Depreciacao'!K31 | ... M17: ='3. Depreciacao'!M31
A18: CUSTO TOTAL | B18: R$ | D18: =SUM(D12:D17) | E18: =SUM(E12:E17) | F18: =SUM(F12:F17) | G18: =SUM(G12:G17) | H18: =SUM(H12:H17) | I18: =SUM(I12:I17) | J18: =SUM(J12:J17) | K18: =SUM(K12:K17) | ... M18: =SUM(M12:M17)
A19: Custo total unitário (CTU) | B19: R$/un | D19: =D18/D11 | E19: =E18/E11 | F19: =F18/F11 | G19: =G18/G11 | H19: =H18/H11 | I19: =I18/I11 | J19: =J18/J11 | K19: =K18/K11 | ... M19: =M18/M11 | O19: Na origem o CTU estava DIGITADO em 21. PVU!C3:C12 e já não batia com o custo calculado.
A20: Markup total | B20: % | D20: ='2. Inputs'!D40 | E20: ='2. Inputs'!E40 | F20: ='2. Inputs'!F40 | G20: ='2. Inputs'!G40 | H20: ='2. Inputs'!H40 | I20: ='2. Inputs'!I40 | J20: ='2. Inputs'!J40 | K20: ='2. Inputs'!K40 | ... M20: ='2. Inputs'!M40
A21: PREÇO BRUTO UNITÁRIO | B21: R$/un | D21: =IF('2. Inputs'!$C$38=1,D19/(1-D20),'2. Inputs'!D39) | E21: =IF('2. Inputs'!$C$38=1,E19/(1-E20),'2. Inputs'!E39) | F21: =IF('2. Inputs'!$C$38=1,F19/(1-F20),'2. Inputs'!F39) | G21: =IF('2. Inputs'!$C$38=1,G19/(1-G20),'2. Inputs'!G39) | H21: =IF('2. Inputs'!$C$38=1,H19/(1-H20),'2. Inputs'!H39) | I21: =IF('2. Inputs'!$C$38=1,I19/(1-I20),'2. Inputs'!I39) | J21: =IF('2. Inputs'!$C$38=1,J19/(1-J20),'2. Inputs'!J39) | K21: =IF('2. Inputs'!$C$38=1,K19/(1-K20),'2. Inputs'!K39) | ... M21: =IF('2. Inputs'!$C$38=1,M19/(1-M20),'2. Inputs'!M39) | O21: Modo 1: CTU / (1 − markup). Modo 2: preço de mercado da aba 2. Inputs.
A23: B. DEMONSTRAÇÃO DE RESULTADO
A24: Volume | B24: un/ano | C24: — | D24: =D11 | E24: =E11 | F24: =F11 | G24: =G11 | H24: =H11 | I24: =I11 | J24: =J11 | K24: =K11 | ... M24: =M11
A25: Preço bruto unitário | B25: R$/un | D25: =D21 | E25: =E21 | F25: =F21 | G25: =G21 | H25: =H21 | I25: =I21 | J25: =J21 | K25: =K21 | ... M25: =M21
A26: RECEITA BRUTA | B26: R$ | D26: =D24*D25 | E26: =E24*E25 | F26: =F24*F25 | G26: =G24*G25 | H26: =H24*H25 | I26: =I24*I25 | J26: =J24*J25 | K26: =K24*K25 | ... M26: =M24*M25
A27: (−) ICMS | B27: R$ | D27: =-'2. Inputs'!D32*D26 | E27: =-'2. Inputs'!E32*E26 | F27: =-'2. Inputs'!F32*F26 | G27: =-'2. Inputs'!G32*G26 | H27: =-'2. Inputs'!H32*H26 | I27: =-'2. Inputs'!I32*I26 | J27: =-'2. Inputs'!J32*J26 | K27: =-'2. Inputs'!K32*K26 | ... M27: =-'2. Inputs'!M32*M26
A28: (−) PIS e COFINS | B28: R$ | D28: =-('2. Inputs'!D33+'2. Inputs'!D34)*D26 | E28: =-('2. Inputs'!E33+'2. Inputs'!E34)*E26 | F28: =-('2. Inputs'!F33+'2. Inputs'!F34)*F26 | G28: =-('2. Inputs'!G33+'2. Inputs'!G34)*G26 | H28: =-('2. Inputs'!H33+'2. Inputs'!H34)*H26 | I28: =-('2. Inputs'!I33+'2. Inputs'!I34)*I26 | J28: =-('2. Inputs'!J33+'2. Inputs'!J34)*J26 | K28: =-('2. Inputs'!K33+'2. Inputs'!K34)*K26 | ... M28: =-('2. Inputs'!M33+'2. Inputs'!M34)*M26
A29: RECEITA LÍQUIDA | B29: R$ | D29: =SUM(D26:D28) | E29: =SUM(E26:E28) | F29: =SUM(F26:F28) | G29: =SUM(G26:G28) | H29: =SUM(H26:H28) | I29: =SUM(I26:I28) | J29: =SUM(J26:J28) | K29: =SUM(K26:K28) | ... M29: =SUM(M26:M28)
A30: Deduções sobre receita bruta | B30: % RB | D30: =-(D27+D28)/D26 | E30: =-(E27+E28)/E26 | F30: =-(F27+F28)/F26 | G30: =-(G27+G28)/G26 | H30: =-(H27+H28)/H26 | I30: =-(I27+I28)/I26 | J30: =-(J27+J28)/J26 | K30: =-(K27+K28)/K26 | ... M30: =-(M27+M28)/M26
A31: (−) Custo variável | B31: R$ | D31: =-D12 | E31: =-E12 | F31: =-F12 | G31: =-G12 | H31: =-H12 | I31: =-I12 | J31: =-J12 | K31: =-K12 | ... M31: =-M12
A32: (−) Frete sobre vendas | B32: R$ | D32: =-D13 | E32: =-E13 | F32: =-F13 | G32: =-G13 | H32: =-H13 | I32: =-I13 | J32: =-J13 | K32: =-K13 | ... M32: =-M13
A33: (−) Comissão sobre vendas | B33: R$ | D33: =-'2. Inputs'!D35*D26 | E33: =-'2. Inputs'!E35*E26 | F33: =-'2. Inputs'!F35*F26 | G33: =-'2. Inputs'!G35*G26 | H33: =-'2. Inputs'!H35*H26 | I33: =-'2. Inputs'!I35*I26 | J33: =-'2. Inputs'!J35*J26 | K33: =-'2. Inputs'!K35*K26 | ... M33: =-'2. Inputs'!M35*M26 | O33: (confirmar) — na origem esta parcela de 3% estava DENTRO do markup e nunca virou despesa: virava margem escondida.
A34: MARGEM DE CONTRIBUIÇÃO | B34: R$ | D34: =SUM(D31:D33)+D29 | E34: =SUM(E31:E33)+E29 | F34: =SUM(F31:F33)+F29 | G34: =SUM(G31:G33)+G29 | H34: =SUM(H31:H33)+H29 | I34: =SUM(I31:I33)+I29 | J34: =SUM(J31:J33)+J29 | K34: =SUM(K31:K33)+K29 | ... M34: =SUM(M31:M33)+M29
A35: Margem de contribuição | B35: % RL | D35: =D34/D29 | E35: =E34/E29 | F35: =F34/F29 | G35: =G34/G29 | H35: =H34/H29 | I35: =I34/I29 | J35: =J34/J29 | K35: =K34/K29 | ... M35: =M34/M29
A36: (−) Custo fixo de estrutura | B36: R$ | D36: =-D14 | E36: =-E14 | F36: =-F14 | G36: =-G14 | H36: =-H14 | I36: =-I14 | J36: =-J14 | K36: =-K14 | ... M36: =-M14
A37: (−) Manutenção e seguro | B37: R$ | D37: =-D15 | E37: =-E15 | F37: =-F15 | G37: =-G15 | H37: =-H15 | I37: =-I15 | J37: =-J15 | K37: =-K15 | ... M37: =-M15
A38: (−) Contingência | B38: R$ | D38: =-D16 | E38: =-E16 | F38: =-F16 | G38: =-G16 | H38: =-H16 | I38: =-I16 | J38: =-J16 | K38: =-K16 | ... M38: =-M16
A39: EBITDA | B39: R$ | D39: =D34+SUM(D36:D38) | E39: =E34+SUM(E36:E38) | F39: =F34+SUM(F36:F38) | G39: =G34+SUM(G36:G38) | H39: =H34+SUM(H36:H38) | I39: =I34+SUM(I36:I38) | J39: =J34+SUM(J36:J38) | K39: =K34+SUM(K36:K38) | ... M39: =M34+SUM(M36:M38)
A40: Margem EBITDA | B40: % RL | D40: =D39/D29 | E40: =E39/E29 | F40: =F39/F29 | G40: =G39/G29 | H40: =H39/H29 | I40: =I39/I29 | J40: =J39/J29 | K40: =K39/K29 | ... M40: =M39/M29
A41: (−) Depreciação | B41: R$ | D41: =-D17 | E41: =-E17 | F41: =-F17 | G41: =-G17 | H41: =-H17 | I41: =-I17 | J41: =-J17 | K41: =-K17 | ... M41: =-M17
A42: EBIT | B42: R$ | D42: =D39+D41 | E42: =E39+E41 | F42: =F39+F41 | G42: =G39+G41 | H42: =H39+H41 | I42: =I39+I41 | J42: =J39+J41 | K42: =K39+K41 | ... M42: =M39+M41
A43: Margem EBIT | B43: % RL | D43: =D42/D29 | E43: =E42/E29 | F43: =F42/F29 | G43: =G42/G29 | H43: =H42/H29 | I43: =I42/I29 | J43: =J42/J29 | K43: =K42/K29 | ... M43: =M42/M29
A44: (−) IRPJ + adicional | B44: R$ | D44: =-IF(D42>0,'2. Inputs'!D58*D42+'2. Inputs'!D59*MAX(0,D42-'2. Inputs'!D60),0) | E44: =-IF(E42>0,'2. Inputs'!E58*E42+'2. Inputs'!E59*MAX(0,E42-'2. Inputs'!E60),0) | F44: =-IF(F42>0,'2. Inputs'!F58*F42+'2. Inputs'!F59*MAX(0,F42-'2. Inputs'!F60),0) | G44: =-IF(G42>0,'2. Inputs'!G58*G42+'2. Inputs'!G59*MAX(0,G42-'2. Inputs'!G60),0) | H44: =-IF(H42>0,'2. Inputs'!H58*H42+'2. Inputs'!H59*MAX(0,H42-'2. Inputs'!H60),0) | I44: =-IF(I42>0,'2. Inputs'!I58*I42+'2. Inputs'!I59*MAX(0,I42-'2. Inputs'!I60),0) | J44: =-IF(J42>0,'2. Inputs'!J58*J42+'2. Inputs'!J59*MAX(0,J42-'2. Inputs'!J60),0) | K44: =-IF(K42>0,'2. Inputs'!K58*K42+'2. Inputs'!K59*MAX(0,K42-'2. Inputs'!K60),0) | ... M44: =-IF(M42>0,'2. Inputs'!M58*M42+'2. Inputs'!M59*MAX(0,M42-'2. Inputs'!M60),0) | O44: A origem não protegia lucro abaixo do limite do adicional nem prejuízo.
A45: (−) CSLL | B45: R$ | D45: =-IF(D42>0,'2. Inputs'!D61*D42,0) | E45: =-IF(E42>0,'2. Inputs'!E61*E42,0) | F45: =-IF(F42>0,'2. Inputs'!F61*F42,0) | G45: =-IF(G42>0,'2. Inputs'!G61*G42,0) | H45: =-IF(H42>0,'2. Inputs'!H61*H42,0) | I45: =-IF(I42>0,'2. Inputs'!I61*I42,0) | J45: =-IF(J42>0,'2. Inputs'!J61*J42,0) | K45: =-IF(K42>0,'2. Inputs'!K61*K42,0) | ... M45: =-IF(M42>0,'2. Inputs'!M61*M42,0)
A46: LUCRO LÍQUIDO | B46: R$ | D46: =D42+D44+D45 | E46: =E42+E44+E45 | F46: =F42+F44+F45 | G46: =G42+G44+G45 | H46: =H42+H44+H45 | I46: =I42+I44+I45 | J46: =J42+J44+J45 | K46: =K42+K44+K45 | ... M46: =M42+M44+M45
A47: Margem líquida | B47: % RL | D47: =D46/D29 | E47: =E46/E29 | F47: =F46/F29 | G47: =G46/G29 | H47: =H46/H29 | I47: =I46/I29 | J47: =J46/J29 | K47: =K46/K29 | ... M47: =M46/M29
A48: Nota: não há resultado financeiro porque o projeto é 100% equity — não existe dívida em nenhuma aba da origem.
A50: C. MEMÓRIA POR UNIDADE (insumo da ponte de variância)
A51: Preço líquido de impostos | B51: R$/un | D51: =D29/D24 | E51: =E29/E24 | F51: =F29/F24 | G51: =G29/G24 | H51: =H29/H24 | I51: =I29/I24 | J51: =J29/J24 | K51: =K29/K24 | ... M51: =M29/M24
A52: Comissão por unidade | B52: R$/un | D52: =-D33/D24 | E52: =-E33/E24 | F52: =-F33/F24 | G52: =-G33/G24 | H52: =-H33/H24 | I52: =-I33/I24 | J52: =-J33/J24 | K52: =-K33/K24 | ... M52: =-M33/M24
A53: Custo variável unitário | B53: R$/un | D53: =-D31/D24 | E53: =-E31/E24 | F53: =-F31/F24 | G53: =-G31/G24 | H53: =-H31/H24 | I53: =-I31/I24 | J53: =-J31/J24 | K53: =-K31/K24 | ... M53: =-M31/M24
A54: Frete unitário (mix) | B54: R$/un | D54: =-D32/D24 | E54: =-E32/E24 | F54: =-F32/F24 | G54: =-G32/G24 | H54: =-H32/H24 | I54: =-I32/I24 | J54: =-J32/J24 | K54: =-K32/K24 | ... M54: =-M32/M24
A55: MARGEM DE CONTRIBUIÇÃO UNITÁRIA | B55: R$/un | D55: =D51-D52-D53-D54 | E55: =E51-E52-E53-E54 | F55: =F51-F52-F53-F54 | G55: =G51-G52-G53-G54 | H55: =H51-H52-H53-H54 | I55: =I51-I52-I53-I54 | J55: =J51-J52-J53-J54 | K55: =K51-K52-K53-K54 | ... M55: =M51-M52-M53-M54
A56: Custo fixo total (caixa) | B56: R$ | D56: =-(D36+D37+D38) | E56: =-(E36+E37+E38) | F56: =-(F36+F37+F38) | G56: =-(G36+G37+G38) | H56: =-(H36+H37+H38) | I56: =-(I36+I37+I38) | J56: =-(J36+J37+J38) | K56: =-(K36+K37+K38) | ... M56: =-(M36+M37+M38)
A57: EBITDA por unidade | B57: R$/un | D57: =D39/D24 | E57: =E39/E24 | F57: =F39/F24 | G57: =G39/G24 | H57: =H39/H24 | I57: =I39/I24 | J57: =J39/J24 | K57: =K39/K24 | ... M57: =M39/M24
A58: Alíquota efetiva sobre o EBIT | B58: % | D58: =IFERROR(-(D44+D45)/D42,0) | E58: =IFERROR(-(E44+E45)/E42,0) | F58: =IFERROR(-(F44+F45)/F42,0) | G58: =IFERROR(-(G44+G45)/G42,0) | H58: =IFERROR(-(H44+H45)/H42,0) | I58: =IFERROR(-(I44+I45)/I42,0) | J58: =IFERROR(-(J44+J45)/J42,0) | K58: =IFERROR(-(K44+K45)/K42,0) | ... M58: =IFERROR(-(M44+M45)/M42,0)

Sheet 5. Fluxo de Caixa
A1: FLUXO DE CAIXA LIVRE
A2: Capital de giro reconstruído sobre prazos declarados; CAPEX corrigido; depreciação da aba 3. Não há dívida, logo o FCL é também o fluxo do acionista.
A7: Ano | C7: 0 | D7: 1 | E7: 2 | F7: 3 | G7: 4 | H7: 5 | I7: 6 | J7: 7 | K7: 8 | L7: 9 | M7: 10 | O7: Observação
A8: Exercício | C8: 2023 | D8: 2024 | E8: 2025 | F8: 2026 | G8: 2027 | H8: 2028 | I8: 2029 | J8: 2030 | K8: 2031 | L8: 2032 | M8: 2033
A10: A. CAPITAL DE GIRO
A11: Contas a receber | B11: R$ | D11: ='2. Inputs'!D64/'2. Inputs'!D68*'4. DRE'!D26 | E11: ='2. Inputs'!E64/'2. Inputs'!E68*'4. DRE'!E26 | F11: ='2. Inputs'!F64/'2. Inputs'!F68*'4. DRE'!F26 | G11: ='2. Inputs'!G64/'2. Inputs'!G68*'4. DRE'!G26 | H11: ='2. Inputs'!H64/'2. Inputs'!H68*'4. DRE'!H26 | I11: ='2. Inputs'!I64/'2. Inputs'!I68*'4. DRE'!I26 | J11: ='2. Inputs'!J64/'2. Inputs'!J68*'4. DRE'!J26 | K11: ='2. Inputs'!K64/'2. Inputs'!K68*'4. DRE'!K26 | ... M11: ='2. Inputs'!M64/'2. Inputs'!M68*'4. DRE'!M26 | O11: PMR x receita bruta / 360.
A12: Estoques | B12: R$ | D12: ='2. Inputs'!D65/'2. Inputs'!D68*(-'4. DRE'!D31-'4. DRE'!D32) | E12: ='2. Inputs'!E65/'2. Inputs'!E68*(-'4. DRE'!E31-'4. DRE'!E32) | F12: ='2. Inputs'!F65/'2. Inputs'!F68*(-'4. DRE'!F31-'4. DRE'!F32) | G12: ='2. Inputs'!G65/'2. Inputs'!G68*(-'4. DRE'!G31-'4. DRE'!G32) | H12: ='2. Inputs'!H65/'2. Inputs'!H68*(-'4. DRE'!H31-'4. DRE'!H32) | I12: ='2. Inputs'!I65/'2. Inputs'!I68*(-'4. DRE'!I31-'4. DRE'!I32) | J12: ='2. Inputs'!J65/'2. Inputs'!J68*(-'4. DRE'!J31-'4. DRE'!J32) | K12: ='2. Inputs'!K65/'2. Inputs'!K68*(-'4. DRE'!K31-'4. DRE'!K32) | ... M12: ='2. Inputs'!M65/'2. Inputs'!M68*(-'4. DRE'!M31-'4. DRE'!M32) | O12: Giro de estoque x (custo variável + frete) / 360.
A13: Caixa mínimo | B13: R$ | D13: ='2. Inputs'!D67/'2. Inputs'!D68*(-'4. DRE'!D31-'4. DRE'!D32-'4. DRE'!D33-'4. DRE'!D36-'4. DRE'!D37-'4. DRE'!D38) | E13: ='2. Inputs'!E67/'2. Inputs'!E68*(-'4. DRE'!E31-'4. DRE'!E32-'4. DRE'!E33-'4. DRE'!E36-'4. DRE'!E37-'4. DRE'!E38) | F13: ='2. Inputs'!F67/'2. Inputs'!F68*(-'4. DRE'!F31-'4. DRE'!F32-'4. DRE'!F33-'4. DRE'!F36-'4. DRE'!F37-'4. DRE'!F38) | G13: ='2. Inputs'!G67/'2. Inputs'!G68*(-'4. DRE'!G31-'4. DRE'!G32-'4. DRE'!G33-'4. DRE'!G36-'4. DRE'!G37-'4. DRE'!G38) | H13: ='2. Inputs'!H67/'2. Inputs'!H68*(-'4. DRE'!H31-'4. DRE'!H32-'4. DRE'!H33-'4. DRE'!H36-'4. DRE'!H37-'4. DRE'!H38) | I13: ='2. Inputs'!I67/'2. Inputs'!I68*(-'4. DRE'!I31-'4. DRE'!I32-'4. DRE'!I33-'4. DRE'!I36-'4. DRE'!I37-'4. DRE'!I38) | J13: ='2. Inputs'!J67/'2. Inputs'!J68*(-'4. DRE'!J31-'4. DRE'!J32-'4. DRE'!J33-'4. DRE'!J36-'4. DRE'!J37-'4. DRE'!J38) | K13: ='2. Inputs'!K67/'2. Inputs'!K68*(-'4. DRE'!K31-'4. DRE'!K32-'4. DRE'!K33-'4. DRE'!K36-'4. DRE'!K37-'4. DRE'!K38) | ... M13: ='2. Inputs'!M67/'2. Inputs'!M68*(-'4. DRE'!M31-'4. DRE'!M32-'4. DRE'!M33-'4. DRE'!M36-'4. DRE'!M37-'4. DRE'!M38) | O13: Dias x custo CAIXA total / 360. A origem usava o custo total, com depreciação dentro — depreciação não exige caixa.
A14: (−) Fornecedores | B14: R$ | D14: =-'2. Inputs'!D66/'2. Inputs'!D68*(-'4. DRE'!D31-'4. DRE'!D32) | E14: =-'2. Inputs'!E66/'2. Inputs'!E68*(-'4. DRE'!E31-'4. DRE'!E32) | F14: =-'2. Inputs'!F66/'2. Inputs'!F68*(-'4. DRE'!F31-'4. DRE'!F32) | G14: =-'2. Inputs'!G66/'2. Inputs'!G68*(-'4. DRE'!G31-'4. DRE'!G32) | H14: =-'2. Inputs'!H66/'2. Inputs'!H68*(-'4. DRE'!H31-'4. DRE'!H32) | I14: =-'2. Inputs'!I66/'2. Inputs'!I68*(-'4. DRE'!I31-'4. DRE'!I32) | J14: =-'2. Inputs'!J66/'2. Inputs'!J68*(-'4. DRE'!J31-'4. DRE'!J32) | K14: =-'2. Inputs'!K66/'2. Inputs'!K68*(-'4. DRE'!K31-'4. DRE'!K32) | ... M14: =-'2. Inputs'!M66/'2. Inputs'!M68*(-'4. DRE'!M31-'4. DRE'!M32) | O14: PMP x (custo variável + frete) / 360. Na origem a rotação do leite no ano 2 estava 260 em vez de 12 (A-03).
A15: NECESSIDADE DE CAPITAL DE GIRO | B15: R$ | C15: =D15 | D15: =SUM(D11:D14) | E15: =SUM(E11:E14) | F15: =SUM(F11:F14) | G15: =SUM(G11:G14) | H15: =SUM(H11:H14) | I15: =SUM(I11:I14) | J15: =SUM(J11:J14) | K15: =SUM(K11:K14) | ... M15: =SUM(M11:M14) | O15: Ano 0 = necessidade do ano 1: o giro é financiado antes de operar.
A16: Δ capital de giro | B16: R$ | C16: =C15 | D16: =D15-C15 | E16: =E15-D15 | F16: =F15-E15 | G16: =G15-F15 | H16: =H15-G15 | I16: =I15-H15 | J16: =J15-I15 | K16: =K15-J15 | ... M16: =M15-L15
A17: Capital de giro sobre receita bruta | B17: % RB | D17: =IFERROR(D15/'4. DRE'!D26,"") | E17: =IFERROR(E15/'4. DRE'!E26,"") | F17: =IFERROR(F15/'4. DRE'!F26,"") | G17: =IFERROR(G15/'4. DRE'!G26,"") | H17: =IFERROR(H15/'4. DRE'!H26,"") | I17: =IFERROR(I15/'4. DRE'!I26,"") | J17: =IFERROR(J15/'4. DRE'!J26,"") | K17: =IFERROR(K15/'4. DRE'!K26,"") | ... M17: =IFERROR(M15/'4. DRE'!M26,"")
A19: B. FLUXO DE CAIXA LIVRE
A20: EBIT | B20: R$ | D20: ='4. DRE'!D42 | E20: ='4. DRE'!E42 | F20: ='4. DRE'!F42 | G20: ='4. DRE'!G42 | H20: ='4. DRE'!H42 | I20: ='4. DRE'!I42 | J20: ='4. DRE'!J42 | K20: ='4. DRE'!K42 | ... M20: ='4. DRE'!M42
A21: (−) IRPJ + adicional | B21: R$ | D21: ='4. DRE'!D44 | E21: ='4. DRE'!E44 | F21: ='4. DRE'!F44 | G21: ='4. DRE'!G44 | H21: ='4. DRE'!H44 | I21: ='4. DRE'!I44 | J21: ='4. DRE'!J44 | K21: ='4. DRE'!K44 | ... M21: ='4. DRE'!M44
A22: (−) CSLL | B22: R$ | D22: ='4. DRE'!D45 | E22: ='4. DRE'!E45 | F22: ='4. DRE'!F45 | G22: ='4. DRE'!G45 | H22: ='4. DRE'!H45 | I22: ='4. DRE'!I45 | J22: ='4. DRE'!J45 | K22: ='4. DRE'!K45 | ... M22: ='4. DRE'!M45
A23: NOPAT | B23: R$ | D23: =SUM(D20:D22) | E23: =SUM(E20:E22) | F23: =SUM(F20:F22) | G23: =SUM(G20:G22) | H23: =SUM(H20:H22) | I23: =SUM(I20:I22) | J23: =SUM(J20:J22) | K23: =SUM(K20:K22) | ... M23: =SUM(M20:M22) | O23: Lucro operacional após imposto. Sem dívida, NOPAT = lucro líquido.
A24: (+) Depreciação | B24: R$ | D24: ='3. Depreciacao'!D31 | E24: ='3. Depreciacao'!E31 | F24: ='3. Depreciacao'!F31 | G24: ='3. Depreciacao'!G31 | H24: ='3. Depreciacao'!H31 | I24: ='3. Depreciacao'!I31 | J24: ='3. Depreciacao'!J31 | K24: ='3. Depreciacao'!K31 | ... M24: ='3. Depreciacao'!M31 | O24: Despesa sem caixa: sai do lucro e volta aqui.
A25: (−) Δ capital de giro | B25: R$ | C25: =-C16 | D25: =-D16 | E25: =-E16 | F25: =-F16 | G25: =-G16 | H25: =-H16 | I25: =-I16 | J25: =-J16 | ... M25: =-M16
A26: (−) CAPEX | B26: R$ | C26: =-'2. Inputs'!C53 | D26: =-'2. Inputs'!D53 | E26: =-'2. Inputs'!E53 | F26: =-'2. Inputs'!F53 | G26: =-'2. Inputs'!G53 | H26: =-'2. Inputs'!H53 | I26: =-'2. Inputs'!I53 | J26: =-'2. Inputs'!J53 | ... M26: =-'2. Inputs'!M53
A27: (+) Recuperação do capital de giro | B27: R$ | C27: =IF(C$7=10,C15,0) | D27: =IF(D$7=10,D15,0) | E27: =IF(E$7=10,E15,0) | F27: =IF(F$7=10,F15,0) | G27: =IF(G$7=10,G15,0) | H27: =IF(H$7=10,H15,0) | I27: =IF(I$7=10,I15,0) | J27: =IF(J$7=10,J15,0) | ... M27: =IF(M$7=10,M15,0) | O27: Liberação integral no fim do horizonte. Na origem isso acontecia por acidente: a célula do ano 10 estava vazia.
A28: FLUXO DE CAIXA LIVRE | B28: R$ | C28: =C23+SUM(C24:C27) | D28: =D23+SUM(D24:D27) | E28: =E23+SUM(E24:E27) | F28: =F23+SUM(F24:F27) | G28: =G23+SUM(G24:G27) | H28: =H23+SUM(H24:H27) | I28: =I23+SUM(I24:I27) | J28: =J23+SUM(J24:J27) | ... M28: =M23+SUM(M24:M27)
A29: FCL acumulado | B29: R$ | C29: =C28 | D29: =C29+D28 | E29: =D29+E28 | F29: =E29+F28 | G29: =F29+G28 | H29: =G29+H28 | I29: =H29+I28 | J29: =I29+J28 | K29: =J29+K28 | ... M29: =L29+M28
A31: C. COMPARAÇÃO COM O FLUXO DA ORIGEM
A32: FCL da origem | B32: R$ | C32: -21598508 | D32: 7986626.2 | E32: 9362640.7 | F32: 10207909 | G32: 6380315.9 | H32: 14515259 | I32: 16744066 | J32: 20668974 | K32: 24904740 | L32: 29857465 | M32: 51228664 | O32: Origem: 22.2 Fluxo de Caixa!G10:G20.
A33: FCL do modelo | B33: R$ | C33: =C28 | D33: =D28 | E33: =E28 | F33: =F28 | G33: =G28 | H33: =H28 | I33: =I28 | J33: =J28 | ... M33: =M28
A34: Diferença | B34: R$ | C34: =C28-C32 | D34: =D28-D32 | E34: =E28-E32 | F34: =F28-F32 | G34: =G28-G32 | H34: =H28-H32 | I34: =I28-I32 | J34: =J28-J32 | ... M34: =M28-M32 | O34: Volume = produzido (não vendido), comissão de 3% virou despesa, CAPEX de 2028 corrigido, capital de giro reconstruído.

Sheet 6. Valuation
A1: VALUATION — WACC NO LUGAR DA SELIC
A2: A origem descontava a 12,25%, "a Selic vigente em outubro de 2020", sem prêmio de risco nenhum. Aqui a taxa é construída e o impacto no VPL fica explícito.
A7: Ano | C7: 0 | D7: 1 | E7: 2 | F7: 3 | G7: 4 | H7: 5 | I7: 6 | J7: 7 | K7: 8 | L7: 9 | M7: 10 | O7: Observação
A8: Exercício | C8: 2023 | D8: 2024 | E8: 2025 | F8: 2026 | G8: 2027 | H8: 2028 | I8: 2029 | J8: 2030 | K8: 2031 | L8: 2032 | M8: 2033
A10: A. FLUXO DESCONTADO
A11: Fluxo de caixa livre | B11: R$ | C11: ='5. Fluxo de Caixa'!C28 | D11: ='5. Fluxo de Caixa'!D28 | E11: ='5. Fluxo de Caixa'!E28 | F11: ='5. Fluxo de Caixa'!F28 | G11: ='5. Fluxo de Caixa'!G28 | H11: ='5. Fluxo de Caixa'!H28 | I11: ='5. Fluxo de Caixa'!I28 | J11: ='5. Fluxo de Caixa'!J28 | ... M11: ='5. Fluxo de Caixa'!M28
A12: Fator de desconto @ WACC | B12: x | C12: =1/(1+'2. Inputs'!$C$81)^C$7 | D12: =1/(1+'2. Inputs'!$C$81)^D$7 | E12: =1/(1+'2. Inputs'!$C$81)^E$7 | F12: =1/(1+'2. Inputs'!$C$81)^F$7 | G12: =1/(1+'2. Inputs'!$C$81)^G$7 | H12: =1/(1+'2. Inputs'!$C$81)^H$7 | I12: =1/(1+'2. Inputs'!$C$81)^I$7 | J12: =1/(1+'2. Inputs'!$C$81)^J$7 | ... M12: =1/(1+'2. Inputs'!$C$81)^M$7 | O12: Cálculo: 1/(1+WACC)^ano.
A13: FCL descontado @ WACC | B13: R$ | C13: =C11*C12 | D13: =D11*D12 | E13: =E11*E12 | F13: =F11*F12 | G13: =G11*G12 | H13: =H11*H12 | I13: =I11*I12 | J13: =J11*J12 | ... M13: =M11*M12
A14: FCL descontado acumulado | B14: R$ | C14: =C13 | D14: =C14+D13 | E14: =D14+E13 | F14: =E14+F13 | G14: =F14+G13 | H14: =G14+H13 | I14: =H14+I13 | J14: =I14+J13 | K14: =J14+K13 | ... M14: =L14+M13
A15: FCL descontado @ Selic 12,25% (critério da origem) | B15: R$ | C15: =C11/(1+'2. Inputs'!$C$82)^C$7 | D15: =D11/(1+'2. Inputs'!$C$82)^D$7 | E15: =E11/(1+'2. Inputs'!$C$82)^E$7 | F15: =F11/(1+'2. Inputs'!$C$82)^F$7 | G15: =G11/(1+'2. Inputs'!$C$82)^G$7 | H15: =H11/(1+'2. Inputs'!$C$82)^H$7 | I15: =I11/(1+'2. Inputs'!$C$82)^I$7 | J15: =J11/(1+'2. Inputs'!$C$82)^J$7 | ... M15: =M11/(1+'2. Inputs'!$C$82)^M$7
A17: B. INDICADORES
A18: VPL @ WACC | C18: =SUM(C13:M13) | O18: Sem valor terminal — comparável ao critério da origem.
A19: VPL @ Selic 12,25% | C19: =SUM(C15:M15) | O19: Mesmo fluxo, taxa da origem.
A20: Diferença — o preço de usar a Selic como taxa de desconto | C20: =C18-C19 | O20: Quanto de VPL a origem criava só por ignorar o risco do projeto.
A21: TIR | C21: =IRR(C11:M11) | O21: Comparar com o WACC, não com a Selic.
A22: TIR − WACC | C22: =C21-'2. Inputs'!$C$81 | O22: O spread que sobra depois do custo de capital.
A23: Payback simples | C23: =IF(COUNTIF('5. Fluxo de Caixa'!C29:'5. Fluxo de Caixa'!M29,"<0")=0,0,IF(COUNTIF('5. Fluxo de Caixa'!C29:'5. Fluxo de Caixa'!M29,"<0")>=11,"não paga no horizonte",COUNTIF('5. Fluxo de Caixa'!C29:'5. Fluxo de Caixa'!M29,"<0")-1+ABS(INDEX('5. Fluxo de Caixa'!C29:'5. Fluxo de Caixa'!M29,COUNTIF('5. Fluxo de Caixa'!C29:'5. Fluxo de Caixa'!M29,"<0")))/INDEX(C11:M11,COUNTIF('5. Fluxo de Caixa'!C29:'5. Fluxo de Caixa'!M29,"<0")+1))) | O23: Na origem estava DIGITADO como texto ("2,5 anos"), não calculado.
A24: Payback descontado | C24: =IF(COUNTIF(C14:M14,"<0")=0,0,IF(COUNTIF(C14:M14,"<0")>=11,"não paga no horizonte",COUNTIF(C14:M14,"<0")-1+ABS(INDEX(C14:M14,COUNTIF(C14:M14,"<0")))/INDEX(C13:M13,COUNTIF(C14:M14,"<0")+1))) | O24: Descontado ao WACC.
A25: Índice de lucratividade | C25: =SUM(D13:M13)/ABS(C11) | O25: VP dos fluxos dos anos 1–10 sobre o desembolso do ano 0.
A27: C. VALOR TERMINAL — o que a origem não tinha
A28: Valor contábil líquido do imobilizado no ano 10 | B28: R$ | C28: ='3. Depreciacao'!M33 | O28: A planta continua existindo no fim do horizonte. A origem descartava esse valor.
A29: VP do valor residual do imobilizado | B29: R$ | C29: =C28*M12
A30: VPL com valor residual (visão de liquidação) | B30: R$ | C30: =C18+C29
A31: Perpetuidade a partir do FCL do ano 10 | B31: R$ | C31: =IFERROR((M11-'5. Fluxo de Caixa'!M27)*(1+'2. Inputs'!$C$83)/('2. Inputs'!$C$81-'2. Inputs'!$C$83),0) | O31: Cálculo: FCL ano 10 (líquido da liberação do giro) x (1+g) / (WACC − g).
A32: VP da perpetuidade | B32: R$ | C32: =C31*M12
A33: VPL com perpetuidade (visão de continuidade) | B33: R$ | C33: =C18+C32
A34: As três visões não se somam: escolha uma. Liquidação e continuidade são hipóteses alternativas sobre o que acontece no ano 11.
A36: D. PONTE DE VPL — DA ORIGEM AO MODELO
A37: VPL da origem | B37: R$ | C37: 66467823 | O37: Origem: 22.2 Fluxo de Caixa!J36, descontado à Selic de 12,25%.
A38: (1) Efeito de reconstruir o fluxo de caixa | B38: R$ | C38: =C19-C37 | O38: Volume = produzido; comissão de 3% virou despesa; CAPEX de 2028 e 2030 corrigidos; depreciação corrigida; capital de giro reconstruído. Mesma taxa de 12,25%.
A39: (2) Efeito de trocar a Selic pelo WACC | B39: R$ | C39: =C18-C19 | O39: O gap 4 do projeto, isolado.
A40: VPL do modelo @ WACC | B40: R$ | C40: =C37+C38+C39
A41: Check: bate com o VPL @ WACC? | C41: =IF(ABS(C40-C18)<1,"OK","ERRO")

Sheet 7. Cenarios e Sensibilidade
A1: CENÁRIOS, SENSIBILIDADE E PONTO DE EQUILÍBRIO
A2: A origem não tinha cenário, tabela de sensibilidade nem leitura de risco. O cálculo fica na aba 8; aqui só o resultado. Troque o cenário ativo na aba 2. Inputs, célula C5.
A6: A. OS TRÊS CENÁRIOS
A7: Métrica | B7: Pessimista | C7: Base | D7: Otimista | E7: Amplitude
A8: Δ volume | B8: ='8. Motor de Cenarios'!C7 | C8: ='8. Motor de Cenarios'!C8 | D8: ='8. Motor de Cenarios'!C9 | E8: =D8-B8
A9: Δ margem-alvo (p.p.) | B9: ='8. Motor de Cenarios'!D7 | C9: ='8. Motor de Cenarios'!D8 | D9: ='8. Motor de Cenarios'!D9 | E9: =D9-B9
A10: Δ custo variável unitário | B10: ='8. Motor de Cenarios'!E7 | C10: ='8. Motor de Cenarios'!E8 | D10: ='8. Motor de Cenarios'!E9 | E10: =D10-B10
A11: Contingência (% do CAPEX/ano) | B11: ='8. Motor de Cenarios'!F7 | C11: ='8. Motor de Cenarios'!F8 | D11: ='8. Motor de Cenarios'!F9 | E11: =D11-B11
A12: Participação do Sudeste | B12: ='8. Motor de Cenarios'!G7 | C12: ='8. Motor de Cenarios'!G8 | D12: ='8. Motor de Cenarios'!G9 | E12: =D12-B12
A13: EBITDA ano 1 | B13: ='8. Motor de Cenarios'!J7 | C13: ='8. Motor de Cenarios'!J8 | D13: ='8. Motor de Cenarios'!J9 | E13: =D13-B13
A14: Margem EBITDA ano 1 | B14: ='8. Motor de Cenarios'!K7 | C14: ='8. Motor de Cenarios'!K8 | D14: ='8. Motor de Cenarios'!K9 | E14: =D14-B14
A15: EBITDA ano 10 | B15: ='8. Motor de Cenarios'!L7 | C15: ='8. Motor de Cenarios'!L8 | D15: ='8. Motor de Cenarios'!L9 | E15: =D15-B15
A16: VPL @ WACC | B16: ='8. Motor de Cenarios'!H7 | C16: ='8. Motor de Cenarios'!H8 | D16: ='8. Motor de Cenarios'!H9 | E16: =D16-B16
A17: TIR | B17: ='8. Motor de Cenarios'!I7 | C17: ='8. Motor de Cenarios'!I8 | D17: ='8. Motor de Cenarios'!I9 | E17: =D17-B17
A18: Payback descontado (anos) | B18: ='8. Motor de Cenarios'!M7 | C18: ='8. Motor de Cenarios'!M8 | D18: ='8. Motor de Cenarios'!M9 | E18: =D18-B18
A20: Leitura
A21: • O VPL vai de R$ 25 mi a R$ 52 mi entre o pessimista e o otimista. Em nenhum dos três o projeto destrói valor: a TIR nunca cai abaixo de 37%, contra um WACC de 18%.
A22: • A alavanca que mais move o resultado é a margem-alvo, não o volume — e a margem-alvo é a premissa com menos base no caso (sobe 2 p.p. ao ano até 43%, sem estudo de preço).
A23: • No modo 1 de precificação (custo + markup, a lógica da origem), custo mais alto gera VPL mais alto, porque o preço sobe junto. É o comportamento do modelo, não do negócio: mude para o modo 2 na aba 2. Inputs para testar preço de mercado fixo.
A24: • O mix regional quase não move o resultado: o frete é 0,4% do custo e 80% do volume já está no Sudeste. Vale manter a alavanca, mas ela não é onde o risco mora.
A26: B. TORNADO — o que mais move o VPL
A27: Alavanca | B27: Cenário baixo | C27: VPL baixo | D27: Cenário alto | E27: VPL alto | F27: Amplitude | G27: % do VPL base
A28: Volume | B28: ='8. Motor de Cenarios'!B10 | C28: ='8. Motor de Cenarios'!H10 | D28: ='8. Motor de Cenarios'!B11 | E28: ='8. Motor de Cenarios'!H11 | F28: =ABS(E28-C28) | G28: =F28/'8. Motor de Cenarios'!$H$8
A29: Margem-alvo | B29: ='8. Motor de Cenarios'!B12 | C29: ='8. Motor de Cenarios'!H12 | D29: ='8. Motor de Cenarios'!B13 | E29: ='8. Motor de Cenarios'!H13 | F29: =ABS(E29-C29) | G29: =F29/'8. Motor de Cenarios'!$H$8
A30: Custo variável unitário | B30: ='8. Motor de Cenarios'!B14 | C30: ='8. Motor de Cenarios'!H14 | D30: ='8. Motor de Cenarios'!B15 | E30: ='8. Motor de Cenarios'!H15 | F30: =ABS(E30-C30) | G30: =F30/'8. Motor de Cenarios'!$H$8
A31: Contingência | B31: ='8. Motor de Cenarios'!B16 | C31: ='8. Motor de Cenarios'!H16 | D31: ='8. Motor de Cenarios'!B17 | E31: ='8. Motor de Cenarios'!H17 | F31: =ABS(E31-C31) | G31: =F31/'8. Motor de Cenarios'!$H$8
A32: Mix — participação do Sudeste | B32: ='8. Motor de Cenarios'!B18 | C32: ='8. Motor de Cenarios'!H18 | D32: ='8. Motor de Cenarios'!B19 | E32: ='8. Motor de Cenarios'!H19 | F32: =ABS(E32-C32) | G32: =F32/'8. Motor de Cenarios'!$H$8
A34: C. SENSIBILIDADE DO VPL AO CUSTO DE CAPITAL
A35: O fluxo de caixa não depende da taxa: esta linha é exata.
A36: Taxa de desconto | B36: 0.1225 | C36: 0.14 | D36: 0.16 | E36: 0.18 | F36: 0.2 | G36: 0.22 | H36: 0.24
A37: VPL sem valor terminal | B37: =SUMPRODUCT('5. Fluxo de Caixa'!$C$28:$M$28,1/(1+B$36)^'5. Fluxo de Caixa'!$C$7:$M$7) | C37: =SUMPRODUCT('5. Fluxo de Caixa'!$C$28:$M$28,1/(1+C$36)^'5. Fluxo de Caixa'!$C$7:$M$7) | D37: =SUMPRODUCT('5. Fluxo de Caixa'!$C$28:$M$28,1/(1+D$36)^'5. Fluxo de Caixa'!$C$7:$M$7) | E37: =SUMPRODUCT('5. Fluxo de Caixa'!$C$28:$M$28,1/(1+E$36)^'5. Fluxo de Caixa'!$C$7:$M$7) | F37: =SUMPRODUCT('5. Fluxo de Caixa'!$C$28:$M$28,1/(1+F$36)^'5. Fluxo de Caixa'!$C$7:$M$7) | G37: =SUMPRODUCT('5. Fluxo de Caixa'!$C$28:$M$28,1/(1+G$36)^'5. Fluxo de Caixa'!$C$7:$M$7) | H37: =SUMPRODUCT('5. Fluxo de Caixa'!$C$28:$M$28,1/(1+H$36)^'5. Fluxo de Caixa'!$C$7:$M$7)
A38: VPL ao WACC do modelo | B38: ='6. Valuation'!C18
A40: D. VPL COM PERPETUIDADE — taxa de desconto x crescimento na perpetuidade
A41: VPL (R$) | B41: 0 | C41: 0.01 | D41: 0.02 | E41: 0.03 | F41: 0.04
A42: 0.1225 | B42: =IF($A42<=B$41,"n/a",SUMPRODUCT('5. Fluxo de Caixa'!$C$28:$M$28,1/(1+$A42)^'5. Fluxo de Caixa'!$C$7:$M$7)+('5. Fluxo de Caixa'!$M$28-'5. Fluxo de Caixa'!$M$27)*(1+B$41)/($A42-B$41)/(1+$A42)^10) | C42: =IF($A42<=C$41,"n/a",SUMPRODUCT('5. Fluxo de Caixa'!$C$28:$M$28,1/(1+$A42)^'5. Fluxo de Caixa'!$C$7:$M$7)+('5. Fluxo de Caixa'!$M$28-'5. Fluxo de Caixa'!$M$27)*(1+C$41)/($A42-C$41)/(1+$A42)^10) | D42: =IF($A42<=D$41,"n/a",SUMPRODUCT('5. Fluxo de Caixa'!$C$28:$M$28,1/(1+$A42)^'5. Fluxo de Caixa'!$C$7:$M$7)+('5. Fluxo de Caixa'!$M$28-'5. Fluxo de Caixa'!$M$27)*(1+D$41)/($A42-D$41)/(1+$A42)^10) | E42: =IF($A42<=E$41,"n/a",SUMPRODUCT('5. Fluxo de Caixa'!$C$28:$M$28,1/(1+$A42)^'5. Fluxo de Caixa'!$C$7:$M$7)+('5. Fluxo de Caixa'!$M$28-'5. Fluxo de Caixa'!$M$27)*(1+E$41)/($A42-E$41)/(1+$A42)^10) | F42: =IF($A42<=F$41,"n/a",SUMPRODUCT('5. Fluxo de Caixa'!$C$28:$M$28,1/(1+$A42)^'5. Fluxo de Caixa'!$C$7:$M$7)+('5. Fluxo de Caixa'!$M$28-'5. Fluxo de Caixa'!$M$27)*(1+F$41)/($A42-F$41)/(1+$A42)^10)
A43: 0.14 | B43: =IF($A43<=B$41,"n/a",SUMPRODUCT('5. Fluxo de Caixa'!$C$28:$M$28,1/(1+$A43)^'5. Fluxo de Caixa'!$C$7:$M$7)+('5. Fluxo de Caixa'!$M$28-'5. Fluxo de Caixa'!$M$27)*(1+B$41)/($A43-B$41)/(1+$A43)^10) | C43: =IF($A43<=C$41,"n/a",SUMPRODUCT('5. Fluxo de Caixa'!$C$28:$M$28,1/(1+$A43)^'5. Fluxo de Caixa'!$C$7:$M$7)+('5. Fluxo de Caixa'!$M$28-'5. Fluxo de Caixa'!$M$27)*(1+C$41)/($A43-C$41)/(1+$A43)^10) | D43: =IF($A43<=D$41,"n/a",SUMPRODUCT('5. Fluxo de Caixa'!$C$28:$M$28,1/(1+$A43)^'5. Fluxo de Caixa'!$C$7:$M$7)+('5. Fluxo de Caixa'!$M$28-'5. Fluxo de Caixa'!$M$27)*(1+D$41)/($A43-D$41)/(1+$A43)^10) | E43: =IF($A43<=E$41,"n/a",SUMPRODUCT('5. Fluxo de Caixa'!$C$28:$M$28,1/(1+$A43)^'5. Fluxo de Caixa'!$C$7:$M$7)+('5. Fluxo de Caixa'!$M$28-'5. Fluxo de Caixa'!$M$27)*(1+E$41)/($A43-E$41)/(1+$A43)^10) | F43: =IF($A43<=F$41,"n/a",SUMPRODUCT('5. Fluxo de Caixa'!$C$28:$M$28,1/(1+$A43)^'5. Fluxo de Caixa'!$C$7:$M$7)+('5. Fluxo de Caixa'!$M$28-'5. Fluxo de Caixa'!$M$27)*(1+F$41)/($A43-F$41)/(1+$A43)^10)
A44: 0.16 | B44: =IF($A44<=B$41,"n/a",SUMPRODUCT('5. Fluxo de Caixa'!$C$28:$M$28,1/(1+$A44)^'5. Fluxo de Caixa'!$C$7:$M$7)+('5. Fluxo de Caixa'!$M$28-'5. Fluxo de Caixa'!$M$27)*(1+B$41)/($A44-B$41)/(1+$A44)^10) | C44: =IF($A44<=C$41,"n/a",SUMPRODUCT('5. Fluxo de Caixa'!$C$28:$M$28,1/(1+$A44)^'5. Fluxo de Caixa'!$C$7:$M$7)+('5. Fluxo de Caixa'!$M$28-'5. Fluxo de Caixa'!$M$27)*(1+C$41)/($A44-C$41)/(1+$A44)^10) | D44: =IF($A44<=D$41,"n/a",SUMPRODUCT('5. Fluxo de Caixa'!$C$28:$M$28,1/(1+$A44)^'5. Fluxo de Caixa'!$C$7:$M$7)+('5. Fluxo de Caixa'!$M$28-'5. Fluxo de Caixa'!$M$27)*(1+D$41)/($A44-D$41)/(1+$A44)^10) | E44: =IF($A44<=E$41,"n/a",SUMPRODUCT('5. Fluxo de Caixa'!$C$28:$M$28,1/(1+$A44)^'5. Fluxo de Caixa'!$C$7:$M$7)+('5. Fluxo de Caixa'!$M$28-'5. Fluxo de Caixa'!$M$27)*(1+E$41)/($A44-E$41)/(1+$A44)^10) | F44: =IF($A44<=F$41,"n/a",SUMPRODUCT('5. Fluxo de Caixa'!$C$28:$M$28,1/(1+$A44)^'5. Fluxo de Caixa'!$C$7:$M$7)+('5. Fluxo de Caixa'!$M$28-'5. Fluxo de Caixa'!$M$27)*(1+F$41)/($A44-F$41)/(1+$A44)^10)
A45: 0.18 | B45: =IF($A45<=B$41,"n/a",SUMPRODUCT('5. Fluxo de Caixa'!$C$28:$M$28,1/(1+$A45)^'5. Fluxo de Caixa'!$C$7:$M$7)+('5. Fluxo de Caixa'!$M$28-'5. Fluxo de Caixa'!$M$27)*(1+B$41)/($A45-B$41)/(1+$A45)^10) | C45: =IF($A45<=C$41,"n/a",SUMPRODUCT('5. Fluxo de Caixa'!$C$28:$M$28,1/(1+$A45)^'5. Fluxo de Caixa'!$C$7:$M$7)+('5. Fluxo de Caixa'!$M$28-'5. Fluxo de Caixa'!$M$27)*(1+C$41)/($A45-C$41)/(1+$A45)^10) | D45: =IF($A45<=D$41,"n/a",SUMPRODUCT('5. Fluxo de Caixa'!$C$28:$M$28,1/(1+$A45)^'5. Fluxo de Caixa'!$C$7:$M$7)+('5. Fluxo de Caixa'!$M$28-'5. Fluxo de Caixa'!$M$27)*(1+D$41)/($A45-D$41)/(1+$A45)^10) | E45: =IF($A45<=E$41,"n/a",SUMPRODUCT('5. Fluxo de Caixa'!$C$28:$M$28,1/(1+$A45)^'5. Fluxo de Caixa'!$C$7:$M$7)+('5. Fluxo de Caixa'!$M$28-'5. Fluxo de Caixa'!$M$27)*(1+E$41)/($A45-E$41)/(1+$A45)^10) | F45: =IF($A45<=F$41,"n/a",SUMPRODUCT('5. Fluxo de Caixa'!$C$28:$M$28,1/(1+$A45)^'5. Fluxo de Caixa'!$C$7:$M$7)+('5. Fluxo de Caixa'!$M$28-'5. Fluxo de Caixa'!$M$27)*(1+F$41)/($A45-F$41)/(1+$A45)^10)
A46: 0.2 | B46: =IF($A46<=B$41,"n/a",SUMPRODUCT('5. Fluxo de Caixa'!$C$28:$M$28,1/(1+$A46)^'5. Fluxo de Caixa'!$C$7:$M$7)+('5. Fluxo de Caixa'!$M$28-'5. Fluxo de Caixa'!$M$27)*(1+B$41)/($A46-B$41)/(1+$A46)^10) | C46: =IF($A46<=C$41,"n/a",SUMPRODUCT('5. Fluxo de Caixa'!$C$28:$M$28,1/(1+$A46)^'5. Fluxo de Caixa'!$C$7:$M$7)+('5. Fluxo de Caixa'!$M$28-'5. Fluxo de Caixa'!$M$27)*(1+C$41)/($A46-C$41)/(1+$A46)^10) | D46: =IF($A46<=D$41,"n/a",SUMPRODUCT('5. Fluxo de Caixa'!$C$28:$M$28,1/(1+$A46)^'5. Fluxo de Caixa'!$C$7:$M$7)+('5. Fluxo de Caixa'!$M$28-'5. Fluxo de Caixa'!$M$27)*(1+D$41)/($A46-D$41)/(1+$A46)^10) | E46: =IF($A46<=E$41,"n/a",SUMPRODUCT('5. Fluxo de Caixa'!$C$28:$M$28,1/(1+$A46)^'5. Fluxo de Caixa'!$C$7:$M$7)+('5. Fluxo de Caixa'!$M$28-'5. Fluxo de Caixa'!$M$27)*(1+E$41)/($A46-E$41)/(1+$A46)^10) | F46: =IF($A46<=F$41,"n/a",SUMPRODUCT('5. Fluxo de Caixa'!$C$28:$M$28,1/(1+$A46)^'5. Fluxo de Caixa'!$C$7:$M$7)+('5. Fluxo de Caixa'!$M$28-'5. Fluxo de Caixa'!$M$27)*(1+F$41)/($A46-F$41)/(1+$A46)^10)
A47: 0.22 | B47: =IF($A47<=B$41,"n/a",SUMPRODUCT('5. Fluxo de Caixa'!$C$28:$M$28,1/(1+$A47)^'5. Fluxo de Caixa'!$C$7:$M$7)+('5. Fluxo de Caixa'!$M$28-'5. Fluxo de Caixa'!$M$27)*(1+B$41)/($A47-B$41)/(1+$A47)^10) | C47: =IF($A47<=C$41,"n/a",SUMPRODUCT('5. Fluxo de Caixa'!$C$28:$M$28,1/(1+$A47)^'5. Fluxo de Caixa'!$C$7:$M$7)+('5. Fluxo de Caixa'!$M$28-'5. Fluxo de Caixa'!$M$27)*(1+C$41)/($A47-C$41)/(1+$A47)^10) | D47: =IF($A47<=D$41,"n/a",SUMPRODUCT('5. Fluxo de Caixa'!$C$28:$M$28,1/(1+$A47)^'5. Fluxo de Caixa'!$C$7:$M$7)+('5. Fluxo de Caixa'!$M$28-'5. Fluxo de Caixa'!$M$27)*(1+D$41)/($A47-D$41)/(1+$A47)^10) | E47: =IF($A47<=E$41,"n/a",SUMPRODUCT('5. Fluxo de Caixa'!$C$28:$M$28,1/(1+$A47)^'5. Fluxo de Caixa'!$C$7:$M$7)+('5. Fluxo de Caixa'!$M$28-'5. Fluxo de Caixa'!$M$27)*(1+E$41)/($A47-E$41)/(1+$A47)^10) | F47: =IF($A47<=F$41,"n/a",SUMPRODUCT('5. Fluxo de Caixa'!$C$28:$M$28,1/(1+$A47)^'5. Fluxo de Caixa'!$C$7:$M$7)+('5. Fluxo de Caixa'!$M$28-'5. Fluxo de Caixa'!$M$27)*(1+F$41)/($A47-F$41)/(1+$A47)^10)
A48: 0.24 | B48: =IF($A48<=B$41,"n/a",SUMPRODUCT('5. Fluxo de Caixa'!$C$28:$M$28,1/(1+$A48)^'5. Fluxo de Caixa'!$C$7:$M$7)+('5. Fluxo de Caixa'!$M$28-'5. Fluxo de Caixa'!$M$27)*(1+B$41)/($A48-B$41)/(1+$A48)^10) | C48: =IF($A48<=C$41,"n/a",SUMPRODUCT('5. Fluxo de Caixa'!$C$28:$M$28,1/(1+$A48)^'5. Fluxo de Caixa'!$C$7:$M$7)+('5. Fluxo de Caixa'!$M$28-'5. Fluxo de Caixa'!$M$27)*(1+C$41)/($A48-C$41)/(1+$A48)^10) | D48: =IF($A48<=D$41,"n/a",SUMPRODUCT('5. Fluxo de Caixa'!$C$28:$M$28,1/(1+$A48)^'5. Fluxo de Caixa'!$C$7:$M$7)+('5. Fluxo de Caixa'!$M$28-'5. Fluxo de Caixa'!$M$27)*(1+D$41)/($A48-D$41)/(1+$A48)^10) | E48: =IF($A48<=E$41,"n/a",SUMPRODUCT('5. Fluxo de Caixa'!$C$28:$M$28,1/(1+$A48)^'5. Fluxo de Caixa'!$C$7:$M$7)+('5. Fluxo de Caixa'!$M$28-'5. Fluxo de Caixa'!$M$27)*(1+E$41)/($A48-E$41)/(1+$A48)^10) | F48: =IF($A48<=F$41,"n/a",SUMPRODUCT('5. Fluxo de Caixa'!$C$28:$M$28,1/(1+$A48)^'5. Fluxo de Caixa'!$C$7:$M$7)+('5. Fluxo de Caixa'!$M$28-'5. Fluxo de Caixa'!$M$27)*(1+F$41)/($A48-F$41)/(1+$A48)^10)
A50: E. PONTO DE EQUILÍBRIO
A51: Ano | C51: 0 | D51: 1 | E51: 2 | F51: 3 | G51: 4 | H51: 5 | I51: 6 | J51: 7 | K51: 8 | L51: 9 | M51: 10
A52: Exercício | C52: 2023 | D52: 2024 | E52: 2025 | F52: 2026 | G52: 2027 | H52: 2028 | I52: 2029 | J52: 2030 | K52: 2031 | L52: 2032 | M52: 2033
A53: Margem de contribuição unitária | B53: R$/un | D53: ='4. DRE'!D55 | E53: ='4. DRE'!E55 | F53: ='4. DRE'!F55 | G53: ='4. DRE'!G55 | H53: ='4. DRE'!H55 | I53: ='4. DRE'!I55 | J53: ='4. DRE'!J55 | K53: ='4. DRE'!K55 | ... M53: ='4. DRE'!M55
A54: Custo fixo de caixa | B54: R$ | D54: ='4. DRE'!D56 | E54: ='4. DRE'!E56 | F54: ='4. DRE'!F56 | G54: ='4. DRE'!G56 | H54: ='4. DRE'!H56 | I54: ='4. DRE'!I56 | J54: ='4. DRE'!J56 | K54: ='4. DRE'!K56 | ... M54: ='4. DRE'!M56
A55: Depreciação | B55: R$ | D55: =-'4. DRE'!D41 | E55: =-'4. DRE'!E41 | F55: =-'4. DRE'!F41 | G55: =-'4. DRE'!G41 | H55: =-'4. DRE'!H41 | I55: =-'4. DRE'!I41 | J55: =-'4. DRE'!J41 | K55: =-'4. DRE'!K41 | ... M55: =-'4. DRE'!M41
A56: Ponto de equilíbrio contábil | B56: un/ano | D56: =(D54+D55)/D53 | E56: =(E54+E55)/E53 | F56: =(F54+F55)/F53 | G56: =(G54+G55)/G53 | H56: =(H54+H55)/H53 | I56: =(I54+I55)/I53 | J56: =(J54+J55)/J53 | K56: =(K54+K55)/K53 | ... M56: =(M54+M55)/M53 | O56: Cobre custo fixo de caixa + depreciação. É o que a origem calculava.
A57: Ponto de equilíbrio de caixa | B57: un/ano | D57: =D54/D53 | E57: =E54/E53 | F57: =F54/F53 | G57: =G54/G53 | H57: =H54/H53 | I57: =I54/I53 | J57: =J54/J53 | K57: =K54/K53 | ... M57: =M54/M53 | O57: Cobre só o custo fixo que exige caixa. É o volume abaixo do qual a planta queima caixa.
A58: Volume do modelo | B58: un/ano | D58: ='4. DRE'!D24 | E58: ='4. DRE'!E24 | F58: ='4. DRE'!F24 | G58: ='4. DRE'!G24 | H58: ='4. DRE'!H24 | I58: ='4. DRE'!I24 | J58: ='4. DRE'!J24 | K58: ='4. DRE'!K24 | ... M58: ='4. DRE'!M24
A59: Ocupação no ponto de equilíbrio contábil | B59: % do volume | D59: =D56/D58 | E59: =E56/E58 | F59: =F56/F58 | G59: =G56/G58 | H59: =H56/H58 | I59: =I56/I58 | J59: =J56/J58 | K59: =K56/K58 | ... M59: =M56/M58
A60: MARGEM DE SEGURANÇA | B60: % do volume | D60: =1-D56/D58 | E60: =1-E56/E58 | F60: =1-F56/F58 | G60: =1-G56/G58 | H60: =1-H56/H58 | I60: =1-I56/I58 | J60: =1-J56/J58 | K60: =1-K56/K58 | ... M60: =1-M56/M58 | O60: Quanto o volume pode cair antes de o resultado virar prejuízo.
A61: Alavancagem operacional | B61: x | D61: =IFERROR('4. DRE'!D34/'4. DRE'!D39,"") | E61: =IFERROR('4. DRE'!E34/'4. DRE'!E39,"") | F61: =IFERROR('4. DRE'!F34/'4. DRE'!F39,"") | G61: =IFERROR('4. DRE'!G34/'4. DRE'!G39,"") | H61: =IFERROR('4. DRE'!H34/'4. DRE'!H39,"") | I61: =IFERROR('4. DRE'!I34/'4. DRE'!I39,"") | J61: =IFERROR('4. DRE'!J34/'4. DRE'!J39,"") | K61: =IFERROR('4. DRE'!K34/'4. DRE'!K39,"") | ... M61: =IFERROR('4. DRE'!M34/'4. DRE'!M39,"") | O61: Cálculo: margem de contribuição / EBITDA. Quanto o EBITDA varia para cada 1% de volume.
A63: Leitura de negócio
A64: • A planta opera bem acima do ponto de equilíbrio em todo o horizonte, e a margem de segurança aumenta ano a ano porque o custo fixo é quase todo herdado do CAPEX e não cresce com o volume.
A65: • O ponto de equilíbrio de caixa é menor que o contábil pela depreciação: mesmo abaixo do PE contábil, a planta ainda gera caixa. É o número que importa numa crise de demanda.
A66: • A alavancagem operacional alta é a outra face disso: cada 1% de volume a menos custa mais de 1% de EBITDA. O risco do caso não é margem, é volume — e o volume vem de uma premissa de 10% de crescimento de market share ao ano que o caso nunca sustentou.

Sheet 8. Motor de Cenarios
A1: MOTOR DE CENÁRIOS (camada de cálculo)
A2: Cada corrida recalcula o modelo inteiro com um jogo de alavancas. A aba 7 só apresenta o resultado. Não editar nada aqui: as alavancas ficam na aba 2. Inputs.
N5: auxiliar: FCL descontado acumulado
A6: N° | B6: Corrida | C6: Δ volume | D6: Δ margem (p.p.) | E6: Δ custo var. | F6: Contingência | G6: Part. Sudeste | H6: VPL @ WACC | I6: TIR | J6: EBITDA ano 1 | K6: Margem EBITDA ano 1 | L6: EBITDA ano 10 | M6: Payback desc.
A7: 1 | B7: Pessimista | C7: ='2. Inputs'!$C$88 | D7: ='2. Inputs'!$C$89 | E7: ='2. Inputs'!$C$90 | F7: ='2. Inputs'!$C$91 | G7: ='2. Inputs'!$C$92 | H7: =SUMPRODUCT(C44:M44,1/(1+'2. Inputs'!$C$81)^C22:M22) | I7: =IRR(C44:M44) | J7: =D38 | K7: =D38/D37 | L7: =M38 | M7: =IF(COUNTIF($N$44:$X$44,"<0")=0,0,IF(COUNTIF($N$44:$X$44,"<0")>=11,"não paga no horizonte",COUNTIF($N$44:$X$44,"<0")-1+ABS(INDEX($N$44:$X$44,COUNTIF($N$44:$X$44,"<0")))/(INDEX($N$44:$X$44,COUNTIF($N$44:$X$44,"<0")+1)-INDEX($N$44:$X$44,COUNTIF($N$44:$X$44,"<0")))))
A8: 2 | B8: Base | C8: ='2. Inputs'!$D$88 | D8: ='2. Inputs'!$D$89 | E8: ='2. Inputs'!$D$90 | F8: ='2. Inputs'!$D$91 | G8: ='2. Inputs'!$D$92 | H8: =SUMPRODUCT(C69:M69,1/(1+'2. Inputs'!$C$81)^C47:M47) | I8: =IRR(C69:M69) | J8: =D63 | K8: =D63/D62 | L8: =M63 | M8: =IF(COUNTIF($N$69:$X$69,"<0")=0,0,IF(COUNTIF($N$69:$X$69,"<0")>=11,"não paga no horizonte",COUNTIF($N$69:$X$69,"<0")-1+ABS(INDEX($N$69:$X$69,COUNTIF($N$69:$X$69,"<0")))/(INDEX($N$69:$X$69,COUNTIF($N$69:$X$69,"<0")+1)-INDEX($N$69:$X$69,COUNTIF($N$69:$X$69,"<0")))))
A9: 3 | B9: Otimista | C9: ='2. Inputs'!$E$88 | D9: ='2. Inputs'!$E$89 | E9: ='2. Inputs'!$E$90 | F9: ='2. Inputs'!$E$91 | G9: ='2. Inputs'!$E$92 | H9: =SUMPRODUCT(C94:M94,1/(1+'2. Inputs'!$C$81)^C72:M72) | I9: =IRR(C94:M94) | J9: =D88 | K9: =D88/D87 | L9: =M88 | M9: =IF(COUNTIF($N$94:$X$94,"<0")=0,0,IF(COUNTIF($N$94:$X$94,"<0")>=11,"não paga no horizonte",COUNTIF($N$94:$X$94,"<0")-1+ABS(INDEX($N$94:$X$94,COUNTIF($N$94:$X$94,"<0")))/(INDEX($N$94:$X$94,COUNTIF($N$94:$X$94,"<0")+1)-INDEX($N$94:$X$94,COUNTIF($N$94:$X$94,"<0")))))
A10: 4 | B10: Volume −10% | C10: -0.1 | D10: ='2. Inputs'!$D$89 | E10: ='2. Inputs'!$D$90 | F10: ='2. Inputs'!$D$91 | G10: ='2. Inputs'!$D$92 | H10: =SUMPRODUCT(C119:M119,1/(1+'2. Inputs'!$C$81)^C97:M97) | I10: =IRR(C119:M119) | J10: =D113 | K10: =D113/D112 | L10: =M113 | M10: =IF(COUNTIF($N$119:$X$119,"<0")=0,0,IF(COUNTIF($N$119:$X$119,"<0")>=11,"não paga no horizonte",COUNTIF($N$119:$X$119,"<0")-1+ABS(INDEX($N$119:$X$119,COUNTIF($N$119:$X$119,"<0")))/(INDEX($N$119:$X$119,COUNTIF($N$119:$X$119,"<0")+1)-INDEX($N$119:$X$119,COUNTIF($N$119:$X$119,"<0")))))
A11: 5 | B11: Volume +10% | C11: 0.1 | D11: ='2. Inputs'!$D$89 | E11: ='2. Inputs'!$D$90 | F11: ='2. Inputs'!$D$91 | G11: ='2. Inputs'!$D$92 | H11: =SUMPRODUCT(C144:M144,1/(1+'2. Inputs'!$C$81)^C122:M122) | I11: =IRR(C144:M144) | J11: =D138 | K11: =D138/D137 | L11: =M138 | M11: =IF(COUNTIF($N$144:$X$144,"<0")=0,0,IF(COUNTIF($N$144:$X$144,"<0")>=11,"não paga no horizonte",COUNTIF($N$144:$X$144,"<0")-1+ABS(INDEX($N$144:$X$144,COUNTIF($N$144:$X$144,"<0")))/(INDEX($N$144:$X$144,COUNTIF($N$144:$X$144,"<0")+1)-INDEX($N$144:$X$144,COUNTIF($N$144:$X$144,"<0")))))
A12: 6 | B12: Margem-alvo −3 p.p. | C12: ='2. Inputs'!$D$88 | D12: -0.03 | E12: ='2. Inputs'!$D$90 | F12: ='2. Inputs'!$D$91 | G12: ='2. Inputs'!$D$92 | H12: =SUMPRODUCT(C169:M169,1/(1+'2. Inputs'!$C$81)^C147:M147) | I12: =IRR(C169:M169) | J12: =D163 | K12: =D163/D162 | L12: =M163 | M12: =IF(COUNTIF($N$169:$X$169,"<0")=0,0,IF(COUNTIF($N$169:$X$169,"<0")>=11,"não paga no horizonte",COUNTIF($N$169:$X$169,"<0")-1+ABS(INDEX($N$169:$X$169,COUNTIF($N$169:$X$169,"<0")))/(INDEX($N$169:$X$169,COUNTIF($N$169:$X$169,"<0")+1)-INDEX($N$169:$X$169,COUNTIF($N$169:$X$169,"<0")))))
A13: 7 | B13: Margem-alvo +3 p.p. | C13: ='2. Inputs'!$D$88 | D13: 0.03 | E13: ='2. Inputs'!$D$90 | F13: ='2. Inputs'!$D$91 | G13: ='2. Inputs'!$D$92 | H13: =SUMPRODUCT(C194:M194,1/(1+'2. Inputs'!$C$81)^C172:M172) | I13: =IRR(C194:M194) | J13: =D188 | K13: =D188/D187 | L13: =M188 | M13: =IF(COUNTIF($N$194:$X$194,"<0")=0,0,IF(COUNTIF($N$194:$X$194,"<0")>=11,"não paga no horizonte",COUNTIF($N$194:$X$194,"<0")-1+ABS(INDEX($N$194:$X$194,COUNTIF($N$194:$X$194,"<0")))/(INDEX($N$194:$X$194,COUNTIF($N$194:$X$194,"<0")+1)-INDEX($N$194:$X$194,COUNTIF($N$194:$X$194,"<0")))))
A14: 8 | B14: Custo variável +10% | C14: ='2. Inputs'!$D$88 | D14: ='2. Inputs'!$D$89 | E14: 0.1 | F14: ='2. Inputs'!$D$91 | G14: ='2. Inputs'!$D$92 | H14: =SUMPRODUCT(C219:M219,1/(1+'2. Inputs'!$C$81)^C197:M197) | I14: =IRR(C219:M219) | J14: =D213 | K14: =D213/D212 | L14: =M213 | M14: =IF(COUNTIF($N$219:$X$219,"<0")=0,0,IF(COUNTIF($N$219:$X$219,"<0")>=11,"não paga no horizonte",COUNTIF($N$219:$X$219,"<0")-1+ABS(INDEX($N$219:$X$219,COUNTIF($N$219:$X$219,"<0")))/(INDEX($N$219:$X$219,COUNTIF($N$219:$X$219,"<0")+1)-INDEX($N$219:$X$219,COUNTIF($N$219:$X$219,"<0")))))
A15: 9 | B15: Custo variável −10% | C15: ='2. Inputs'!$D$88 | D15: ='2. Inputs'!$D$89 | E15: -0.1 | F15: ='2. Inputs'!$D$91 | G15: ='2. Inputs'!$D$92 | H15: =SUMPRODUCT(C244:M244,1/(1+'2. Inputs'!$C$81)^C222:M222) | I15: =IRR(C244:M244) | J15: =D238 | K15: =D238/D237 | L15: =M238 | M15: =IF(COUNTIF($N$244:$X$244,"<0")=0,0,IF(COUNTIF($N$244:$X$244,"<0")>=11,"não paga no horizonte",COUNTIF($N$244:$X$244,"<0")-1+ABS(INDEX($N$244:$X$244,COUNTIF($N$244:$X$244,"<0")))/(INDEX($N$244:$X$244,COUNTIF($N$244:$X$244,"<0")+1)-INDEX($N$244:$X$244,COUNTIF($N$244:$X$244,"<0")))))
A16: 10 | B16: Contingência 15% | C16: ='2. Inputs'!$D$88 | D16: ='2. Inputs'!$D$89 | E16: ='2. Inputs'!$D$90 | F16: 0.15 | G16: ='2. Inputs'!$D$92 | H16: =SUMPRODUCT(C269:M269,1/(1+'2. Inputs'!$C$81)^C247:M247) | I16: =IRR(C269:M269) | J16: =D263 | K16: =D263/D262 | L16: =M263 | M16: =IF(COUNTIF($N$269:$X$269,"<0")=0,0,IF(COUNTIF($N$269:$X$269,"<0")>=11,"não paga no horizonte",COUNTIF($N$269:$X$269,"<0")-1+ABS(INDEX($N$269:$X$269,COUNTIF($N$269:$X$269,"<0")))/(INDEX($N$269:$X$269,COUNTIF($N$269:$X$269,"<0")+1)-INDEX($N$269:$X$269,COUNTIF($N$269:$X$269,"<0")))))
A17: 11 | B17: Contingência 5% | C17: ='2. Inputs'!$D$88 | D17: ='2. Inputs'!$D$89 | E17: ='2. Inputs'!$D$90 | F17: 0.05 | G17: ='2. Inputs'!$D$92 | H17: =SUMPRODUCT(C294:M294,1/(1+'2. Inputs'!$C$81)^C272:M272) | I17: =IRR(C294:M294) | J17: =D288 | K17: =D288/D287 | L17: =M288 | M17: =IF(COUNTIF($N$294:$X$294,"<0")=0,0,IF(COUNTIF($N$294:$X$294,"<0")>=11,"não paga no horizonte",COUNTIF($N$294:$X$294,"<0")-1+ABS(INDEX($N$294:$X$294,COUNTIF($N$294:$X$294,"<0")))/(INDEX($N$294:$X$294,COUNTIF($N$294:$X$294,"<0")+1)-INDEX($N$294:$X$294,COUNTIF($N$294:$X$294,"<0")))))
A18: 12 | B18: Sudeste 70% | C18: ='2. Inputs'!$D$88 | D18: ='2. Inputs'!$D$89 | E18: ='2. Inputs'!$D$90 | F18: ='2. Inputs'!$D$91 | G18: 0.7 | H18: =SUMPRODUCT(C319:M319,1/(1+'2. Inputs'!$C$81)^C297:M297) | I18: =IRR(C319:M319) | J18: =D313 | K18: =D313/D312 | L18: =M313 | M18: =IF(COUNTIF($N$319:$X$319,"<0")=0,0,IF(COUNTIF($N$319:$X$319,"<0")>=11,"não paga no horizonte",COUNTIF($N$319:$X$319,"<0")-1+ABS(INDEX($N$319:$X$319,COUNTIF($N$319:$X$319,"<0")))/(INDEX($N$319:$X$319,COUNTIF($N$319:$X$319,"<0")+1)-INDEX($N$319:$X$319,COUNTIF($N$319:$X$319,"<0")))))
A19: 13 | B19: Sudeste 90% | C19: ='2. Inputs'!$D$88 | D19: ='2. Inputs'!$D$89 | E19: ='2. Inputs'!$D$90 | F19: ='2. Inputs'!$D$91 | G19: 0.9 | H19: =SUMPRODUCT(C344:M344,1/(1+'2. Inputs'!$C$81)^C322:M322) | I19: =IRR(C344:M344) | J19: =D338 | K19: =D338/D337 | L19: =M338 | M19: =IF(COUNTIF($N$344:$X$344,"<0")=0,0,IF(COUNTIF($N$344:$X$344,"<0")>=11,"não paga no horizonte",COUNTIF($N$344:$X$344,"<0")-1+ABS(INDEX($N$344:$X$344,COUNTIF($N$344:$X$344,"<0")))/(INDEX($N$344:$X$344,COUNTIF($N$344:$X$344,"<0")+1)-INDEX($N$344:$X$344,COUNTIF($N$344:$X$344,"<0")))))
A21: CORRIDA 1 — Pessimista
A22: Ano | C22: 0 | D22: 1 | E22: 2 | F22: 3 | G22: 4 | H22: 5 | I22: 6 | J22: 7 | K22: 8 | L22: 9 | M22: 10
A23: Volume (un) | D23: ='2. Inputs'!D11*(1+$C$7) | E23: ='2. Inputs'!E11*(1+$C$7) | F23: ='2. Inputs'!F11*(1+$C$7) | G23: ='2. Inputs'!G11*(1+$C$7) | H23: ='2. Inputs'!H11*(1+$C$7) | I23: ='2. Inputs'!I11*(1+$C$7) | J23: ='2. Inputs'!J11*(1+$C$7) | K23: ='2. Inputs'!K11*(1+$C$7) | ... M23: ='2. Inputs'!M11*(1+$C$7)
A24: Frete unitário (R$/un) | B24: =('2. Inputs'!D25*'2. Inputs'!$C$96+'2. Inputs'!D26*'2. Inputs'!$C$97+'2. Inputs'!D27*'2. Inputs'!$C$98+'2. Inputs'!D28*'2. Inputs'!$C$99)/'2. Inputs'!$C$100 | D24: =$G$7*'2. Inputs'!D24+(1-$G$7)*$B$24 | E24: =$G$7*'2. Inputs'!E24+(1-$G$7)*$B$24 | F24: =$G$7*'2. Inputs'!F24+(1-$G$7)*$B$24 | G24: =$G$7*'2. Inputs'!G24+(1-$G$7)*$B$24 | H24: =$G$7*'2. Inputs'!H24+(1-$G$7)*$B$24 | I24: =$G$7*'2. Inputs'!I24+(1-$G$7)*$B$24 | J24: =$G$7*'2. Inputs'!J24+(1-$G$7)*$B$24 | K24: =$G$7*'2. Inputs'!K24+(1-$G$7)*$B$24 | ... M24: =$G$7*'2. Inputs'!M24+(1-$G$7)*$B$24 | O24: Coluna B: frete unitário médio fora do Sudeste, nas proporções da origem (Sul 5%, NE 3%, N 2%, CO 10%).
A25: Custo variável unitário (R$/un) | D25: ='2. Inputs'!D43*(1+$E$7) | E25: ='2. Inputs'!E43*(1+$E$7) | F25: ='2. Inputs'!F43*(1+$E$7) | G25: ='2. Inputs'!G43*(1+$E$7) | H25: ='2. Inputs'!H43*(1+$E$7) | I25: ='2. Inputs'!I43*(1+$E$7) | J25: ='2. Inputs'!J43*(1+$E$7) | K25: ='2. Inputs'!K43*(1+$E$7) | ... M25: ='2. Inputs'!M43*(1+$E$7)
A26: Markup total (%) | D26: ='2. Inputs'!D32+'2. Inputs'!D33+'2. Inputs'!D34+'2. Inputs'!D35+'2. Inputs'!D36+$D$7 | E26: ='2. Inputs'!E32+'2. Inputs'!E33+'2. Inputs'!E34+'2. Inputs'!E35+'2. Inputs'!E36+$D$7 | F26: ='2. Inputs'!F32+'2. Inputs'!F33+'2. Inputs'!F34+'2. Inputs'!F35+'2. Inputs'!F36+$D$7 | G26: ='2. Inputs'!G32+'2. Inputs'!G33+'2. Inputs'!G34+'2. Inputs'!G35+'2. Inputs'!G36+$D$7 | H26: ='2. Inputs'!H32+'2. Inputs'!H33+'2. Inputs'!H34+'2. Inputs'!H35+'2. Inputs'!H36+$D$7 | I26: ='2. Inputs'!I32+'2. Inputs'!I33+'2. Inputs'!I34+'2. Inputs'!I35+'2. Inputs'!I36+$D$7 | J26: ='2. Inputs'!J32+'2. Inputs'!J33+'2. Inputs'!J34+'2. Inputs'!J35+'2. Inputs'!J36+$D$7 | K26: ='2. Inputs'!K32+'2. Inputs'!K33+'2. Inputs'!K34+'2. Inputs'!K35+'2. Inputs'!K36+$D$7 | ... M26: ='2. Inputs'!M32+'2. Inputs'!M33+'2. Inputs'!M34+'2. Inputs'!M35+'2. Inputs'!M36+$D$7
A27: Custo variável (R$) | D27: =D23*D25 | E27: =E23*E25 | F27: =F23*F25 | G27: =G23*G25 | H27: =H23*H25 | I27: =I23*I25 | J27: =J23*J25 | K27: =K23*K25 | ... M27: =M23*M25
A28: Frete (R$) | D28: =D23*D24 | E28: =E23*E24 | F28: =F23*F24 | G28: =G23*G24 | H28: =H23*H24 | I28: =I23*I24 | J28: =J23*J24 | K28: =K23*K24 | ... M28: =M23*M24
A29: Custo fixo de estrutura (R$) | D29: ='2. Inputs'!D46 | E29: ='2. Inputs'!E46 | F29: ='2. Inputs'!F46 | G29: ='2. Inputs'!G46 | H29: ='2. Inputs'!H46 | I29: ='2. Inputs'!I46 | J29: ='2. Inputs'!J46 | K29: ='2. Inputs'!K46 | ... M29: ='2. Inputs'!M46
A30: Manutenção e seguro (R$) | D30: =('2. Inputs'!D47+'2. Inputs'!D48)*'2. Inputs'!D54 | E30: =('2. Inputs'!E47+'2. Inputs'!E48)*'2. Inputs'!E54 | F30: =('2. Inputs'!F47+'2. Inputs'!F48)*'2. Inputs'!F54 | G30: =('2. Inputs'!G47+'2. Inputs'!G48)*'2. Inputs'!G54 | H30: =('2. Inputs'!H47+'2. Inputs'!H48)*'2. Inputs'!H54 | I30: =('2. Inputs'!I47+'2. Inputs'!I48)*'2. Inputs'!I54 | J30: =('2. Inputs'!J47+'2. Inputs'!J48)*'2. Inputs'!J54 | K30: =('2. Inputs'!K47+'2. Inputs'!K48)*'2. Inputs'!K54 | ... M30: =('2. Inputs'!M47+'2. Inputs'!M48)*'2. Inputs'!M54
A31: Contingência (R$) | D31: =$F$7*'2. Inputs'!D54 | E31: =$F$7*'2. Inputs'!E54 | F31: =$F$7*'2. Inputs'!F54 | G31: =$F$7*'2. Inputs'!G54 | H31: =$F$7*'2. Inputs'!H54 | I31: =$F$7*'2. Inputs'!I54 | J31: =$F$7*'2. Inputs'!J54 | K31: =$F$7*'2. Inputs'!K54 | ... M31: =$F$7*'2. Inputs'!M54
A32: Depreciação (R$) | D32: ='3. Depreciacao'!D31 | E32: ='3. Depreciacao'!E31 | F32: ='3. Depreciacao'!F31 | G32: ='3. Depreciacao'!G31 | H32: ='3. Depreciacao'!H31 | I32: ='3. Depreciacao'!I31 | J32: ='3. Depreciacao'!J31 | K32: ='3. Depreciacao'!K31 | ... M32: ='3. Depreciacao'!M31
A33: Custo total (R$) | D33: =SUM(D27:D32) | E33: =SUM(E27:E32) | F33: =SUM(F27:F32) | G33: =SUM(G27:G32) | H33: =SUM(H27:H32) | I33: =SUM(I27:I32) | J33: =SUM(J27:J32) | K33: =SUM(K27:K32) | ... M33: =SUM(M27:M32)
A34: Preço bruto unitário (R$/un) | D34: =IF('2. Inputs'!$C$38=1,D33/D23/(1-D26),'2. Inputs'!D39) | E34: =IF('2. Inputs'!$C$38=1,E33/E23/(1-E26),'2. Inputs'!E39) | F34: =IF('2. Inputs'!$C$38=1,F33/F23/(1-F26),'2. Inputs'!F39) | G34: =IF('2. Inputs'!$C$38=1,G33/G23/(1-G26),'2. Inputs'!G39) | H34: =IF('2. Inputs'!$C$38=1,H33/H23/(1-H26),'2. Inputs'!H39) | I34: =IF('2. Inputs'!$C$38=1,I33/I23/(1-I26),'2. Inputs'!I39) | J34: =IF('2. Inputs'!$C$38=1,J33/J23/(1-J26),'2. Inputs'!J39) | K34: =IF('2. Inputs'!$C$38=1,K33/K23/(1-K26),'2. Inputs'!K39) | ... M34: =IF('2. Inputs'!$C$38=1,M33/M23/(1-M26),'2. Inputs'!M39)
A35: Receita bruta (R$) | D35: =D23*D34 | E35: =E23*E34 | F35: =F23*F34 | G35: =G23*G34 | H35: =H23*H34 | I35: =I23*I34 | J35: =J23*J34 | K35: =K23*K34 | ... M35: =M23*M34
A36: Comissão (R$) | D36: ='2. Inputs'!D35*D35 | E36: ='2. Inputs'!E35*E35 | F36: ='2. Inputs'!F35*F35 | G36: ='2. Inputs'!G35*G35 | H36: ='2. Inputs'!H35*H35 | I36: ='2. Inputs'!I35*I35 | J36: ='2. Inputs'!J35*J35 | K36: ='2. Inputs'!K35*K35 | ... M36: ='2. Inputs'!M35*M35
A37: Receita líquida (R$) | D37: =D35*(1-'2. Inputs'!D32-'2. Inputs'!D33-'2. Inputs'!D34) | E37: =E35*(1-'2. Inputs'!E32-'2. Inputs'!E33-'2. Inputs'!E34) | F37: =F35*(1-'2. Inputs'!F32-'2. Inputs'!F33-'2. Inputs'!F34) | G37: =G35*(1-'2. Inputs'!G32-'2. Inputs'!G33-'2. Inputs'!G34) | H37: =H35*(1-'2. Inputs'!H32-'2. Inputs'!H33-'2. Inputs'!H34) | I37: =I35*(1-'2. Inputs'!I32-'2. Inputs'!I33-'2. Inputs'!I34) | J37: =J35*(1-'2. Inputs'!J32-'2. Inputs'!J33-'2. Inputs'!J34) | K37: =K35*(1-'2. Inputs'!K32-'2. Inputs'!K33-'2. Inputs'!K34) | ... M37: =M35*(1-'2. Inputs'!M32-'2. Inputs'!M33-'2. Inputs'!M34)
A38: EBITDA (R$) | D38: =D37-D27-D28-D36-D29-D30-D31 | E38: =E37-E27-E28-E36-E29-E30-E31 | F38: =F37-F27-F28-F36-F29-F30-F31 | G38: =G37-G27-G28-G36-G29-G30-G31 | H38: =H37-H27-H28-H36-H29-H30-H31 | I38: =I37-I27-I28-I36-I29-I30-I31 | J38: =J37-J27-J28-J36-J29-J30-J31 | K38: =K37-K27-K28-K36-K29-K30-K31 | ... M38: =M37-M27-M28-M36-M29-M30-M31
A39: EBIT (R$) | D39: =D38-D32 | E39: =E38-E32 | F39: =F38-F32 | G39: =G38-G32 | H39: =H38-H32 | I39: =I38-I32 | J39: =J38-J32 | K39: =K38-K32 | ... M39: =M38-M32
A40: IRPJ + adicional + CSLL (R$) | D40: =IF(D39>0,'2. Inputs'!D58*D39+'2. Inputs'!D59*MAX(0,D39-'2. Inputs'!D60)+'2. Inputs'!D61*D39,0) | E40: =IF(E39>0,'2. Inputs'!E58*E39+'2. Inputs'!E59*MAX(0,E39-'2. Inputs'!E60)+'2. Inputs'!E61*E39,0) | F40: =IF(F39>0,'2. Inputs'!F58*F39+'2. Inputs'!F59*MAX(0,F39-'2. Inputs'!F60)+'2. Inputs'!F61*F39,0) | G40: =IF(G39>0,'2. Inputs'!G58*G39+'2. Inputs'!G59*MAX(0,G39-'2. Inputs'!G60)+'2. Inputs'!G61*G39,0) | H40: =IF(H39>0,'2. Inputs'!H58*H39+'2. Inputs'!H59*MAX(0,H39-'2. Inputs'!H60)+'2. Inputs'!H61*H39,0) | I40: =IF(I39>0,'2. Inputs'!I58*I39+'2. Inputs'!I59*MAX(0,I39-'2. Inputs'!I60)+'2. Inputs'!I61*I39,0) | J40: =IF(J39>0,'2. Inputs'!J58*J39+'2. Inputs'!J59*MAX(0,J39-'2. Inputs'!J60)+'2. Inputs'!J61*J39,0) | K40: =IF(K39>0,'2. Inputs'!K58*K39+'2. Inputs'!K59*MAX(0,K39-'2. Inputs'!K60)+'2. Inputs'!K61*K39,0) | ... M40: =IF(M39>0,'2. Inputs'!M58*M39+'2. Inputs'!M59*MAX(0,M39-'2. Inputs'!M60)+'2. Inputs'!M61*M39,0)
A41: NOPAT (R$) | D41: =D39-D40 | E41: =E39-E40 | F41: =F39-F40 | G41: =G39-G40 | H41: =H39-H40 | I41: =I39-I40 | J41: =J39-J40 | K41: =K39-K40 | ... M41: =M39-M40
A42: Capital de giro (R$) | C42: =D42 | D42: ='2. Inputs'!D64/'2. Inputs'!D68*D35+'2. Inputs'!D65/'2. Inputs'!D68*(D27+D28)+'2. Inputs'!D67/'2. Inputs'!D68*(D27+D28+D36+D29+D30+D31)-'2. Inputs'!D66/'2. Inputs'!D68*(D27+D28) | E42: ='2. Inputs'!E64/'2. Inputs'!E68*E35+'2. Inputs'!E65/'2. Inputs'!E68*(E27+E28)+'2. Inputs'!E67/'2. Inputs'!E68*(E27+E28+E36+E29+E30+E31)-'2. Inputs'!E66/'2. Inputs'!E68*(E27+E28) | F42: ='2. Inputs'!F64/'2. Inputs'!F68*F35+'2. Inputs'!F65/'2. Inputs'!F68*(F27+F28)+'2. Inputs'!F67/'2. Inputs'!F68*(F27+F28+F36+F29+F30+F31)-'2. Inputs'!F66/'2. Inputs'!F68*(F27+F28) | G42: ='2. Inputs'!G64/'2. Inputs'!G68*G35+'2. Inputs'!G65/'2. Inputs'!G68*(G27+G28)+'2. Inputs'!G67/'2. Inputs'!G68*(G27+G28+G36+G29+G30+G31)-'2. Inputs'!G66/'2. Inputs'!G68*(G27+G28) | H42: ='2. Inputs'!H64/'2. Inputs'!H68*H35+'2. Inputs'!H65/'2. Inputs'!H68*(H27+H28)+'2. Inputs'!H67/'2. Inputs'!H68*(H27+H28+H36+H29+H30+H31)-'2. Inputs'!H66/'2. Inputs'!H68*(H27+H28) | I42: ='2. Inputs'!I64/'2. Inputs'!I68*I35+'2. Inputs'!I65/'2. Inputs'!I68*(I27+I28)+'2. Inputs'!I67/'2. Inputs'!I68*(I27+I28+I36+I29+I30+I31)-'2. Inputs'!I66/'2. Inputs'!I68*(I27+I28) | J42: ='2. Inputs'!J64/'2. Inputs'!J68*J35+'2. Inputs'!J65/'2. Inputs'!J68*(J27+J28)+'2. Inputs'!J67/'2. Inputs'!J68*(J27+J28+J36+J29+J30+J31)-'2. Inputs'!J66/'2. Inputs'!J68*(J27+J28) | K42: ='2. Inputs'!K64/'2. Inputs'!K68*K35+'2. Inputs'!K65/'2. Inputs'!K68*(K27+K28)+'2. Inputs'!K67/'2. Inputs'!K68*(K27+K28+K36+K29+K30+K31)-'2. Inputs'!K66/'2. Inputs'!K68*(K27+K28) | ... M42: ='2. Inputs'!M64/'2. Inputs'!M68*M35+'2. Inputs'!M65/'2. Inputs'!M68*(M27+M28)+'2. Inputs'!M67/'2. Inputs'!M68*(M27+M28+M36+M29+M30+M31)-'2. Inputs'!M66/'2. Inputs'!M68*(M27+M28)
A43: Δ capital de giro (R$) | C43: =C42 | D43: =D42-C42 | E43: =E42-D42 | F43: =F42-E42 | G43: =G42-F42 | H43: =H42-G42 | I43: =I42-H42 | J43: =J42-I42 | K43: =K42-J42 | ... M43: =M42-L42
A44: Fluxo de caixa livre (R$) | C44: =-C43-'2. Inputs'!C53 | D44: =D41+D32-D43-'2. Inputs'!D53+IF(D$22=10,D42,0) | E44: =E41+E32-E43-'2. Inputs'!E53+IF(E$22=10,E42,0) | F44: =F41+F32-F43-'2. Inputs'!F53+IF(F$22=10,F42,0) | G44: =G41+G32-G43-'2. Inputs'!G53+IF(G$22=10,G42,0) | H44: =H41+H32-H43-'2. Inputs'!H53+IF(H$22=10,H42,0) | I44: =I41+I32-I43-'2. Inputs'!I53+IF(I$22=10,I42,0) | J44: =J41+J32-J43-'2. Inputs'!J53+IF(J$22=10,J42,0) | K44: =K41+K32-K43-'2. Inputs'!K53+IF(K$22=10,K42,0) | ... M44: =M41+M32-M43-'2. Inputs'!M53+IF(M$22=10,M42,0) | N44: =C44/(1+'2. Inputs'!$C$81)^C22 | O44: =N44+D44/(1+'2. Inputs'!$C$81)^D22 | P44: =O44+E44/(1+'2. Inputs'!$C$81)^E22 | Q44: =P44+F44/(1+'2. Inputs'!$C$81)^F22 | R44: =Q44+G44/(1+'2. Inputs'!$C$81)^G22 | S44: =R44+H44/(1+'2. Inputs'!$C$81)^H22 | T44: =S44+I44/(1+'2. Inputs'!$C$81)^I22 | U44: =T44+J44/(1+'2. Inputs'!$C$81)^J22 | V44: =U44+K44/(1+'2. Inputs'!$C$81)^K22 | ... X44: =W44+M44/(1+'2. Inputs'!$C$81)^M22
A46: CORRIDA 2 — Base
A47: Ano | C47: 0 | D47: 1 | E47: 2 | F47: 3 | G47: 4 | H47: 5 | I47: 6 | J47: 7 | K47: 8 | L47: 9 | M47: 10
A48: Volume (un) | D48: ='2. Inputs'!D11*(1+$C$8) | E48: ='2. Inputs'!E11*(1+$C$8) | F48: ='2. Inputs'!F11*(1+$C$8) | G48: ='2. Inputs'!G11*(1+$C$8) | H48: ='2. Inputs'!H11*(1+$C$8) | I48: ='2. Inputs'!I11*(1+$C$8) | J48: ='2. Inputs'!J11*(1+$C$8) | K48: ='2. Inputs'!K11*(1+$C$8) | ... M48: ='2. Inputs'!M11*(1+$C$8)
A49: Frete unitário (R$/un) | B49: =('2. Inputs'!D25*'2. Inputs'!$C$96+'2. Inputs'!D26*'2. Inputs'!$C$97+'2. Inputs'!D27*'2. Inputs'!$C$98+'2. Inputs'!D28*'2. Inputs'!$C$99)/'2. Inputs'!$C$100 | D49: =$G$8*'2. Inputs'!D24+(1-$G$8)*$B$49 | E49: =$G$8*'2. Inputs'!E24+(1-$G$8)*$B$49 | F49: =$G$8*'2. Inputs'!F24+(1-$G$8)*$B$49 | G49: =$G$8*'2. Inputs'!G24+(1-$G$8)*$B$49 | H49: =$G$8*'2. Inputs'!H24+(1-$G$8)*$B$49 | I49: =$G$8*'2. Inputs'!I24+(1-$G$8)*$B$49 | J49: =$G$8*'2. Inputs'!J24+(1-$G$8)*$B$49 | K49: =$G$8*'2. Inputs'!K24+(1-$G$8)*$B$49 | ... M49: =$G$8*'2. Inputs'!M24+(1-$G$8)*$B$49 | O49: Coluna B: frete unitário médio fora do Sudeste, nas proporções da origem (Sul 5%, NE 3%, N 2%, CO 10%).
A50: Custo variável unitário (R$/un) | D50: ='2. Inputs'!D43*(1+$E$8) | E50: ='2. Inputs'!E43*(1+$E$8) | F50: ='2. Inputs'!F43*(1+$E$8) | G50: ='2. Inputs'!G43*(1+$E$8) | H50: ='2. Inputs'!H43*(1+$E$8) | I50: ='2. Inputs'!I43*(1+$E$8) | J50: ='2. Inputs'!J43*(1+$E$8) | K50: ='2. Inputs'!K43*(1+$E$8) | ... M50: ='2. Inputs'!M43*(1+$E$8)
A51: Markup total (%) | D51: ='2. Inputs'!D32+'2. Inputs'!D33+'2. Inputs'!D34+'2. Inputs'!D35+'2. Inputs'!D36+$D$8 | E51: ='2. Inputs'!E32+'2. Inputs'!E33+'2. Inputs'!E34+'2. Inputs'!E35+'2. Inputs'!E36+$D$8 | F51: ='2. Inputs'!F32+'2. Inputs'!F33+'2. Inputs'!F34+'2. Inputs'!F35+'2. Inputs'!F36+$D$8 | G51: ='2. Inputs'!G32+'2. Inputs'!G33+'2. Inputs'!G34+'2. Inputs'!G35+'2. Inputs'!G36+$D$8 | H51: ='2. Inputs'!H32+'2. Inputs'!H33+'2. Inputs'!H34+'2. Inputs'!H35+'2. Inputs'!H36+$D$8 | I51: ='2. Inputs'!I32+'2. Inputs'!I33+'2. Inputs'!I34+'2. Inputs'!I35+'2. Inputs'!I36+$D$8 | J51: ='2. Inputs'!J32+'2. Inputs'!J33+'2. Inputs'!J34+'2. Inputs'!J35+'2. Inputs'!J36+$D$8 | K51: ='2. Inputs'!K32+'2. Inputs'!K33+'2. Inputs'!K34+'2. Inputs'!K35+'2. Inputs'!K36+$D$8 | ... M51: ='2. Inputs'!M32+'2. Inputs'!M33+'2. Inputs'!M34+'2. Inputs'!M35+'2. Inputs'!M36+$D$8
A52: Custo variável (R$) | D52: =D48*D50 | E52: =E48*E50 | F52: =F48*F50 | G52: =G48*G50 | H52: =H48*H50 | I52: =I48*I50 | J52: =J48*J50 | K52: =K48*K50 | ... M52: =M48*M50
A53: Frete (R$) | D53: =D48*D49 | E53: =E48*E49 | F53: =F48*F49 | G53: =G48*G49 | H53: =H48*H49 | I53: =I48*I49 | J53: =J48*J49 | K53: =K48*K49 | ... M53: =M48*M49
A54: Custo fixo de estrutura (R$) | D54: ='2. Inputs'!D46 | E54: ='2. Inputs'!E46 | F54: ='2. Inputs'!F46 | G54: ='2. Inputs'!G46 | H54: ='2. Inputs'!H46 | I54: ='2. Inputs'!I46 | J54: ='2. Inputs'!J46 | K54: ='2. Inputs'!K46 | ... M54: ='2. Inputs'!M46
A55: Manutenção e seguro (R$) | D55: =('2. Inputs'!D47+'2. Inputs'!D48)*'2. Inputs'!D54 | E55: =('2. Inputs'!E47+'2. Inputs'!E48)*'2. Inputs'!E54 | F55: =('2. Inputs'!F47+'2. Inputs'!F48)*'2. Inputs'!F54 | G55: =('2. Inputs'!G47+'2. Inputs'!G48)*'2. Inputs'!G54 | H55: =('2. Inputs'!H47+'2. Inputs'!H48)*'2. Inputs'!H54 | I55: =('2. Inputs'!I47+'2. Inputs'!I48)*'2. Inputs'!I54 | J55: =('2. Inputs'!J47+'2. Inputs'!J48)*'2. Inputs'!J54 | K55: =('2. Inputs'!K47+'2. Inputs'!K48)*'2. Inputs'!K54 | ... M55: =('2. Inputs'!M47+'2. Inputs'!M48)*'2. Inputs'!M54
A56: Contingência (R$) | D56: =$F$8*'2. Inputs'!D54 | E56: =$F$8*'2. Inputs'!E54 | F56: =$F$8*'2. Inputs'!F54 | G56: =$F$8*'2. Inputs'!G54 | H56: =$F$8*'2. Inputs'!H54 | I56: =$F$8*'2. Inputs'!I54 | J56: =$F$8*'2. Inputs'!J54 | K56: =$F$8*'2. Inputs'!K54 | ... M56: =$F$8*'2. Inputs'!M54
A57: Depreciação (R$) | D57: ='3. Depreciacao'!D31 | E57: ='3. Depreciacao'!E31 | F57: ='3. Depreciacao'!F31 | G57: ='3. Depreciacao'!G31 | H57: ='3. Depreciacao'!H31 | I57: ='3. Depreciacao'!I31 | J57: ='3. Depreciacao'!J31 | K57: ='3. Depreciacao'!K31 | ... M57: ='3. Depreciacao'!M31
A58: Custo total (R$) | D58: =SUM(D52:D57) | E58: =SUM(E52:E57) | F58: =SUM(F52:F57) | G58: =SUM(G52:G57) | H58: =SUM(H52:H57) | I58: =SUM(I52:I57) | J58: =SUM(J52:J57) | K58: =SUM(K52:K57) | ... M58: =SUM(M52:M57)
A59: Preço bruto unitário (R$/un) | D59: =IF('2. Inputs'!$C$38=1,D58/D48/(1-D51),'2. Inputs'!D39) | E59: =IF('2. Inputs'!$C$38=1,E58/E48/(1-E51),'2. Inputs'!E39) | F59: =IF('2. Inputs'!$C$38=1,F58/F48/(1-F51),'2. Inputs'!F39) | G59: =IF('2. Inputs'!$C$38=1,G58/G48/(1-G51),'2. Inputs'!G39) | H59: =IF('2. Inputs'!$C$38=1,H58/H48/(1-H51),'2. Inputs'!H39) | I59: =IF('2. Inputs'!$C$38=1,I58/I48/(1-I51),'2. Inputs'!I39) | J59: =IF('2. Inputs'!$C$38=1,J58/J48/(1-J51),'2. Inputs'!J39) | K59: =IF('2. Inputs'!$C$38=1,K58/K48/(1-K51),'2. Inputs'!K39) | ... M59: =IF('2. Inputs'!$C$38=1,M58/M48/(1-M51),'2. Inputs'!M39)
A60: Receita bruta (R$) | D60: =D48*D59 | E60: =E48*E59 | F60: =F48*F59 | G60: =G48*G59 | H60: =H48*H59 | I60: =I48*I59 | J60: =J48*J59 | K60: =K48*K59 | ... M60: =M48*M59
A61: Comissão (R$) | D61: ='2. Inputs'!D35*D60 | E61: ='2. Inputs'!E35*E60 | F61: ='2. Inputs'!F35*F60 | G61: ='2. Inputs'!G35*G60 | H61: ='2. Inputs'!H35*H60 | I61: ='2. Inputs'!I35*I60 | J61: ='2. Inputs'!J35*J60 | K61: ='2. Inputs'!K35*K60 | ... M61: ='2. Inputs'!M35*M60
A62: Receita líquida (R$) | D62: =D60*(1-'2. Inputs'!D32-'2. Inputs'!D33-'2. Inputs'!D34) | E62: =E60*(1-'2. Inputs'!E32-'2. Inputs'!E33-'2. Inputs'!E34) | F62: =F60*(1-'2. Inputs'!F32-'2. Inputs'!F33-'2. Inputs'!F34) | G62: =G60*(1-'2. Inputs'!G32-'2. Inputs'!G33-'2. Inputs'!G34) | H62: =H60*(1-'2. Inputs'!H32-'2. Inputs'!H33-'2. Inputs'!H34) | I62: =I60*(1-'2. Inputs'!I32-'2. Inputs'!I33-'2. Inputs'!I34) | J62: =J60*(1-'2. Inputs'!J32-'2. Inputs'!J33-'2. Inputs'!J34) | K62: =K60*(1-'2. Inputs'!K32-'2. Inputs'!K33-'2. Inputs'!K34) | ... M62: =M60*(1-'2. Inputs'!M32-'2. Inputs'!M33-'2. Inputs'!M34)
A63: EBITDA (R$) | D63: =D62-D52-D53-D61-D54-D55-D56 | E63: =E62-E52-E53-E61-E54-E55-E56 | F63: =F62-F52-F53-F61-F54-F55-F56 | G63: =G62-G52-G53-G61-G54-G55-G56 | H63: =H62-H52-H53-H61-H54-H55-H56 | I63: =I62-I52-I53-I61-I54-I55-I56 | J63: =J62-J52-J53-J61-J54-J55-J56 | K63: =K62-K52-K53-K61-K54-K55-K56 | ... M63: =M62-M52-M53-M61-M54-M55-M56
A64: EBIT (R$) | D64: =D63-D57 | E64: =E63-E57 | F64: =F63-F57 | G64: =G63-G57 | H64: =H63-H57 | I64: =I63-I57 | J64: =J63-J57 | K64: =K63-K57 | ... M64: =M63-M57
A65: IRPJ + adicional + CSLL (R$) | D65: =IF(D64>0,'2. Inputs'!D58*D64+'2. Inputs'!D59*MAX(0,D64-'2. Inputs'!D60)+'2. Inputs'!D61*D64,0) | E65: =IF(E64>0,'2. Inputs'!E58*E64+'2. Inputs'!E59*MAX(0,E64-'2. Inputs'!E60)+'2. Inputs'!E61*E64,0) | F65: =IF(F64>0,'2. Inputs'!F58*F64+'2. Inputs'!F59*MAX(0,F64-'2. Inputs'!F60)+'2. Inputs'!F61*F64,0) | G65: =IF(G64>0,'2. Inputs'!G58*G64+'2. Inputs'!G59*MAX(0,G64-'2. Inputs'!G60)+'2. Inputs'!G61*G64,0) | H65: =IF(H64>0,'2. Inputs'!H58*H64+'2. Inputs'!H59*MAX(0,H64-'2. Inputs'!H60)+'2. Inputs'!H61*H64,0) | I65: =IF(I64>0,'2. Inputs'!I58*I64+'2. Inputs'!I59*MAX(0,I64-'2. Inputs'!I60)+'2. Inputs'!I61*I64,0) | J65: =IF(J64>0,'2. Inputs'!J58*J64+'2. Inputs'!J59*MAX(0,J64-'2. Inputs'!J60)+'2. Inputs'!J61*J64,0) | K65: =IF(K64>0,'2. Inputs'!K58*K64+'2. Inputs'!K59*MAX(0,K64-'2. Inputs'!K60)+'2. Inputs'!K61*K64,0) | ... M65: =IF(M64>0,'2. Inputs'!M58*M64+'2. Inputs'!M59*MAX(0,M64-'2. Inputs'!M60)+'2. Inputs'!M61*M64,0)
A66: NOPAT (R$) | D66: =D64-D65 | E66: =E64-E65 | F66: =F64-F65 | G66: =G64-G65 | H66: =H64-H65 | I66: =I64-I65 | J66: =J64-J65 | K66: =K64-K65 | ... M66: =M64-M65
A67: Capital de giro (R$) | C67: =D67 | D67: ='2. Inputs'!D64/'2. Inputs'!D68*D60+'2. Inputs'!D65/'2. Inputs'!D68*(D52+D53)+'2. Inputs'!D67/'2. Inputs'!D68*(D52+D53+D61+D54+D55+D56)-'2. Inputs'!D66/'2. Inputs'!D68*(D52+D53) | E67: ='2. Inputs'!E64/'2. Inputs'!E68*E60+'2. Inputs'!E65/'2. Inputs'!E68*(E52+E53)+'2. Inputs'!E67/'2. Inputs'!E68*(E52+E53+E61+E54+E55+E56)-'2. Inputs'!E66/'2. Inputs'!E68*(E52+E53) | F67: ='2. Inputs'!F64/'2. Inputs'!F68*F60+'2. Inputs'!F65/'2. Inputs'!F68*(F52+F53)+'2. Inputs'!F67/'2. Inputs'!F68*(F52+F53+F61+F54+F55+F56)-'2. Inputs'!F66/'2. Inputs'!F68*(F52+F53) | G67: ='2. Inputs'!G64/'2. Inputs'!G68*G60+'2. Inputs'!G65/'2. Inputs'!G68*(G52+G53)+'2. Inputs'!G67/'2. Inputs'!G68*(G52+G53+G61+G54+G55+G56)-'2. Inputs'!G66/'2. Inputs'!G68*(G52+G53) | H67: ='2. Inputs'!H64/'2. Inputs'!H68*H60+'2. Inputs'!H65/'2. Inputs'!H68*(H52+H53)+'2. Inputs'!H67/'2. Inputs'!H68*(H52+H53+H61+H54+H55+H56)-'2. Inputs'!H66/'2. Inputs'!H68*(H52+H53) | I67: ='2. Inputs'!I64/'2. Inputs'!I68*I60+'2. Inputs'!I65/'2. Inputs'!I68*(I52+I53)+'2. Inputs'!I67/'2. Inputs'!I68*(I52+I53+I61+I54+I55+I56)-'2. Inputs'!I66/'2. Inputs'!I68*(I52+I53) | J67: ='2. Inputs'!J64/'2. Inputs'!J68*J60+'2. Inputs'!J65/'2. Inputs'!J68*(J52+J53)+'2. Inputs'!J67/'2. Inputs'!J68*(J52+J53+J61+J54+J55+J56)-'2. Inputs'!J66/'2. Inputs'!J68*(J52+J53) | K67: ='2. Inputs'!K64/'2. Inputs'!K68*K60+'2. Inputs'!K65/'2. Inputs'!K68*(K52+K53)+'2. Inputs'!K67/'2. Inputs'!K68*(K52+K53+K61+K54+K55+K56)-'2. Inputs'!K66/'2. Inputs'!K68*(K52+K53) | ... M67: ='2. Inputs'!M64/'2. Inputs'!M68*M60+'2. Inputs'!M65/'2. Inputs'!M68*(M52+M53)+'2. Inputs'!M67/'2. Inputs'!M68*(M52+M53+M61+M54+M55+M56)-'2. Inputs'!M66/'2. Inputs'!M68*(M52+M53)
A68: Δ capital de giro (R$) | C68: =C67 | D68: =D67-C67 | E68: =E67-D67 | F68: =F67-E67 | G68: =G67-F67 | H68: =H67-G67 | I68: =I67-H67 | J68: =J67-I67 | K68: =K67-J67 | ... M68: =M67-L67
A69: Fluxo de caixa livre (R$) | C69: =-C68-'2. Inputs'!C53 | D69: =D66+D57-D68-'2. Inputs'!D53+IF(D$47=10,D67,0) | E69: =E66+E57-E68-'2. Inputs'!E53+IF(E$47=10,E67,0) | F69: =F66+F57-F68-'2. Inputs'!F53+IF(F$47=10,F67,0) | G69: =G66+G57-G68-'2. Inputs'!G53+IF(G$47=10,G67,0) | H69: =H66+H57-H68-'2. Inputs'!H53+IF(H$47=10,H67,0) | I69: =I66+I57-I68-'2. Inputs'!I53+IF(I$47=10,I67,0) | J69: =J66+J57-J68-'2. Inputs'!J53+IF(J$47=10,J67,0) | K69: =K66+K57-K68-'2. Inputs'!K53+IF(K$47=10,K67,0) | ... M69: =M66+M57-M68-'2. Inputs'!M53+IF(M$47=10,M67,0) | N69: =C69/(1+'2. Inputs'!$C$81)^C47 | O69: =N69+D69/(1+'2. Inputs'!$C$81)^D47 | P69: =O69+E69/(1+'2. Inputs'!$C$81)^E47 | Q69: =P69+F69/(1+'2. Inputs'!$C$81)^F47 | R69: =Q69+G69/(1+'2. Inputs'!$C$81)^G47 | S69: =R69+H69/(1+'2. Inputs'!$C$81)^H47 | T69: =S69+I69/(1+'2. Inputs'!$C$81)^I47 | U69: =T69+J69/(1+'2. Inputs'!$C$81)^J47 | V69: =U69+K69/(1+'2. Inputs'!$C$81)^K47 | ... X69: =W69+M69/(1+'2. Inputs'!$C$81)^M47
A71: CORRIDA 3 — Otimista
A72: Ano | C72: 0 | D72: 1 | E72: 2 | F72: 3 | G72: 4 | H72: 5 | I72: 6 | J72: 7 | K72: 8 | L72: 9 | M72: 10
A73: Volume (un) | D73: ='2. Inputs'!D11*(1+$C$9) | E73: ='2. Inputs'!E11*(1+$C$9) | F73: ='2. Inputs'!F11*(1+$C$9) | G73: ='2. Inputs'!G11*(1+$C$9) | H73: ='2. Inputs'!H11*(1+$C$9) | I73: ='2. Inputs'!I11*(1+$C$9) | J73: ='2. Inputs'!J11*(1+$C$9) | K73: ='2. Inputs'!K11*(1+$C$9) | ... M73: ='2. Inputs'!M11*(1+$C$9)
A74: Frete unitário (R$/un) | B74: =('2. Inputs'!D25*'2. Inputs'!$C$96+'2. Inputs'!D26*'2. Inputs'!$C$97+'2. Inputs'!D27*'2. Inputs'!$C$98+'2. Inputs'!D28*'2. Inputs'!$C$99)/'2. Inputs'!$C$100 | D74: =$G$9*'2. Inputs'!D24+(1-$G$9)*$B$74 | E74: =$G$9*'2. Inputs'!E24+(1-$G$9)*$B$74 | F74: =$G$9*'2. Inputs'!F24+(1-$G$9)*$B$74 | G74: =$G$9*'2. Inputs'!G24+(1-$G$9)*$B$74 | H74: =$G$9*'2. Inputs'!H24+(1-$G$9)*$B$74 | I74: =$G$9*'2. Inputs'!I24+(1-$G$9)*$B$74 | J74: =$G$9*'2. Inputs'!J24+(1-$G$9)*$B$74 | K74: =$G$9*'2. Inputs'!K24+(1-$G$9)*$B$74 | ... M74: =$G$9*'2. Inputs'!M24+(1-$G$9)*$B$74 | O74: Coluna B: frete unitário médio fora do Sudeste, nas proporções da origem (Sul 5%, NE 3%, N 2%, CO 10%).
A75: Custo variável unitário (R$/un) | D75: ='2. Inputs'!D43*(1+$E$9) | E75: ='2. Inputs'!E43*(1+$E$9) | F75: ='2. Inputs'!F43*(1+$E$9) | G75: ='2. Inputs'!G43*(1+$E$9) | H75: ='2. Inputs'!H43*(1+$E$9) | I75: ='2. Inputs'!I43*(1+$E$9) | J75: ='2. Inputs'!J43*(1+$E$9) | K75: ='2. Inputs'!K43*(1+$E$9) | ... M75: ='2. Inputs'!M43*(1+$E$9)
A76: Markup total (%) | D76: ='2. Inputs'!D32+'2. Inputs'!D33+'2. Inputs'!D34+'2. Inputs'!D35+'2. Inputs'!D36+$D$9 | E76: ='2. Inputs'!E32+'2. Inputs'!E33+'2. Inputs'!E34+'2. Inputs'!E35+'2. Inputs'!E36+$D$9 | F76: ='2. Inputs'!F32+'2. Inputs'!F33+'2. Inputs'!F34+'2. Inputs'!F35+'2. Inputs'!F36+$D$9 | G76: ='2. Inputs'!G32+'2. Inputs'!G33+'2. Inputs'!G34+'2. Inputs'!G35+'2. Inputs'!G36+$D$9 | H76: ='2. Inputs'!H32+'2. Inputs'!H33+'2. Inputs'!H34+'2. Inputs'!H35+'2. Inputs'!H36+$D$9 | I76: ='2. Inputs'!I32+'2. Inputs'!I33+'2. Inputs'!I34+'2. Inputs'!I35+'2. Inputs'!I36+$D$9 | J76: ='2. Inputs'!J32+'2. Inputs'!J33+'2. Inputs'!J34+'2. Inputs'!J35+'2. Inputs'!J36+$D$9 | K76: ='2. Inputs'!K32+'2. Inputs'!K33+'2. Inputs'!K34+'2. Inputs'!K35+'2. Inputs'!K36+$D$9 | ... M76: ='2. Inputs'!M32+'2. Inputs'!M33+'2. Inputs'!M34+'2. Inputs'!M35+'2. Inputs'!M36+$D$9
A77: Custo variável (R$) | D77: =D73*D75 | E77: =E73*E75 | F77: =F73*F75 | G77: =G73*G75 | H77: =H73*H75 | I77: =I73*I75 | J77: =J73*J75 | K77: =K73*K75 | ... M77: =M73*M75
A78: Frete (R$) | D78: =D73*D74 | E78: =E73*E74 | F78: =F73*F74 | G78: =G73*G74 | H78: =H73*H74 | I78: =I73*I74 | J78: =J73*J74 | K78: =K73*K74 | ... M78: =M73*M74
A79: Custo fixo de estrutura (R$) | D79: ='2. Inputs'!D46 | E79: ='2. Inputs'!E46 | F79: ='2. Inputs'!F46 | G79: ='2. Inputs'!G46 | H79: ='2. Inputs'!H46 | I79: ='2. Inputs'!I46 | J79: ='2. Inputs'!J46 | K79: ='2. Inputs'!K46 | ... M79: ='2. Inputs'!M46
A80: Manutenção e seguro (R$) | D80: =('2. Inputs'!D47+'2. Inputs'!D48)*'2. Inputs'!D54 | E80: =('2. Inputs'!E47+'2. Inputs'!E48)*'2. Inputs'!E54 | F80: =('2. Inputs'!F47+'2. Inputs'!F48)*'2. Inputs'!F54 | G80: =('2. Inputs'!G47+'2. Inputs'!G48)*'2. Inputs'!G54 | H80: =('2. Inputs'!H47+'2. Inputs'!H48)*'2. Inputs'!H54 | I80: =('2. Inputs'!I47+'2. Inputs'!I48)*'2. Inputs'!I54 | J80: =('2. Inputs'!J47+'2. Inputs'!J48)*'2. Inputs'!J54 | K80: =('2. Inputs'!K47+'2. Inputs'!K48)*'2. Inputs'!K54 | ... M80: =('2. Inputs'!M47+'2. Inputs'!M48)*'2. Inputs'!M54
A81: Contingência (R$) | D81: =$F$9*'2. Inputs'!D54 | E81: =$F$9*'2. Inputs'!E54 | F81: =$F$9*'2. Inputs'!F54 | G81: =$F$9*'2. Inputs'!G54 | H81: =$F$9*'2. Inputs'!H54 | I81: =$F$9*'2. Inputs'!I54 | J81: =$F$9*'2. Inputs'!J54 | K81: =$F$9*'2. Inputs'!K54 | ... M81: =$F$9*'2. Inputs'!M54
A82: Depreciação (R$) | D82: ='3. Depreciacao'!D31 | E82: ='3. Depreciacao'!E31 | F82: ='3. Depreciacao'!F31 | G82: ='3. Depreciacao'!G31 | H82: ='3. Depreciacao'!H31 | I82: ='3. Depreciacao'!I31 | J82: ='3. Depreciacao'!J31 | K82: ='3. Depreciacao'!K31 | ... M82: ='3. Depreciacao'!M31
A83: Custo total (R$) | D83: =SUM(D77:D82) | E83: =SUM(E77:E82) | F83: =SUM(F77:F82) | G83: =SUM(G77:G82) | H83: =SUM(H77:H82) | I83: =SUM(I77:I82) | J83: =SUM(J77:J82) | K83: =SUM(K77:K82) | ... M83: =SUM(M77:M82)
A84: Preço bruto unitário (R$/un) | D84: =IF('2. Inputs'!$C$38=1,D83/D73/(1-D76),'2. Inputs'!D39) | E84: =IF('2. Inputs'!$C$38=1,E83/E73/(1-E76),'2. Inputs'!E39) | F84: =IF('2. Inputs'!$C$38=1,F83/F73/(1-F76),'2. Inputs'!F39) | G84: =IF('2. Inputs'!$C$38=1,G83/G73/(1-G76),'2. Inputs'!G39) | H84: =IF('2. Inputs'!$C$38=1,H83/H73/(1-H76),'2. Inputs'!H39) | I84: =IF('2. Inputs'!$C$38=1,I83/I73/(1-I76),'2. Inputs'!I39) | J84: =IF('2. Inputs'!$C$38=1,J83/J73/(1-J76),'2. Inputs'!J39) | K84: =IF('2. Inputs'!$C$38=1,K83/K73/(1-K76),'2. Inputs'!K39) | ... M84: =IF('2. Inputs'!$C$38=1,M83/M73/(1-M76),'2. Inputs'!M39)
A85: Receita bruta (R$) | D85: =D73*D84 | E85: =E73*E84 | F85: =F73*F84 | G85: =G73*G84 | H85: =H73*H84 | I85: =I73*I84 | J85: =J73*J84 | K85: =K73*K84 | ... M85: =M73*M84
A86: Comissão (R$) | D86: ='2. Inputs'!D35*D85 | E86: ='2. Inputs'!E35*E85 | F86: ='2. Inputs'!F35*F85 | G86: ='2. Inputs'!G35*G85 | H86: ='2. Inputs'!H35*H85 | I86: ='2. Inputs'!I35*I85 | J86: ='2. Inputs'!J35*J85 | K86: ='2. Inputs'!K35*K85 | ... M86: ='2. Inputs'!M35*M85
A87: Receita líquida (R$) | D87: =D85*(1-'2. Inputs'!D32-'2. Inputs'!D33-'2. Inputs'!D34) | E87: =E85*(1-'2. Inputs'!E32-'2. Inputs'!E33-'2. Inputs'!E34) | F87: =F85*(1-'2. Inputs'!F32-'2. Inputs'!F33-'2. Inputs'!F34) | G87: =G85*(1-'2. Inputs'!G32-'2. Inputs'!G33-'2. Inputs'!G34) | H87: =H85*(1-'2. Inputs'!H32-'2. Inputs'!H33-'2. Inputs'!H34) | I87: =I85*(1-'2. Inputs'!I32-'2. Inputs'!I33-'2. Inputs'!I34) | J87: =J85*(1-'2. Inputs'!J32-'2. Inputs'!J33-'2. Inputs'!J34) | K87: =K85*(1-'2. Inputs'!K32-'2. Inputs'!K33-'2. Inputs'!K34) | ... M87: =M85*(1-'2. Inputs'!M32-'2. Inputs'!M33-'2. Inputs'!M34)
A88: EBITDA (R$) | D88: =D87-D77-D78-D86-D79-D80-D81 | E88: =E87-E77-E78-E86-E79-E80-E81 | F88: =F87-F77-F78-F86-F79-F80-F81 | G88: =G87-G77-G78-G86-G79-G80-G81 | H88: =H87-H77-H78-H86-H79-H80-H81 | I88: =I87-I77-I78-I86-I79-I80-I81 | J88: =J87-J77-J78-J86-J79-J80-J81 | K88: =K87-K77-K78-K86-K79-K80-K81 | ... M88: =M87-M77-M78-M86-M79-M80-M81
A89: EBIT (R$) | D89: =D88-D82 | E89: =E88-E82 | F89: =F88-F82 | G89: =G88-G82 | H89: =H88-H82 | I89: =I88-I82 | J89: =J88-J82 | K89: =K88-K82 | ... M89: =M88-M82
A90: IRPJ + adicional + CSLL (R$) | D90: =IF(D89>0,'2. Inputs'!D58*D89+'2. Inputs'!D59*MAX(0,D89-'2. Inputs'!D60)+'2. Inputs'!D61*D89,0) | E90: =IF(E89>0,'2. Inputs'!E58*E89+'2. Inputs'!E59*MAX(0,E89-'2. Inputs'!E60)+'2. Inputs'!E61*E89,0) | F90: =IF(F89>0,'2. Inputs'!F58*F89+'2. Inputs'!F59*MAX(0,F89-'2. Inputs'!F60)+'2. Inputs'!F61*F89,0) | G90: =IF(G89>0,'2. Inputs'!G58*G89+'2. Inputs'!G59*MAX(0,G89-'2. Inputs'!G60)+'2. Inputs'!G61*G89,0) | H90: =IF(H89>0,'2. Inputs'!H58*H89+'2. Inputs'!H59*MAX(0,H89-'2. Inputs'!H60)+'2. Inputs'!H61*H89,0) | I90: =IF(I89>0,'2. Inputs'!I58*I89+'2. Inputs'!I59*MAX(0,I89-'2. Inputs'!I60)+'2. Inputs'!I61*I89,0) | J90: =IF(J89>0,'2. Inputs'!J58*J89+'2. Inputs'!J59*MAX(0,J89-'2. Inputs'!J60)+'2. Inputs'!J61*J89,0) | K90: =IF(K89>0,'2. Inputs'!K58*K89+'2. Inputs'!K59*MAX(0,K89-'2. Inputs'!K60)+'2. Inputs'!K61*K89,0) | ... M90: =IF(M89>0,'2. Inputs'!M58*M89+'2. Inputs'!M59*MAX(0,M89-'2. Inputs'!M60)+'2. Inputs'!M61*M89,0)
A91: NOPAT (R$) | D91: =D89-D90 | E91: =E89-E90 | F91: =F89-F90 | G91: =G89-G90 | H91: =H89-H90 | I91: =I89-I90 | J91: =J89-J90 | K91: =K89-K90 | ... M91: =M89-M90
A92: Capital de giro (R$) | C92: =D92 | D92: ='2. Inputs'!D64/'2. Inputs'!D68*D85+'2. Inputs'!D65/'2. Inputs'!D68*(D77+D78)+'2. Inputs'!D67/'2. Inputs'!D68*(D77+D78+D86+D79+D80+D81)-'2. Inputs'!D66/'2. Inputs'!D68*(D77+D78) | E92: ='2. Inputs'!E64/'2. Inputs'!E68*E85+'2. Inputs'!E65/'2. Inputs'!E68*(E77+E78)+'2. Inputs'!E67/'2. Inputs'!E68*(E77+E78+E86+E79+E80+E81)-'2. Inputs'!E66/'2. Inputs'!E68*(E77+E78) | F92: ='2. Inputs'!F64/'2. Inputs'!F68*F85+'2. Inputs'!F65/'2. Inputs'!F68*(F77+F78)+'2. Inputs'!F67/'2. Inputs'!F68*(F77+F78+F86+F79+F80+F81)-'2. Inputs'!F66/'2. Inputs'!F68*(F77+F78) | G92: ='2. Inputs'!G64/'2. Inputs'!G68*G85+'2. Inputs'!G65/'2. Inputs'!G68*(G77+G78)+'2. Inputs'!G67/'2. Inputs'!G68*(G77+G78+G86+G79+G80+G81)-'2. Inputs'!G66/'2. Inputs'!G68*(G77+G78) | H92: ='2. Inputs'!H64/'2. Inputs'!H68*H85+'2. Inputs'!H65/'2. Inputs'!H68*(H77+H78)+'2. Inputs'!H67/'2. Inputs'!H68*(H77+H78+H86+H79+H80+H81)-'2. Inputs'!H66/'2. Inputs'!H68*(H77+H78) | I92: ='2. Inputs'!I64/'2. Inputs'!I68*I85+'2. Inputs'!I65/'2. Inputs'!I68*(I77+I78)+'2. Inputs'!I67/'2. Inputs'!I68*(I77+I78+I86+I79+I80+I81)-'2. Inputs'!I66/'2. Inputs'!I68*(I77+I78) | J92: ='2. Inputs'!J64/'2. Inputs'!J68*J85+'2. Inputs'!J65/'2. Inputs'!J68*(J77+J78)+'2. Inputs'!J67/'2. Inputs'!J68*(J77+J78+J86+J79+J80+J81)-'2. Inputs'!J66/'2. Inputs'!J68*(J77+J78) | K92: ='2. Inputs'!K64/'2. Inputs'!K68*K85+'2. Inputs'!K65/'2. Inputs'!K68*(K77+K78)+'2. Inputs'!K67/'2. Inputs'!K68*(K77+K78+K86+K79+K80+K81)-'2. Inputs'!K66/'2. Inputs'!K68*(K77+K78) | ... M92: ='2. Inputs'!M64/'2. Inputs'!M68*M85+'2. Inputs'!M65/'2. Inputs'!M68*(M77+M78)+'2. Inputs'!M67/'2. Inputs'!M68*(M77+M78+M86+M79+M80+M81)-'2. Inputs'!M66/'2. Inputs'!M68*(M77+M78)
A93: Δ capital de giro (R$) | C93: =C92 | D93: =D92-C92 | E93: =E92-D92 | F93: =F92-E92 | G93: =G92-F92 | H93: =H92-G92 | I93: =I92-H92 | J93: =J92-I92 | K93: =K92-J92 | ... M93: =M92-L92
A94: Fluxo de caixa livre (R$) | C94: =-C93-'2. Inputs'!C53 | D94: =D91+D82-D93-'2. Inputs'!D53+IF(D$72=10,D92,0) | E94: =E91+E82-E93-'2. Inputs'!E53+IF(E$72=10,E92,0) | F94: =F91+F82-F93-'2. Inputs'!F53+IF(F$72=10,F92,0) | G94: =G91+G82-G93-'2. Inputs'!G53+IF(G$72=10,G92,0) | H94: =H91+H82-H93-'2. Inputs'!H53+IF(H$72=10,H92,0) | I94: =I91+I82-I93-'2. Inputs'!I53+IF(I$72=10,I92,0) | J94: =J91+J82-J93-'2. Inputs'!J53+IF(J$72=10,J92,0) | K94: =K91+K82-K93-'2. Inputs'!K53+IF(K$72=10,K92,0) | ... M94: =M91+M82-M93-'2. Inputs'!M53+IF(M$72=10,M92,0) | N94: =C94/(1+'2. Inputs'!$C$81)^C72 | O94: =N94+D94/(1+'2. Inputs'!$C$81)^D72 | P94: =O94+E94/(1+'2. Inputs'!$C$81)^E72 | Q94: =P94+F94/(1+'2. Inputs'!$C$81)^F72 | R94: =Q94+G94/(1+'2. Inputs'!$C$81)^G72 | S94: =R94+H94/(1+'2. Inputs'!$C$81)^H72 | T94: =S94+I94/(1+'2. Inputs'!$C$81)^I72 | U94: =T94+J94/(1+'2. Inputs'!$C$81)^J72 | V94: =U94+K94/(1+'2. Inputs'!$C$81)^K72 | ... X94: =W94+M94/(1+'2. Inputs'!$C$81)^M72
A96: CORRIDA 4 — Volume −10%
A97: Ano | C97: 0 | D97: 1 | E97: 2 | F97: 3 | G97: 4 | H97: 5 | I97: 6 | J97: 7 | K97: 8 | L97: 9 | M97: 10
A98: Volume (un) | D98: ='2. Inputs'!D11*(1+$C$10) | E98: ='2. Inputs'!E11*(1+$C$10) | F98: ='2. Inputs'!F11*(1+$C$10) | G98: ='2. Inputs'!G11*(1+$C$10) | H98: ='2. Inputs'!H11*(1+$C$10) | I98: ='2. Inputs'!I11*(1+$C$10) | J98: ='2. Inputs'!J11*(1+$C$10) | K98: ='2. Inputs'!K11*(1+$C$10) | ... M98: ='2. Inputs'!M11*(1+$C$10)
A99: Frete unitário (R$/un) | B99: =('2. Inputs'!D25*'2. Inputs'!$C$96+'2. Inputs'!D26*'2. Inputs'!$C$97+'2. Inputs'!D27*'2. Inputs'!$C$98+'2. Inputs'!D28*'2. Inputs'!$C$99)/'2. Inputs'!$C$100 | D99: =$G$10*'2. Inputs'!D24+(1-$G$10)*$B$99 | E99: =$G$10*'2. Inputs'!E24+(1-$G$10)*$B$99 | F99: =$G$10*'2. Inputs'!F24+(1-$G$10)*$B$99 | G99: =$G$10*'2. Inputs'!G24+(1-$G$10)*$B$99 | H99: =$G$10*'2. Inputs'!H24+(1-$G$10)*$B$99 | I99: =$G$10*'2. Inputs'!I24+(1-$G$10)*$B$99 | J99: =$G$10*'2. Inputs'!J24+(1-$G$10)*$B$99 | K99: =$G$10*'2. Inputs'!K24+(1-$G$10)*$B$99 | ... M99: =$G$10*'2. Inputs'!M24+(1-$G$10)*$B$99 | O99: Coluna B: frete unitário médio fora do Sudeste, nas proporções da origem (Sul 5%, NE 3%, N 2%, CO 10%).
A100: Custo variável unitário (R$/un) | D100: ='2. Inputs'!D43*(1+$E$10) | E100: ='2. Inputs'!E43*(1+$E$10) | F100: ='2. Inputs'!F43*(1+$E$10) | G100: ='2. Inputs'!G43*(1+$E$10) | H100: ='2. Inputs'!H43*(1+$E$10) | I100: ='2. Inputs'!I43*(1+$E$10) | J100: ='2. Inputs'!J43*(1+$E$10) | K100: ='2. Inputs'!K43*(1+$E$10) | ... M100: ='2. Inputs'!M43*(1+$E$10)
A101: Markup total (%) | D101: ='2. Inputs'!D32+'2. Inputs'!D33+'2. Inputs'!D34+'2. Inputs'!D35+'2. Inputs'!D36+$D$10 | E101: ='2. Inputs'!E32+'2. Inputs'!E33+'2. Inputs'!E34+'2. Inputs'!E35+'2. Inputs'!E36+$D$10 | F101: ='2. Inputs'!F32+'2. Inputs'!F33+'2. Inputs'!F34+'2. Inputs'!F35+'2. Inputs'!F36+$D$10 | G101: ='2. Inputs'!G32+'2. Inputs'!G33+'2. Inputs'!G34+'2. Inputs'!G35+'2. Inputs'!G36+$D$10 | H101: ='2. Inputs'!H32+'2. Inputs'!H33+'2. Inputs'!H34+'2. Inputs'!H35+'2. Inputs'!H36+$D$10 | I101: ='2. Inputs'!I32+'2. Inputs'!I33+'2. Inputs'!I34+'2. Inputs'!I35+'2. Inputs'!I36+$D$10 | J101: ='2. Inputs'!J32+'2. Inputs'!J33+'2. Inputs'!J34+'2. Inputs'!J35+'2. Inputs'!J36+$D$10 | K101: ='2. Inputs'!K32+'2. Inputs'!K33+'2. Inputs'!K34+'2. Inputs'!K35+'2. Inputs'!K36+$D$10 | ... M101: ='2. Inputs'!M32+'2. Inputs'!M33+'2. Inputs'!M34+'2. Inputs'!M35+'2. Inputs'!M36+$D$10
A102: Custo variável (R$) | D102: =D98*D100 | E102: =E98*E100 | F102: =F98*F100 | G102: =G98*G100 | H102: =H98*H100 | I102: =I98*I100 | J102: =J98*J100 | K102: =K98*K100 | ... M102: =M98*M100
A103: Frete (R$) | D103: =D98*D99 | E103: =E98*E99 | F103: =F98*F99 | G103: =G98*G99 | H103: =H98*H99 | I103: =I98*I99 | J103: =J98*J99 | K103: =K98*K99 | ... M103: =M98*M99
A104: Custo fixo de estrutura (R$) | D104: ='2. Inputs'!D46 | E104: ='2. Inputs'!E46 | F104: ='2. Inputs'!F46 | G104: ='2. Inputs'!G46 | H104: ='2. Inputs'!H46 | I104: ='2. Inputs'!I46 | J104: ='2. Inputs'!J46 | K104: ='2. Inputs'!K46 | ... M104: ='2. Inputs'!M46
A105: Manutenção e seguro (R$) | D105: =('2. Inputs'!D47+'2. Inputs'!D48)*'2. Inputs'!D54 | E105: =('2. Inputs'!E47+'2. Inputs'!E48)*'2. Inputs'!E54 | F105: =('2. Inputs'!F47+'2. Inputs'!F48)*'2. Inputs'!F54 | G105: =('2. Inputs'!G47+'2. Inputs'!G48)*'2. Inputs'!G54 | H105: =('2. Inputs'!H47+'2. Inputs'!H48)*'2. Inputs'!H54 | I105: =('2. Inputs'!I47+'2. Inputs'!I48)*'2. Inputs'!I54 | J105: =('2. Inputs'!J47+'2. Inputs'!J48)*'2. Inputs'!J54 | K105: =('2. Inputs'!K47+'2. Inputs'!K48)*'2. Inputs'!K54 | ... M105: =('2. Inputs'!M47+'2. Inputs'!M48)*'2. Inputs'!M54
A106: Contingência (R$) | D106: =$F$10*'2. Inputs'!D54 | E106: =$F$10*'2. Inputs'!E54 | F106: =$F$10*'2. Inputs'!F54 | G106: =$F$10*'2. Inputs'!G54 | H106: =$F$10*'2. Inputs'!H54 | I106: =$F$10*'2. Inputs'!I54 | J106: =$F$10*'2. Inputs'!J54 | K106: =$F$10*'2. Inputs'!K54 | ... M106: =$F$10*'2. Inputs'!M54
...

Sheet 9. Ponte EBITDA
A1: PONTE DE VARIÂNCIA DO EBITDA
A2: Volume · Preço · Mix · Custo variável · Custo fixo, nessa ordem, fechando exatamente no ΔEBITDA. A origem não tinha EBITDA para decompor.
A7: Ano | C7: 0 | D7: 1 | E7: 2 | F7: 3 | G7: 4 | H7: 5 | I7: 6 | J7: 7 | K7: 8 | L7: 9 | M7: 10 | O7: Observação
A8: Exercício | C8: 2023 | D8: 2024 | E8: 2025 | F8: 2026 | G8: 2027 | H8: 2028 | I8: 2029 | J8: 2030 | K8: 2031 | L8: 2032 | M8: 2033
A10: A. PONTE ANO A ANO (cada ano contra o anterior)
A11: EBITDA do ano anterior | B11: R$ | E11: ='4. DRE'!D39 | F11: ='4. DRE'!E39 | G11: ='4. DRE'!F39 | H11: ='4. DRE'!G39 | I11: ='4. DRE'!H39 | J11: ='4. DRE'!I39 | K11: ='4. DRE'!J39 | L11: ='4. DRE'!K39 | M11: ='4. DRE'!L39
A12: Efeito VOLUME | B12: R$ | E12: =('4. DRE'!E24-'4. DRE'!D24)*'4. DRE'!D55 | F12: =('4. DRE'!F24-'4. DRE'!E24)*'4. DRE'!E55 | G12: =('4. DRE'!G24-'4. DRE'!F24)*'4. DRE'!F55 | H12: =('4. DRE'!H24-'4. DRE'!G24)*'4. DRE'!G55 | I12: =('4. DRE'!I24-'4. DRE'!H24)*'4. DRE'!H55 | J12: =('4. DRE'!J24-'4. DRE'!I24)*'4. DRE'!I55 | K12: =('4. DRE'!K24-'4. DRE'!J24)*'4. DRE'!J55 | L12: =('4. DRE'!L24-'4. DRE'!K24)*'4. DRE'!K55 | M12: =('4. DRE'!M24-'4. DRE'!L24)*'4. DRE'!L55 | O12: Cálculo: (volume do ano − volume anterior) x margem de contribuição unitária ANTERIOR.
A13: Efeito PREÇO | B13: R$ | E13: ='4. DRE'!E24*(('4. DRE'!E51-'4. DRE'!E52)-('4. DRE'!D51-'4. DRE'!D52)) | F13: ='4. DRE'!F24*(('4. DRE'!F51-'4. DRE'!F52)-('4. DRE'!E51-'4. DRE'!E52)) | G13: ='4. DRE'!G24*(('4. DRE'!G51-'4. DRE'!G52)-('4. DRE'!F51-'4. DRE'!F52)) | H13: ='4. DRE'!H24*(('4. DRE'!H51-'4. DRE'!H52)-('4. DRE'!G51-'4. DRE'!G52)) | I13: ='4. DRE'!I24*(('4. DRE'!I51-'4. DRE'!I52)-('4. DRE'!H51-'4. DRE'!H52)) | J13: ='4. DRE'!J24*(('4. DRE'!J51-'4. DRE'!J52)-('4. DRE'!I51-'4. DRE'!I52)) | K13: ='4. DRE'!K24*(('4. DRE'!K51-'4. DRE'!K52)-('4. DRE'!J51-'4. DRE'!J52)) | L13: ='4. DRE'!L24*(('4. DRE'!L51-'4. DRE'!L52)-('4. DRE'!K51-'4. DRE'!K52)) | M13: ='4. DRE'!M24*(('4. DRE'!M51-'4. DRE'!M52)-('4. DRE'!L51-'4. DRE'!L52)) | O13: Cálculo: volume do ano x variação do preço líquido de impostos e de comissão.
A14: Efeito MIX | B14: R$ | E14: ='4. DRE'!E24*('4. DRE'!D54-'4. DRE'!E54) | F14: ='4. DRE'!F24*('4. DRE'!E54-'4. DRE'!F54) | G14: ='4. DRE'!G24*('4. DRE'!F54-'4. DRE'!G54) | H14: ='4. DRE'!H24*('4. DRE'!G54-'4. DRE'!H54) | I14: ='4. DRE'!I24*('4. DRE'!H54-'4. DRE'!I54) | J14: ='4. DRE'!J24*('4. DRE'!I54-'4. DRE'!J54) | K14: ='4. DRE'!K24*('4. DRE'!J54-'4. DRE'!K54) | L14: ='4. DRE'!L24*('4. DRE'!K54-'4. DRE'!L54) | M14: ='4. DRE'!M24*('4. DRE'!L54-'4. DRE'!M54) | O14: Cálculo: volume do ano x queda do frete unitário ponderado. Mix regional: sair do Sudeste encarece o frete.
A15: Efeito CUSTO VARIÁVEL | B15: R$ | E15: ='4. DRE'!E24*('4. DRE'!D53-'4. DRE'!E53) | F15: ='4. DRE'!F24*('4. DRE'!E53-'4. DRE'!F53) | G15: ='4. DRE'!G24*('4. DRE'!F53-'4. DRE'!G53) | H15: ='4. DRE'!H24*('4. DRE'!G53-'4. DRE'!H53) | I15: ='4. DRE'!I24*('4. DRE'!H53-'4. DRE'!I53) | J15: ='4. DRE'!J24*('4. DRE'!I53-'4. DRE'!J53) | K15: ='4. DRE'!K24*('4. DRE'!J53-'4. DRE'!K53) | L15: ='4. DRE'!L24*('4. DRE'!K53-'4. DRE'!L53) | M15: ='4. DRE'!M24*('4. DRE'!L53-'4. DRE'!M53) | O15: Cálculo: volume do ano x queda do custo variável unitário.
A16: Efeito CUSTO FIXO | B16: R$ | E16: =-('4. DRE'!E56-'4. DRE'!D56) | F16: =-('4. DRE'!F56-'4. DRE'!E56) | G16: =-('4. DRE'!G56-'4. DRE'!F56) | H16: =-('4. DRE'!H56-'4. DRE'!G56) | I16: =-('4. DRE'!I56-'4. DRE'!H56) | J16: =-('4. DRE'!J56-'4. DRE'!I56) | K16: =-('4. DRE'!K56-'4. DRE'!J56) | L16: =-('4. DRE'!L56-'4. DRE'!K56) | M16: =-('4. DRE'!M56-'4. DRE'!L56) | O16: Cálculo: −(custo fixo do ano − custo fixo anterior). Estrutura, manutenção, seguro e contingência.
A17: EBITDA do ano | B17: R$ | E17: ='4. DRE'!E39 | F17: ='4. DRE'!F39 | G17: ='4. DRE'!G39 | H17: ='4. DRE'!H39 | I17: ='4. DRE'!I39 | J17: ='4. DRE'!J39 | K17: ='4. DRE'!K39 | L17: ='4. DRE'!L39 | M17: ='4. DRE'!M39
A18: Δ EBITDA | B18: R$ | E18: =E17-E11 | F18: =F17-F11 | G18: =G17-G11 | H18: =H17-H11 | I18: =I17-I11 | J18: =J17-J11 | K18: =K17-K11 | L18: =L17-L11 | M18: =M17-M11
A19: Soma dos efeitos | B19: R$ | E19: =SUM(E12:E16) | F19: =SUM(F12:F16) | G19: =SUM(G12:G16) | H19: =SUM(H12:H16) | I19: =SUM(I12:I16) | J19: =SUM(J12:J16) | K19: =SUM(K12:K16) | L19: =SUM(L12:L16) | M19: =SUM(M12:M16)
A20: CHECK — a ponte fecha? | E20: =IF(ABS(E19-E18)<0.01,"OK","ERRO") | F20: =IF(ABS(F19-F18)<0.01,"OK","ERRO") | G20: =IF(ABS(G19-G18)<0.01,"OK","ERRO") | H20: =IF(ABS(H19-H18)<0.01,"OK","ERRO") | I20: =IF(ABS(I19-I18)<0.01,"OK","ERRO") | J20: =IF(ABS(J19-J18)<0.01,"OK","ERRO") | K20: =IF(ABS(K19-K18)<0.01,"OK","ERRO") | L20: =IF(ABS(L19-L18)<0.01,"OK","ERRO") | M20: =IF(ABS(M19-M18)<0.01,"OK","ERRO")
A22: B. PONTE DE UM ANO — leitura de gestor
A23: Ano a destacar (2 a 10) | C23: 2
A24: Exercício | C24: =INDEX($C$8:$M$8,1,$C$23+1)
A25: EBITDA do ano anterior | C25: =INDEX($C$11:$M$11,1,$C$23+1)
A26: Volume | C26: =INDEX($C$12:$M$12,1,$C$23+1)
A27: Preço | C27: =INDEX($C$13:$M$13,1,$C$23+1)
A28: Mix | C28: =INDEX($C$14:$M$14,1,$C$23+1)
A29: Custo variável | C29: =INDEX($C$15:$M$15,1,$C$23+1)
A30: Custo fixo | C30: =INDEX($C$16:$M$16,1,$C$23+1)
A31: EBITDA do ano | C31: =INDEX($C$17:$M$17,1,$C$23+1)
A32: Δ EBITDA | C32: =INDEX($C$18:$M$18,1,$C$23+1)
A33: Δ EBITDA (%) | C33: =INDEX($C$18:$M$18,1,$C$23+1)/INDEX($C$11:$M$11,1,$C$23+1)
A35: C. CENÁRIO ATIVO CONTRA O CENÁRIO BASE (mesmo ano)
A36: Lê o cenário selecionado na aba 2. Inputs (C5) e compara com o Base. Com o cenário Base ativo, todos os efeitos são zero.
A37: EBITDA — cenário Base | C37: =INDEX('8. Motor de Cenarios'!$C$63:'8. Motor de Cenarios'!$M$63,1,$C$23+1)
A38: Efeito VOLUME | C38: =(INDEX('4. DRE'!$C$24:'4. DRE'!$M$24,1,$C$23+1)-INDEX('8. Motor de Cenarios'!$C$48:'8. Motor de Cenarios'!$M$48,1,$C$23+1))*((INDEX('8. Motor de Cenarios'!$C$62:'8. Motor de Cenarios'!$M$62,1,$C$23+1)/INDEX('8. Motor de Cenarios'!$C$48:'8. Motor de Cenarios'!$M$48,1,$C$23+1))-(INDEX('8. Motor de Cenarios'!$C$61:'8. Motor de Cenarios'!$M$61,1,$C$23+1)/INDEX('8. Motor de Cenarios'!$C$48:'8. Motor de Cenarios'!$M$48,1,$C$23+1))-INDEX('8. Motor de Cenarios'!$C$50:'8. Motor de Cenarios'!$M$50,1,$C$23+1)-INDEX('8. Motor de Cenarios'!$C$49:'8. Motor de Cenarios'!$M$49,1,$C$23+1))
A39: Efeito PREÇO | C39: =INDEX('4. DRE'!$C$24:'4. DRE'!$M$24,1,$C$23+1)*((INDEX('4. DRE'!$C$51:'4. DRE'!$M$51,1,$C$23+1)-INDEX('4. DRE'!$C$52:'4. DRE'!$M$52,1,$C$23+1))-((INDEX('8. Motor de Cenarios'!$C$62:'8. Motor de Cenarios'!$M$62,1,$C$23+1)/INDEX('8. Motor de Cenarios'!$C$48:'8. Motor de Cenarios'!$M$48,1,$C$23+1))-(INDEX('8. Motor de Cenarios'!$C$61:'8. Motor de Cenarios'!$M$61,1,$C$23+1)/INDEX('8. Motor de Cenarios'!$C$48:'8. Motor de Cenarios'!$M$48,1,$C$23+1))))
A40: Efeito MIX | C40: =INDEX('4. DRE'!$C$24:'4. DRE'!$M$24,1,$C$23+1)*(INDEX('8. Motor de Cenarios'!$C$49:'8. Motor de Cenarios'!$M$49,1,$C$23+1)-INDEX('4. DRE'!$C$54:'4. DRE'!$M$54,1,$C$23+1))
A41: Efeito CUSTO VARIÁVEL | C41: =INDEX('4. DRE'!$C$24:'4. DRE'!$M$24,1,$C$23+1)*(INDEX('8. Motor de Cenarios'!$C$50:'8. Motor de Cenarios'!$M$50,1,$C$23+1)-INDEX('4. DRE'!$C$53:'4. DRE'!$M$53,1,$C$23+1))
A42: Efeito CUSTO FIXO | C42: =-(INDEX('4. DRE'!$C$56:'4. DRE'!$M$56,1,$C$23+1)-(INDEX('8. Motor de Cenarios'!$C$54:'8. Motor de Cenarios'!$M$54,1,$C$23+1)+INDEX('8. Motor de Cenarios'!$C$55:'8. Motor de Cenarios'!$M$55,1,$C$23+1)+INDEX('8. Motor de Cenarios'!$C$56:'8. Motor de Cenarios'!$M$56,1,$C$23+1)))
A43: EBITDA — cenário ativo | C43: =INDEX('4. DRE'!$C$39:'4. DRE'!$M$39,1,$C$23+1)
A44: CHECK — a ponte fecha? | C44: =IF(ABS(SUM(C38:C42)-(C43-C37))<0.01,"OK","ERRO")
A46: D. COMENTÁRIO DE GESTOR (modelo — reescrever com o cenário que for apresentado)
A47: • O EBITDA do ano 2 cresce sobre o ano 1 movido por volume e por preço, nessa ordem. Volume é o balanço de massa da engenharia; preço é a margem-alvo, que sobe 2 p.p. por ano por premissa, não por estudo de mercado.
A48: • O efeito custo variável é sistematicamente negativo em reais e praticamente nulo por unidade: o custo variável unitário fica em torno de R$ 11,1 o ano inteiro. Nenhum ganho de escala foi modelado na matéria-prima — é uma oportunidade real de plano, não uma falha da planilha.
A49: • O efeito custo fixo é o mais confortável da ponte: a estrutura é quase toda herdada do CAPEX e não cresce com o volume. É o que faz a margem EBITDA subir de 35% para 56% ao longo do horizonte.
A50: • O efeito mix é irrelevante em base: 80% do volume já está no Sudeste e o frete é 0,4% do custo. A alavanca existe para o caso de a distribuição mudar, não porque ela explique o resultado de hoje.
A51: • O que essa ponte NÃO explica, e é onde eu colocaria a discussão: a margem-alvo de 43% no ano 10 e o crescimento de 10% ao ano de market share. Os dois vêm da premissa, não do dado. Tudo o mais no caso é engenharia verificável.

Sheet 10. Checks
A1: CHECKS DE AMARRAÇÃO
A2: Check escondido não é check. Se qualquer linha abaixo sair de OK, o modelo não sai da gaveta.
A4: VEREDITO | C4: =IF(COUNTIF(F7:F25,"OK")=19,"MODELO FECHA — 19 de 19 checks OK","ATENÇÃO: "&(19-COUNTIF(F7:F25,"OK"))&" de 19 checks NÃO estão OK")
A6: N° | B6: O que amarra | C6: Valor A | D6: Valor B | E6: Diferença | F6: Status | G6: Por que este check existe
A7: 1 | B7: Participações regionais somam 100% | C7: =SUM('2. Inputs'!D18:D22) | D7: =1 | E7: =C7-D7 | F7: =IF(ABS(C7-D7)<0.0000001,"OK","ERRO") | G7: Se o mix não fecha em 100%, o frete unitário ponderado está errado e o custo variável inteiro sai do lugar.
A8: 2 | B8: Ativos do ano 0 + terreno = CAPEX corrigido do ano 0 | C8: =SUMIF('3. Depreciacao'!$C$12:$C$18,0,'3. Depreciacao'!$D$12:$D$18)+'3. Depreciacao'!$D$20 | D8: ='2. Inputs'!C53 | E8: =C8-D8 | F8: =IF(ABS(C8-D8)<0.01,"OK","ERRO") | G8: Todo real investido no ano 0 tem de estar classificado em alguma vida útil — ou declarado como terreno. Foi exatamente aqui que a origem perdeu R$ 16.773.
A9: 3 | B9: Reinvestimentos no registro = CAPEX dos anos 1 a 10 | C9: =SUMIF('3. Depreciacao'!$C$12:$C$18,">0",'3. Depreciacao'!$D$12:$D$18) | D9: =SUM('2. Inputs'!D53:M53) | E9: =C9-D9 | F9: =IF(ABS(C9-D9)<0.01,"OK","ERRO") | G9: O defeito D3 da origem: reinvestimento que sai do caixa e nunca entra na base de depreciação.
A10: 4 | B10: Depreciação acumulada nunca passa da base depreciável | C10: ='3. Depreciacao'!M32 | D10: ='3. Depreciacao'!D19 | E10: =C10-D10 | F10: =IF(C10<=D10+0.01,"OK","ERRO") | G10: O defeito D2 da origem: depreciar 200% de um ativo de 5 anos ao longo de 10. Este check é Valor A <= Valor B.
A11: 5 | B11: DRE: receita bruta = volume x preço | C11: ='4. DRE'!D26 | D11: ='4. DRE'!D24*'4. DRE'!D25 | E11: =C11-D11 | F11: =IF(ABS(C11-D11)<0.01,"OK","ERRO") | G11: Amarra a linha de cima do resultado com os dois drivers que a geram.
A12: 6 | B12: DRE: custo total = CTU x volume | C12: ='4. DRE'!D18 | D12: ='4. DRE'!D19*'4. DRE'!D24 | E12: =C12-D12 | F12: =IF(ABS(C12-D12)<0.01,"OK","ERRO") | G12: Na origem o CTU estava DIGITADO e já não batia com o custo calculado: 15,323 contra 15,3406.
A13: 7 | B13: EBITDA = margem de contribuição − custos fixos | C13: ='4. DRE'!D39 | D13: ='4. DRE'!D34+'4. DRE'!D36+'4. DRE'!D37+'4. DRE'!D38 | E13: =C13-D13 | F13: =IF(ABS(C13-D13)<0.01,"OK","ERRO") | G13: Recalcula o EBITDA por outro caminho. Se os dois não baterem, alguma linha de custo entrou duas vezes ou nenhuma.
A14: 8 | B14: Sem dívida: NOPAT = lucro líquido | C14: ='5. Fluxo de Caixa'!D23 | D14: ='4. DRE'!D46 | E14: =C14-D14 | F14: =IF(ABS(C14-D14)<0.01,"OK","ERRO") | G14: O projeto é 100% equity. Se NOPAT e lucro líquido divergirem, apareceu um resultado financeiro que não deveria existir.
A15: 9 | B15: FCL = NOPAT + depreciação − ΔCG − CAPEX | C15: ='5. Fluxo de Caixa'!D28 | D15: ='5. Fluxo de Caixa'!D23+'3. Depreciacao'!D31-'5. Fluxo de Caixa'!D16-'2. Inputs'!D53 | E15: =C15-D15 | F15: =IF(ABS(C15-D15)<0.01,"OK","ERRO") | G15: A ponte entre resultado e caixa, recalculada célula a célula.
A16: 10 | B16: Capital de giro volta a zero no fim do horizonte | C16: =SUM('5. Fluxo de Caixa'!C16:M16)-'5. Fluxo de Caixa'!M15 | D16: =0 | E16: =C16-D16 | F16: =IF(ABS(C16-D16)<0.01,"OK","ERRO") | G16: Tudo que entrou em giro tem de sair no ano 10. Na origem isso acontecia por acidente, porque uma célula estava vazia.
A17: 11 | B17: VPL = soma do FCL descontado (recalculado) | C17: ='6. Valuation'!C18 | D17: =SUMPRODUCT('5. Fluxo de Caixa'!C28:M28,1/(1+'2. Inputs'!$C$81)^'5. Fluxo de Caixa'!C7:M7) | E17: =C17-D17 | F17: =IF(ABS(C17-D17)<0.01,"OK","ERRO") | G17: Recalcula o VPL por SOMARPRODUTO, sem passar pela linha de fatores de desconto.
A18: 12 | B18: TIR zera o VPL | C18: =SUMPRODUCT('5. Fluxo de Caixa'!C28:M28,1/(1+'6. Valuation'!C21)^'5. Fluxo de Caixa'!C7:M7) | D18: =0 | E18: =C18-D18 | F18: =IF(ABS(C18-D18)<0.01,"OK","ERRO") | G18: Definição de TIR. Se não zerar, a função pegou o intervalo errado.
A19: 13 | B19: Motor de cenários reproduz o VPL do modelo principal, no cenário ativo | C19: =INDEX('8. Motor de Cenarios'!$H$7:$H$9,'2. Inputs'!$C$5) | D19: ='6. Valuation'!C18 | E19: =C19-D19 | F19: =IF(ABS(C19-D19)<0.01,"OK","ERRO") | G19: A camada de cenários é uma segunda implementação do mesmo modelo, escrita com outras fórmulas e sem passar por nenhuma aba intermediária. Se as duas não coincidirem, uma das duas está errada.
A20: 14 | B20: Motor de cenários reproduz o EBITDA do ano 1, no cenário ativo | C20: =INDEX('8. Motor de Cenarios'!$J$7:$J$9,'2. Inputs'!$C$5) | D20: ='4. DRE'!D39 | E20: =C20-D20 | F20: =IF(ABS(C20-D20)<0.01,"OK","ERRO") | G20: Mesmo raciocínio do check anterior, um nível acima do fluxo de caixa: pega erro de custo ou de preço que o VPL poderia compensar.
A21: 15 | B21: Ponte de EBITDA fecha em todos os anos | C21: =COUNTIF('9. Ponte EBITDA'!E20:M20,"ERRO") | D21: =0 | E21: =C21-D21 | F21: =IF(ABS(C21-D21)<0.0000001,"OK","ERRO") | G21: A decomposição volume x preço x mix x custo tem de somar exatamente o ΔEBITDA. Ponte que não fecha é ponte inventada.
A22: 16 | B22: Ponte de VPL (origem -> modelo) fecha | C22: =IF('6. Valuation'!C41="OK",0,1) | D22: =0 | E22: =C22-D22 | F22: =IF(ABS(C22-D22)<0.0000001,"OK","ERRO") | G22: A ponte entre o VPL da planilha de faculdade e o VPL deste modelo tem de explicar o valor inteiro.
A23: 17 | B23: Margem de contribuição unitária positiva em todos os anos | C23: =COUNTIF('4. DRE'!D55:M55,"<=0") | D23: =0 | E23: =C23-D23 | F23: =IF(ABS(C23-D23)<0.0000001,"OK","ERRO") | G23: Se em algum ano o preço não cobre o custo variável, vender mais piora o resultado — e todo o raciocínio de volume desaba.
A24: 18 | B24: Imposto zero quando o EBIT é negativo | C24: =SUMPRODUCT(('4. DRE'!D42:M42<0)*('4. DRE'!D44:M44<0)) | D24: =0 | E24: =C24-D24 | F24: =IF(ABS(C24-D24)<0.0000001,"OK","ERRO") | G24: A fórmula da origem, (lucro-240000)*0,1, gerava crédito de imposto sobre prejuízo. Aqui não pode acontecer.
A25: 19 | B25: Payback descontado: motor de cenários = aba Valuation | C25: =INDEX('8. Motor de Cenarios'!$M$7:$M$9,'2. Inputs'!$C$5) | D25: ='6. Valuation'!C24 | E25: =IFERROR(C25-D25,0) | F25: =IFERROR(IF(ABS(C25-D25)<0.01,"OK","ERRO"),IF(C25=D25,"OK","ERRO")) | G25: O motor descontava o acumulado e dividia pelo fluxo do ano SEM descontar — dois paybacks diferentes para o mesmo cenário. Este check amarra as duas implementações, como os checks 13 e 14 fazem com VPL e EBITDA.
